Workbook

Sheet Drop Down Lists
A1: PERF | B1: MECH | C1: Territories
A2: ABRAMUS | B2: ABRAMUS | C2: Argentina
A3: AKM-AUME | B3: AKM-AUME | C3: Australia
A4: AMRA | B4: AMRA | C4: Austria
A5: APDAYC | B5: APDAYC | C5: Belgium
A6: APRA-AMCOS | B6: APRA-AMCOS | C6: Bolivia
A7: ASCAP | B7: ASCAP | C7: Brazil
A8: BMI | B8: BMI | C8: Canada
A9: BUMA | B9: BUMA | C9: Chile
A10: CASH | B10: CASH | C10: China
A11: COMPASS | B11: COMPASS | C11: Colombia
A12: GEMA | B12: GEMA | C12: Costa Rica
... A31: SUISA | B31: SUISA | C31: Peru
C32: Philippines
C33: Poland
C34: Portugal
C35: Russia
C36: Singapore
C37: South Africa
C38: South Korea
C39: Spain
C40: Sweden
C41: Switzerland
C42: Taiwan
C43: Thailand
... C49: Vietnam

Sheet MATRIX CALCULATOR
G1: PERFORMANCE | K1: MECHANICAL
B2: Last updated 29/07/2024
B3: PERF AFFILIATION | D3: USAGE TERRITORY | G3: ONLINE - MULTI-TERRITORY (eg. Spotify, Apple Music, YouTube etc...) | K3: ONLINE - MULTI-TERRITORY (eg. Spotify, Apple Music, YouTube etc...)
G4: LICENSED BY: | H4: LICENSOR PAYS: | I4: KOBALT PAID BY: | K4: LICENSED BY: | L4: LICENSOR PAYS: | M4: KOBALT PAID BY:
B5: SOCAN | D5: United Kingdom | G5: {=INDEX('Licensed By Table'!C2:AX35,MATCH(B5,'Licensed By Table'!A2:A35,0),MATCH(D5,'Licensed By Table'!C1:AX1,0))} -> AMRA | H5: {=INDEX('Licensor Pays Table'!C2:AX35,MATCH(B5,'Licensor Pays Table'!A2:A35,0),MATCH(D5,'Licensor Pays Table'!C1:AX1,0))} -> AMRA | I5: {=INDEX('Paid By Table'!C2:AX35, MATCH(B5,'Paid By Table'!A2:A35,0),MATCH(D5,'Paid By Table'!C1:AX1,0))} -> AMRA | K5: {=INDEX('MECH - Licensed By'!C2:AX35,MATCH(B8,'MECH - Licensed By'!A2:A35,0),MATCH(D5,'MECH - Licensed By'!C1:AX1,0))} -> ICE | L5: {=INDEX('MECH - Licensor Pays'!C2:AX35,MATCH(B8,'MECH - Licensor Pays'!A2:A35,0),MATCH(D5,'MECH - Licensor Pays'!C1:AX1,0))} -> AUME | M5: {=INDEX('MECH - Paid By'!C2:AX35, MATCH(B8,'MECH - Paid By'!A2:A35,0),MATCH(D5,'MECH - Paid By'!C1:AX1,0))} -> MCPS-PRS
B6: MECH AFFILIATION | D6: # | G6: =IF(D6=TRUE,"PLEASE NOTE ALL INCOME FOR EUROPE IS PAID DIRECT TO KOBALT FROM WRITER'S AFFILIATED SOCIETY","")
B8: AKM-AUME | G8: ONLINE - AV (eg. Netflix, Amazon Prime Video...) | K8: ONLINE - AV (eg. Netflix, Amazon Prime Video...)
G9: LICENSED BY: | H9: LICENSOR PAYS: | I9: KOBALT PAID BY: | K9: LICENSED BY: | L9: LICENSOR PAYS: | M9: KOBALT PAID BY:
B10: LICENSING & REVENUE PIPELINE MATRIX | G10: =VLOOKUP($D$5,'Offline Matrix'!A:E,2,false) -> PRS | H10: =VLOOKUP($D$5,'Offline Matrix'!A:E,4,false) -> PRS | I10: =H10 -> PRS | K10: =VLOOKUP($D$5,'Offline Matrix'!A:E,3,false) -> MCPS | L10: =VLOOKUP($D$5,'Offline Matrix'!A:E,5,false) -> MCPS | M10: =L10 -> MCPS
G12: ONLINE - Local (Available in single territory) | K12: ONLINE - Local (Available in single territory)
G13: LICENSED BY: | H13: LICENSOR PAYS: | I13: KOBALT PAID BY: | K13: LICENSED BY: | L13: LICENSOR PAYS: | M13: KOBALT PAID BY:
G14: =VLOOKUP($D$5,'Offline Matrix'!A:E,2,false) -> PRS | H14: =VLOOKUP($D$5,'Offline Matrix'!A:E,4,false) -> PRS | I14: =H14 -> PRS | K14: =VLOOKUP($D$5,'Offline Matrix'!A:E,3,false) -> MCPS | L14: =VLOOKUP($D$5,'Offline Matrix'!A:E,5,false) -> MCPS | M14: =L14 -> MCPS
G16: BROADCAST - TV | K16: BROADCAST - TV
H17: LICENSOR PAYS: | I17: KOBALT PAID BY: | K17: LICENSED BY: | L17: LICENSOR PAYS: | M17: KOBALT PAID BY:
G18: =VLOOKUP($D$5,'Offline Matrix'!A:E,2,false) -> PRS | H18: =VLOOKUP($D$5,'Offline Matrix'!A:E,4,false) -> PRS | I18: =H18 -> PRS | K18: =VLOOKUP($D$5,'Offline Matrix'!A:E,3,false) -> MCPS | L18: =VLOOKUP($D$5,'Offline Matrix'!A:E,5,false) -> MCPS | M18: =L18 -> MCPS
G20: BROADCAST - RADIO | K20: BROADCAST - RADIO
G21: LICENSED BY: | H21: LICENSOR PAYS: | I21: KOBALT PAID BY: | K21: LICENSED BY: | L21: LICENSOR PAYS: | M21: KOBALT PAID BY:
G22: =VLOOKUP($D$5,'Offline Matrix'!A:E,2,false) -> PRS | H22: =VLOOKUP($D$5,'Offline Matrix'!A:E,4,false) -> PRS | I22: =H22 -> PRS | K22: =VLOOKUP($D$5,'Offline Matrix'!A:E,3,false) -> MCPS | L22: =VLOOKUP($D$5,'Offline Matrix'!A:E,5,false) -> MCPS | M22: =L22 -> MCPS
G24: PUBLIC PERFORMANCE - LIVE | K24: MECHANICAL REPRODUCTION
G25: LICENSED BY: | H25: LICENSOR PAYS: | I25: KOBALT PAID BY: | K25: LICENSED BY: | L25: LICENSOR PAYS: | M25: KOBALT PAID BY:
G26: =VLOOKUP($D$5,'Offline Matrix'!A:E,2,false) -> PRS | H26: =VLOOKUP($D$5,'Offline Matrix'!A:E,4,false) -> PRS | I26: =H26 -> PRS | K26: =IF($D$5="United States","Major Label / HFA ", IF(OR(D5 = "China",D5= "Hong Kong", D5 = "Thailand", D5 = "Philippines", D5 = "Singapore"),"Varies Consult Source Owner",VLOOKUP($D$5,'Offline Matrix'!A:E,3,false))) -> MCPS | L26: =IF($D$5="United States","Major Label / HFA",IF(OR(D5 = "China",D5= "Hong Kong", D5 = "Thailand", D5 = "Philippines", D5 = "Singapore"),"Varies Consult Source Owner", VLOOKUP($D$5,'Offline Matrix'!A:E,5,false))) -> MCPS | M26: =L26 -> MCPS
G28: PUBLIC PERFORMANCE - CINEMA
G29: LICENSED BY: | H29: LICENSOR PAYS: | I29: KOBALT PAID BY:
G30: =IF($D$5="United States","Not Licensed",VLOOKUP($D$5,'Offline Matrix'!A:E,2,FALSE)) -> PRS | H30: =IF($D$5="United States","Not Licensed",VLOOKUP($D$5,'Offline Matrix'!A:E,4,false)) -> PRS | I30: =H30 -> PRS
G32: PUBLIC PERFORMANCE - LICENSED PREMESES
G33: LICENSED BY: | H33: LICENSOR PAYS: | I33: KOBALT PAID BY:
G34: =VLOOKUP($D$5,'Offline Matrix'!A:E,2,false) -> PRS | H34: =VLOOKUP($D$5,'Offline Matrix'!A:E,4,false) -> PRS | I34: =H34 -> PRS

Sheet Matrix - PERF
A1: Licensed By: How our pub share is licensed Licensor Pays: First society income is paid to Kobalt Paid By: Pub share payment made to Kobalt | D1: PERFORMANCE INCOME - NOT INCLUDED IN DL
D2: EUROPE | W2: US / Canada | Y2: Latin America | AJ2: Australasia | AL2: Asia | AX2: Africa
A3: BIEM Rep (Example: 1 Writer -> Kobalt) | B3: SOCIETY | D3: Austria | E3: Belgium | F3: France | G3: Germany | H3: Italy | I3: Netherlands | J3: Nordics Finland / Norway / Iceland, etc) | K3: Portugal | L3: Spain | M3: Sweden | N3: Switzerland | O3: United Kingdom | P3: Croatia | Q3: Greece | R3: Poland | S3: Russia | T3: Israel | U3: UAE | V3: Turkey | W3: Canada | X3: United States | Y3: Argentina | Z3: Bolivia | AA3: Brazil | AB3: Chile | AC3: Colombia | AD3: Costa Rica | AE3: Ecuador | AF3: Mexico | AG3: Paraguay | AH3: Peru | AI3: Uruguay | AJ3: Australia | AK3: New Zealand | AL3: China | AM3: HongKong | AN3: India | AO3: Japan | AP3: Malaysia | AQ3: Philippines | AR3: Vietnam | AS3: Thailand | AT3: Singapore | AU3: South Korea | AV3: Indonesia | AW3: Taiwan | AX3: South Africa | AY3: North Africa
A4: AKM-AUME | B4: AKM-AUME | C4: Licensed By | D4: AKM | E4: ICE | F4: ICE | G4: ICE | H4: ICE | I4: ICE | J4: ICE | K4: ICE | L4: ICE | M4: ICE | N4: ICE | O4: ICE | P4: ICE | Q4: ICE | R4: ICE | S4: RAO | T4: ACUM | U4: ESMAA | V4: MSG | W4: SOCAN | X4: ASCAP/BMI/SESAC/GMR | Y4: SADAIC | Z4: Latin Autor | AA4: ECAD | AB4: Latin Autor | AC4: Latin Autor | AD4: Latin Autor | AE4: Latin Autor | AF4: SACM | AG4: Latin Autor | AH4: Latin Autor | AI4: Latin Autor | AJ4: APRA-AMCOS | AK4: APRA-AMCOS | AL4: MCSC | AM4: CASH | AO4: JASRAC | AP4: MACP | AQ4: FILSCAP | AR4: VCPMC | AS4: MCT | AT4: COMPASS | AU4: KOMCA | AW4: MUST | AX4: SAMRO | AY4: ICE
B5: AKM-AUME | C5: Licensor Pays | D5: AKM | E5: SABAM | F5: SACEM | G5: GEMA | H5: SIAE | I5: BUMA | J5: STIM | K5: SPA | L5: SGAE | M5: STIM | N5: SUISA | O5: MCPS-PRS | P5: HDS-ZAMP | Q5: AUTODIA | R5: ZAIKS | S5: Blue Sun | T5: Dalia | U5: Pop Arabia | V5: Zeplin | W5: SOCAN | X5: ASCAP/BMI/SESAC/GMR | Y5: SADAIC | Z5: Latin Autor (Processed by BO) | AA5: ECAD | AB5: Latin Autor (Processed by BO) | AC5: Latin Autor (Processed by BO) | AD5: Latin Autor (Processed by BO) | AE5: Latin Autor (Processed by BO) | AF5: SACM | AG5: Latin Autor (Processed by BO) | AH5: Latin Autor (Processed by BO) | AI5: Latin Autor (Processed by BO) | AJ5: APRA-AMCOS | AK5: APRA-AMCOS | AL5: MCSC | AM5: CASH | AO5: JASRAC | AP5: MACP | AQ5: FILSCAP | AR5: VCPMC | AS5: MCT | AT5: COMPASS | AU5: KOMCA | AW5: MUST | AX5: SAMRO | AY5: AKM
B6: AKM-AUME | C6: Kobalt Paid By | D6: AKM | E6: SABAM | F6: SACEM | G6: GEMA | H6: SIAE | I6: BUMA | J6: STIM | K6: SPA | L6: SGAE | M6: STIM | N6: SUISA | O6: MCPS-PRS | P6: IDM | Q6: D-Version | R6: Schubert | S6: Blue Sun | T6: Dalia | U6: Pop Arabia | V6: Zeplin | W6: SOCAN | X6: ASCAP/BMI/SESAC/GMR | Y6: SADAIC | Z6: No Membership | AA6: ABRAMUS | AB6: SCD | AC6: SAYCO | AD6: Briana Music | AE6: SAYCE | AF6: SACM | AG6: No Membership | AH6: APDAYC | AI6: AGADU | AJ6: APRA-AMCOS | AK6: APRA-AMCOS | AL6: CASH | AM6: CASH | AO6: SMPJ | AP6: Indie Works | AQ6: COMPASS | AR6: COMPASS | AS6: COMPASS | AT6: COMPASS | AU6: EKKO | AW6: One Asia | AX6: SAMRO | AY6: SACEM
A7: BUMA-STEMRA | B7: BUMA-STEMRA | C7: Licensed By | D7: BUMA | E7: BUMA | F7: BUMA | G7: BUMA | H7: BUMA | I7: BUMA | J7: BUMA | K7: BUMA | L7: BUMA | M7: BUMA | N7: BUMA | O7: BUMA | P7: BUMA | Q7: BUMA | R7: BUMA | S7: RAO | T7: ACUM | U7: ESMAA | V7: MSG | W7: SOCAN | X7: ASCAP/BMI/SESAC/GMR | Y7: SADAIC | Z7: Latin Autor | AA7: ECAD | AB7: Latin Autor | AC7: Latin Autor | AD7: Latin Autor | AE7: Latin Autor | AF7: SACM | AG7: Latin Autor | AH7: Latin Autor | AI7: Latin Autor | AJ7: APRA-AMCOS | AK7: APRA-AMCOS | AL7: MCSC | AM7: APRA-AMCOS | AN7: APRA-AMCOS | AO7: APRA-AMCOS | AP7: APRA-AMCOS | AQ7: APRA-AMCOS | AR7: APRA-AMCOS | AS7: APRA-AMCOS | AT7: APRA-AMCOS | AU7: KOMCA | AV7: APRA-AMCOS | AW7: APRA-AMCOS | AX7: SAMRO | AY7: BUMA
B8: BUMA-STEMRA | C8: Licensor Pays | D8: BUMA | E8: BUMA | F8: BUMA | G8: BUMA | H8: BUMA | I8: BUMA | J8: BUMA | K8: BUMA | L8: BUMA | M8: BUMA | N8: BUMA | O8: BUMA | P8: BUMA | Q8: BUMA | R8: BUMA | S8: Blue Sun | T8: Dalia | U8: Pop Arabia | V8: Zeplin | W8: SOCAN | X8: ASCAP/BMI/SESAC/GMR | Y8: SADAIC | Z8: Latin Autor (Processed by BO) | AA8: ECAD | AB8: Latin Autor (Processed by BO) | AC8: Latin Autor (Processed by BO) | AD8: Latin Autor (Processed by BO) | AE8: Latin Autor (Processed by BO) | AF8: SACM | AG8: Latin Autor (Processed by BO) | AH8: Latin Autor (Processed by BO) | AI8: Latin Autor (Processed by BO) | AJ8: APRA-AMCOS | AK8: APRA-AMCOS | AL8: MCSC | AM8: BUMA | AN8: BUMA | AO8: BUMA | AP8: BUMA | AQ8: BUMA | AR8: BUMA | AS8: BUMA | AT8: BUMA | AU8: KOMCA | AV8: BUMA | AW8: BUMA | AX8: SAMRO | AY8: BUMA
B9: BUMA-STEMRA | C9: Kobalt Paid By | D9: AKM | E9: SABAM | F9: SACEM | G9: GEMA | H9: SIAE | I9: BUMA | J9: Nordic Sources | K9: SPA | L9: SGAE | M9: STIM | N9: SUISA | O9: MCPS-PRS | P9: IDM | Q9: D-Version | R9: Schubert | S9: Blue Sun | T9: Dalia | U9: Pop Arabia | V9: Zeplin | W9: SOCAN | X9: ASCAP/BMI/SESAC/GMR | Y9: SADAIC | Z9: No Membership | AA9: ABRAMUS | AB9: SCD | AC9: SAYCO | AD9: Briana Music | AE9: SAYCE | AF9: SACM | AG9: No Membership | AH9: APDAYC | AI9: AGADU | AJ9: APRA-AMCOS | AK9: APRA-AMCOS | AL9: CASH | AM9: CASH | AN9: Turnkey | AO9: SMPJ | AP9: Indie Works | AQ9: STIM | AR9: STIM | AS9: STIM | AT9: STIM | AU9: EKKO | AV9: PT Nadaku | AW9: One Asia | AX9: SAMRO | AY9: BUMA
A10: GEMA | B10: GEMA | C10: Licensed By | D10: ICE | E10: ICE | F10: ICE | G10: GEMA | H10: ICE | I10: ICE | J10: ICE | K10: ICE | L10: ICE | M10: ICE | N10: ICE | O10: ICE | P10: ICE | Q10: ICE | R10: ICE | S10: RAO | T10: ACUM | U10: ESMAA | V10: MSG | W10: SOCAN | X10: ASCAP/BMI/SESAC/GMR | Y10: SADAIC | Z10: Latin Autor | AA10: ECAD | AB10: SCD | AC10: SAYCO | AD10: Latin Autor | AE10: Latin Autor | AF10: SACM | AG10: Latin Autor | AH10: APDAYC | AI10: Latin Autor | AJ10: APRA-AMCOS | AK10: APRA-AMCOS | AL10: MCSC | AM10: CASH | AN10: IPRS | AO10: JASRAC | AP10: MACP | AQ10: FILSCAP | AR10: VCPMC | AS10: MCT | AT10: COMPASS | AU10: KOMCA | AV10: WAMI | AW10: MUST | AX10: SAMRO | AY10: ICE
B11: GEMA | C11: Licensor Pays | D11: AKM | E11: SABAM | F11: SACEM | G11: GEMA | H11: SIAE | I11: BUMA | J11: Nordic Sources | K11: SPA | L11: SGAE | M11: STIM | N11: SUISA | O11: MCPS-PRS | P11: HDS-ZAMP | Q11: GEMA | R11: ZAIKS | S11: Blue Sun | T11: Dalia | U11: Pop Arabia | V11: Zeplin | W11: SOCAN | X11: ASCAP/BMI/SESAC/GMR | Y11: SADAIC | Z11: Latin Autor (Processed by BO) | AA11: ECAD | AB11: SCD | AC11: SAYCO | AD11: Latin Autor (Processed by BO) | AE11: Latin Autor (Processed by BO) | AF11: SACM | AG11: Latin Autor (Processed by BO) | AH11: APDAYC | AI11: Latin Autor (Processed by BO) | AJ11: APRA-AMCOS | AK11: APRA-AMCOS | AL11: MCSC | AM11: CASH | AN11: IPRS | AO11: JASRAC | AP11: MACP | AQ11: FILSCAP | AR11: VCPMC | AS11: MCT | AT11: COMPASS | AU11: KOMCA | AV11: WAMI | AW11: MUST | AX11: SAMRO | AY11: GEMA
B12: GEMA | C12: Kobalt Paid By | D12: AKM | E12: SABAM | F12: SACEM | G12: GEMA | H12: SIAE | I12: BUMA | J12: Nordic Sources | K12: SPA | L12: SGAE | M12: STIM | N12: SUISA | O12: MCPS-PRS | P12: IDM | Q12: D-Version | R12: Schubert | S12: Blue Sun | T12: Dalia | U12: Pop Arabia | V12: Zeplin | W12: SOCAN | X12: ASCAP/BMI/SESAC/GMR | Y12: SADAIC | Z12: No Membership | AA12: ABRAMUS | AB12: SCD | AC12: SAYCO | AD12: Briana Music | AE12: SAYCE | AF12: SACM | AG12: No Membership | AH12: APDAYC | AI12: AGADU | AJ12: APRA-AMCOS | AK12: APRA-AMCOS | AL12: CASH | AM12: CASH | AN12: Turnkey | AO12: SMPJ | AP12: Indie Works | AQ12: COMPASS | AR12: COMPASS | AS12: COMPASS | AT12: COMPASS | AU12: EKKO | AV12: PT Nadaku | AW12: One Asia | AX12: SAMRO | AY12: GEMA
A13: SABAM | B13: SABAM | C13: Licensed By | D13: ICE | E13: ICE | F13: ICE | G13: ICE | H13: ICE | I13: ICE | J13: ICE | K13: ICE | L13: ICE | M13: ICE | N13: ICE | O13: ICE | P13: ICE | Q13: ICE | R13: ICE | S13: RAO | T13: ACUM | U13: ESMAA | V13: MSG | W13: SOCAN | X13: ASCAP/BMI/SESAC/GMR | Y13: SADAIC | Z13: Latin Autor | AA13: ECAD | AB13: Latin Autor | AC13: Latin Autor | AD13: Latin Autor | AE13: Latin Autor | AF13: SACM | AG13: Latin Autor | AH13: Latin Autor | AI13: Latin Autor | AJ13: APRA-AMCOS | AK13: APRA-AMCOS | AL13: MCSC | AM13: CASH | AN13: IPRS | AO13: JASRAC | AP13: MACP | AQ13: FILSCAP | AR13: VCPMC | AS13: MCT | AT13: COMPASS | AU13: KOMCA | AV13: WAMI | AW13: MUST | AX13: SAMRO | AY13: ICE
B14: SABAM | C14: Licensor Pays | D14: SABAM | E14: SABAM | F14: SABAM | G14: SABAM | H14: SABAM | I14: SABAM | J14: SABAM | K14: SABAM | L14: SABAM | M14: SABAM | N14: SABAM | O14: SABAM | P14: SABAM | Q14: SABAM | R14: SABAM | S14: Blue Sun | T14: Dalia | U14: Pop Arabia | V14: Zeplin | W14: SOCAN | X14: ASCAP/BMI/SESAC/GMR | Y14: SADAIC | Z14: Latin Autor (Processed by BO) | AA14: ECAD | AB14: Latin Autor (Processed by BO) | AC14: Latin Autor (Processed by BO) | AD14: Latin Autor (Processed by BO) | AE14: Latin Autor (Processed by BO) | AF14: SACM | AG14: Latin Autor (Processed by BO) | AH14: Latin Autor (Processed by BO) | AI14: Latin Autor (Processed by BO) | AJ14: APRA-AMCOS | AK14: APRA-AMCOS | AL14: MCSC | AM14: CASH | AN14: IPRS | AO14: JASRAC | AP14: MACP | AQ14: FILSCAP | AR14: VCPMC | AS14: MCT | AT14: COMPASS | AU14: KOMCA | AV14: WAMI | AW14: MUST | AX14: SAMRO | AY14: SABAM
B15: SABAM | C15: Kobalt Paid By | D15: AKM | E15: SABAM | F15: SACEM | G15: GEMA | H15: SIAE | I15: BUMA | J15: Nordic Sources | K15: SPA | L15: SGAE | M15: STIM | N15: SUISA | O15: MCPS-PRS | P15: IDM | Q15: D-Version | R15: Schubert | S15: Blue Sun | T15: Dalia | U15: Pop Arabia | V15: Zeplin | W15: SOCAN | X15: ASCAP/BMI/SESAC/GMR | Y15: SADAIC | Z15: No Membership | AA15: ABRAMUS | AB15: SCD | AC15: SAYCO | AD15: Briana Music | AE15: SAYCE | AF15: SACM | AG15: No Membership | AH15: APDAYC | AI15: AGADU | AJ15: APRA-AMCOS | AK15: APRA-AMCOS | AL15: CASH | AM15: CASH | AN15: Turnkey | AO15: SMPJ | AP15: Indie Works | AQ15: COMPASS | AR15: COMPASS | AS15: COMPASS | AT15: COMPASS | AU15: EKKO | AV15: PT Nadaku | AW15: One Asia | AX15: SAMRO | AY15: SACEM
A16: SACEM | B16: SACEM | C16: Licensed By | D16: SACEM | E16: SACEM | F16: SACEM | G16: SACEM | H16: SACEM | I16: SACEM | J16: SACEM | K16: SACEM | L16: SACEM | M16: SACEM | N16: SACEM | O16: SACEM | P16: SACEM | Q16: SACEM | R16: SACEM | S16: RAO | T16: ACUM | U16: ESMAA | V16: MSG | W16: SOCAN | X16: ASCAP/BMI/SESAC/GMR | Y16: SADAIC | Z16: Latin Autor | AA16: ECAD | AB16: Latin Autor | AC16: Latin Autor | AD16: Latin Autor | AE16: Latin Autor | AF16: SACM | AG16: Latin Autor | AH16: Latin Autor | AI16: Latin Autor | AJ16: APRA-AMCOS | AK16: APRA-AMCOS | AL16: QUERY SOURCE/ TERR OWNER | AM16: QUERY SOURCE/ TERR OWNER | AN16: QUERY SOURCE/ TERR OWNER | AO16: QUERY SOURCE/ TERR OWNER | AP16: QUERY SOURCE/ TERR OWNER | AQ16: QUERY SOURCE/ TERR OWNER | AR16: QUERY SOURCE/ TERR OWNER | AS16: QUERY SOURCE/ TERR OWNER | AT16: QUERY SOURCE/ TERR OWNER | AU16: QUERY SOURCE/ TERR OWNER | AV16: QUERY SOURCE/ TERR OWNER | AW16: QUERY SOURCE/ TERR OWNER | AX16: SAMRO | AY16: SACEM
B17: SACEM | C17: Licensor Pays | D17: SACEM | E17: SACEM | F17: SACEM | G17: SACEM | H17: SACEM | I17: SACEM | J17: SACEM | K17: SACEM | L17: SACEM | M17: SACEM | N17: SACEM | O17: SACEM | P17: SACEM | Q17: SACEM | R17: SACEM | S17: Blue Sun | T17: Dalia | U17: Pop Arabia | V17: Zeplin | W17: SOCAN | X17: ASCAP/BMI/SESAC/GMR | Y17: SADAIC | Z17: Latin Autor (Processed by BO) | AA17: ECAD | AB17: Latin Autor (Processed by BO) | AC17: Latin Autor (Processed by BO) | AD17: Latin Autor (Processed by BO) | AE17: Latin Autor (Processed by BO) | AF17: SACM | AG17: Latin Autor (Processed by BO) | AH17: Latin Autor (Processed by BO) | AI17: Latin Autor (Processed by BO) | AJ17: APRA-AMCOS | AK17: APRA-AMCOS | AL17: QUERY SOURCE/ TERR OWNER | AM17: QUERY SOURCE/ TERR OWNER | AN17: QUERY SOURCE/ TERR OWNER | AO17: QUERY SOURCE/ TERR OWNER | AP17: QUERY SOURCE/ TERR OWNER | AQ17: QUERY SOURCE/ TERR OWNER | AR17: QUERY SOURCE/ TERR OWNER | AS17: QUERY SOURCE/ TERR OWNER | AT17: QUERY SOURCE/ TERR OWNER | AU17: QUERY SOURCE/ TERR OWNER | AV17: QUERY SOURCE/ TERR OWNER | AW17: QUERY SOURCE/ TERR OWNER | AX17: SAMRO | AY17: SACEM
B18: SACEM | C18: Kobalt Paid By | D18: SACEM | E18: SACEM | F18: SACEM | G18: SACEM | H18: SACEM | I18: SACEM | J18: SACEM | K18: SACEM | L18: SACEM | M18: SACEM | N18: SACEM | O18: SACEM | P18: SACEM | Q18: SACEM | R18: SACEM | S18: Blue Sun | T18: Dalia | U18: Pop Arabia | V18: Zeplin | W18: SOCAN | X18: ASCAP/BMI/SESAC/GMR | Y18: SADAIC | Z18: No Membership | AA18: ABRAMUS | AB18: SCD | AC18: SAYCO | AD18: Briana Music | AE18: SAYCE | AF18: SACM | AG18: No Membership | AH18: APDAYC | AI18: AGADU | AJ18: APRA-AMCOS | AK18: APRA-AMCOS | AL18: QUERY SOURCE/ TERR OWNER | AM18: QUERY SOURCE/ TERR OWNER | AN18: QUERY SOURCE/ TERR OWNER | AO18: QUERY SOURCE/ TERR OWNER | AP18: QUERY SOURCE/ TERR OWNER | AQ18: QUERY SOURCE/ TERR OWNER | AR18: QUERY SOURCE/ TERR OWNER | AS18: QUERY SOURCE/ TERR OWNER | AT18: QUERY SOURCE/ TERR OWNER | AU18: QUERY SOURCE/ TERR OWNER | AV18: QUERY SOURCE/ TERR OWNER | AW18: QUERY SOURCE/ TERR OWNER | AX18: SAMRO | AY18: SACEM
A19: SGAE | B19: SGAE | C19: Licensed By | D19: AKM | E19: SABAM | F19: SACEM | G19: GEMA | H19: SIAE | I19: BUMA | J19: Nordic Sources | K19: SPA | L19: SGAE | M19: STIM | N19: SUISA | O19: MCPS-PRS | P19: HDS-ZAMP | Q19: AUTODIA | R19: ZAIKS | S19: RAO | T19: ACUM | U19: ESMAA | V19: MSG | W19: SOCAN | X19: ASCAP/BMI/SESAC/GMR | Y19: SADAIC | Z19: Latin Autor | AA19: ECAD | AB19: Latin Autor | AC19: Latin Autor | AD19: Latin Autor | AE19: Latin Autor | AF19: SACM | AG19: Latin Autor | AH19: Latin Autor | AI19: Latin Autor | AJ19: APRA-AMCOS | AK19: APRA-AMCOS | AL19: MCSC | AM19: CASH | AN19: IPRS | AO19: JASRAC | AP19: MACP | AQ19: FILSCAP | AR19: VCPMC | AS19: MCT | AT19: COMPASS | AU19: KOMCA | AV19: WAMI | AW19: MUST | AX19: SAMRO
B20: SGAE | C20: Licensor Pays | D20: AKM | E20: SABAM | F20: SACEM | G20: GEMA | H20: SIAE | I20: BUMA | J20: Nordic Sources | K20: SPA | L20: SGAE | M20: STIM | N20: SUISA | O20: MCPS-PRS | P20: IDM | Q20: D-Version | R20: Schubert | S20: Blue Sun | T20: Dalia | U20: Pop Arabia | V20: Zeplin | W20: SOCAN | X20: ASCAP/BMI/SESAC/GMR | Y20: SADAIC | Z20: Latin Autor (Processed by BO) | AA20: ECAD | AB20: Latin Autor (Processed by BO) | AC20: Latin Autor (Processed by BO) | AD20: Latin Autor (Processed by BO) | AE20: Latin Autor (Processed by BO) | AF20: SACM | AG20: Latin Autor (Processed by BO) | AH20: Latin Autor (Processed by BO) | AI20: Latin Autor (Processed by BO) | AJ20: APRA-AMCOS | AK20: APRA-AMCOS | AL20: MCSC | AM20: CASH | AN20: IPRS | AO20: JASRAC | AP20: MACP | AQ20: FILSCAP | AR20: VCPMC | AS20: MCT | AT20: COMPASS | AU20: KOMCA | AV20: WAMI | AW20: MUST | AX20: SAMRO
B21: SGAE | C21: Kobalt Paid By | D21: AKM | E21: SABAM | F21: SACEM | G21: GEMA | H21: SIAE | I21: BUMA | J21: Nordic Sources | K21: SPA | L21: SGAE | M21: STIM | N21: SUISA | O21: MCPS-PRS | P21: IDM | Q21: D-Version | R21: Schubert | S21: Blue Sun | T21: Dalia | U21: Pop Arabia | V21: Zeplin | W21: SOCAN | X21: ASCAP/BMI/SESAC/GMR | Y21: SADAIC | Z21: No Membership | AA21: ABRAMUS | AB21: SCD | AC21: SAYCO | AD21: Briana Music | AE21: SAYCE | AF21: SACM | AG21: No Membership | AH21: APDAYC | AI21: AGADU | AJ21: APRA-AMCOS | AK21: APRA-AMCOS | AL21: CASH | AM21: CASH | AN21: Turnkey | AO21: SMPJ | AP21: Indie Works | AQ21: COMPASS | AR21: COMPASS | AS21: COMPASS | AT21: COMPASS | AU21: EKKO | AV21: PT Nadaku | AW21: One Asia | AX21: SAMRO
A22: SIAE | B22: SIAE | C22: Licensed By | D22: AKM | E22: SABAM | F22: SACEM | G22: GEMA | H22: SIAE | I22: BUMA | J22: Nordic Sources | K22: SPA | L22: SGAE | M22: STIM | N22: SUISA | O22: MCPS-PRS | P22: QUERY SOURCE/ TERR OWNER | Q22: QUERY SOURCE/ TERR OWNER | R22: QUERY SOURCE/ TERR OWNER | S22: RAO | T22: ACUM | U22: ESMAA | V22: MSG | W22: SOCAN | X22: ASCAP/BMI/SESAC/GMR | Y22: SADAIC | Z22: Latin Autor | AA22: ECAD | AB22: Latin Autor | AC22: Latin Autor | AD22: Latin Autor | AE22: Latin Autor | AF22: SACM | AG22: Latin Autor | AH22: Latin Autor | AI22: Latin Autor | AJ22: APRA-AMCOS | AK22: APRA-AMCOS | AL22: MCSC | AM22: CASH | AN22: IPRS | AO22: JASRAC | AP22: MACP | AQ22: FILSCAP | AR22: VCPMC | AS22: MCT | AT22: COMPASS | AU22: KOMCA | AV22: WAMI | AW22: MUST | AX22: SAMRO | AY22: QUERY SOURCE/ TERR OWNER
B23: SIAE | C23: Licensor Pays | D23: AKM | E23: SABAM | F23: SACEM | G23: GEMA | H23: SIAE | I23: BUMA | J23: Nordic Sources | K23: SPA | L23: SGAE | M23: STIM | N23: SUISA | O23: MCPS-PRS | P23: QUERY SOURCE/ TERR OWNER | Q23: QUERY SOURCE/ TERR OWNER | R23: QUERY SOURCE/ TERR OWNER | S23: Blue Sun | T23: Dalia | U23: Pop Arabia | V23: Zeplin | W23: SOCAN | X23: ASCAP/BMI/SESAC/GMR | Y23: SADAIC | Z23: Latin Autor (Processed by BO) | AA23: ECAD | AB23: Latin Autor (Processed by BO) | AC23: Latin Autor (Processed by BO) | AD23: Latin Autor (Processed by BO) | AE23: Latin Autor (Processed by BO) | AF23: SACM | AG23: Latin Autor (Processed by BO) | AH23: Latin Autor (Processed by BO) | AI23: Latin Autor (Processed by BO) | AJ23: APRA-AMCOS | AK23: APRA-AMCOS | AL23: MCSC | AM23: CASH | AN23: IPRS | AO23: JASRAC | AP23: MACP | AQ23: FILSCAP | AR23: VCPMC | AS23: MCT | AT23: COMPASS | AU23: KOMCA | AV23: WAMI | AW23: MUST | AX23: SAMRO | AY23: QUERY SOURCE/ TERR OWNER
B24: SIAE | C24: Kobalt Paid By | D24: AKM | E24: SABAM | F24: SACEM | G24: GEMA | H24: SIAE | I24: BUMA | J24: Nordic Sources | K24: SPA | L24: SGAE | M24: STIM | N24: SUISA | O24: MCPS-PRS | P24: IDM | Q24: D-Version | R24: Schubert | S24: Blue Sun | T24: Dalia | U24: Pop Arabia | V24: Zeplin | W24: SOCAN | X24: ASCAP/BMI/SESAC/GMR | Y24: SADAIC | Z24: No Membership | AA24: ABRAMUS | AB24: SCD | AC24: SAYCO | AD24: Briana Music | AE24: SAYCE | AF24: SACM | AG24: No Membership | AH24: APDAYC | AI24: AGADU | AJ24: APRA-AMCOS | AK24: APRA-AMCOS | AL24: CASH | AM24: CASH | AN24: Turnkey | AO24: SMPJ | AP24: Indie Works | AQ24: COMPASS | AR24: COMPASS | AS24: COMPASS | AT24: COMPASS | AU24: EKKO | AV24: PT Nadaku | AW24: One Asia | AX24: SAMRO | AY24: QUERY SOURCE/ TERR OWNER
A25: SPA | B25: SPA | C25: Licensed By | D25: AKM | E25: SABAM | F25: SACEM | G25: GEMA | H25: SIAE | I25: BUMA | J25: Nordic Sources | K25: SPA | L25: SGAE | M25: STIM | N25: SUISA | O25: MCPS-PRS | P25: HDS-ZAMP | Q25: AUTODIA | R25: ZAIKS | S25: RAO | T25: ACUM | U25: ESMAA | V25: MSG | W25: SOCAN | X25: ASCAP/BMI/SESAC/GMR | Y25: SADAIC | Z25: Latin Autor | AA25: ABRAMUS | AB25: SCD | AC25: SAYCO | AD25: Latin Autor | AE25: Latin Autor | AF25: SACM | AG25: Latin Autor | AH25: APDAYC | AI25: Latin Autor | AJ25: APRA-AMCOS | AK25: APRA-AMCOS | AM25: CASH | AO25: JASRAC | AP25: MACP | AQ25: FILSCAP | AR25: VCPMC | AS25: MCT | AU25: KOMCA | AW25: MUST | AX25: SAMRO
B26: SPA | C26: Licensor Pays | D26: AKM | E26: SABAM | F26: SACEM | G26: GEMA | H26: SIAE | I26: BUMA | J26: Nordic Sources | K26: SPA | L26: SGAE | M26: STIM | N26: SUISA | O26: MCPS-PRS | P26: IDM | Q26: D-Version | R26: Schubert | S26: Blue Sun | T26: Dalia | U26: Pop Arabia | V26: Zeplin | W26: SOCAN | X26: ASCAP/BMI/SESAC/GMR | Y26: SADAIC | Z26: Latin Autor (Processed by BO) | AA26: ABRAMUS | AB26: SCD | AC26: SAYCO | AD26: Latin Autor (Processed by BO) | AE26: Latin Autor (Processed by BO) | AF26: SACM | AG26: Latin Autor (Processed by BO) | AH26: APDAYC | AI26: Latin Autor (Processed by BO) | AJ26: APRA-AMCOS | AK26: APRA-AMCOS | AM26: CASH | AO26: JASRAC | AP26: MACP | AQ26: FILSCAP | AR26: VCPMC | AS26: MCT | AU26: KOMCA | AW26: MUST | AX26: SAMRO
B27: SPA | C27: Kobalt Paid By | D27: AKM | E27: SABAM | F27: SACEM | G27: GEMA | H27: SIAE | I27: BUMA | J27: Nordic Sources | K27: SPA | L27: SGAE | M27: STIM | N27: SUISA | O27: MCPS-PRS | P27: IDM | Q27: D-Version | R27: Schubert | S27: Blue Sun | T27: Dalia | U27: Pop Arabia | V27: Zeplin | W27: SOCAN | X27: ASCAP/BMI/SESAC/GMR | Y27: SADAIC | Z27: No Membership | AA27: ABRAMUS | AB27: SCD | AC27: SAYCO | AD27: Briana Music | AE27: SAYCE | AF27: SACM | AG27: No Membership | AH27: APDAYC | AI27: AGADU | AJ27: APRA-AMCOS | AK27: APRA-AMCOS | AM27: CASH | AO27: SMPJ | AP27: Indie Works | AQ27: COMPASS | AR27: COMPASS | AS27: Compass | AU27: EKKO | AW27: One Asia | AX27: SAMRO
A28: STIM-NCB | B28: STIM-NCB | C28: Licensed By | D28: ICE | E28: ICE | F28: ICE | G28: ICE | H28: ICE | I28: ICE | J28: ICE | K28: ICE | L28: ICE | M28: ICE | N28: ICE | O28: ICE | P28: ICE | Q28: ICE | R28: ICE | S28: RAO | T28: ACUM | U28: ESMAA | V28: MSG | W28: SOCAN | X28: ASCAP/BMI/SESAC/GMR | Y28: SADAIC | Z28: Latin Autor | AA28: ECAD | AB28: Latin Autor | AC28: Latin Autor | AD28: Latin Autor | AE28: Latin Autor | AF28: SACM | AG28: Latin Autor | AH28: Latin Autor | AI28: Latin Autor | AJ28: APRA-AMCOS | AK28: APRA-AMCOS | AL28: APRA-AMCOS | AM28: APRA-AMCOS | AN28: APRA-AMCOS | AO28: APRA-AMCOS | AP28: APRA-AMCOS | AQ28: APRA-AMCOS | AR28: APRA-AMCOS | AS28: APRA-AMCOS | AT28: APRA-AMCOS | AU28: APRA-AMCOS | AV28: APRA-AMCOS | AW28: APRA-AMCOS | AX28: SAMRO | AY28: ICE
B29: STIM-NCB | C29: Licensor Pays | D29: STIM | E29: STIM | F29: STIM | G29: STIM | H29: STIM | I29: STIM | J29: STIM | K29: STIM | L29: STIM | M29: STIM | N29: STIM | O29: STIM | P29: STIM | Q29: STIM | R29: STIM | S29: Blue Sun | T29: Dalia | U29: Pop Arabia | V29: Zeplin | W29: SOCAN | X29: ASCAP/BMI/SESAC/GMR | Y29: SADAIC | Z29: Latin Autor (Processed by BO) | AA29: ECAD | AB29: Latin Autor (Processed by BO) | AC29: Latin Autor (Processed by BO) | AD29: Latin Autor (Processed by BO) | AE29: Latin Autor (Processed by BO) | AF29: SACM | AG29: Latin Autor (Processed by BO) | AH29: Latin Autor (Processed by BO) | AI29: Latin Autor (Processed by BO) | AJ29: APRA-AMCOS | AK29: APRA-AMCOS | AL29: STIM | AM29: STIM | AN29: STIM | AO29: STIM | AP29: STIM | AQ29: STIM | AR29: STIM | AS29: STIM | AT29: STIM | AU29: STIM | AV29: STIM | AW29: STIM | AX29: SAMRO | AY29: STIM
B30: STIM-NCB | C30: Kobalt Paid By | D30: STIM | E30: STIM | F30: STIM | G30: STIM | H30: STIM | I30: STIM | J30: STIM | K30: STIM | L30: STIM | M30: STIM | N30: STIM | O30: STIM | P30: IDM | Q30: D-Version | R30: Schubert | S30: Blue Sun | T30: Dalia | U30: Pop Arabia | V30: Zeplin | W30: SOCAN | X30: ASCAP/BMI/SESAC/GMR | Y30: SADAIC | Z30: No Membership | AA30: ABRAMUS | AB30: SCD | AC30: SAYCO | AD30: Briana Music | AE30: SAYCE | AF30: SACM | AG30: No Membership | AH30: APDAYC | AI30: AGADU | AJ30: APRA-AMCOS | AK30: APRA-AMCOS | AL30: STIM | AM30: STIM | AN30: Turnkey | AO30: SMPJ | AP30: Indie Works | AQ30: STIM | AR30: STIM | AS30: STIM | AT30: STIM | AU30: EKKO | AV30: PT Nadaku | AW30: One Asia | AX30: SAMRO | AY30: STIM
A31: SUISA | B31: SUISA | C31: Licensed By | D31: MINT / ICE | E31: MINT / ICE | F31: MINT / ICE | G31: MINT / ICE | H31: MINT / ICE | I31: MINT / ICE | J31: MINT / ICE | K31: MINT / ICE | L31: MINT / ICE | M31: MINT / ICE | N31: SUISA | O31: MINT | P31: MINT / ICE | Q31: MINT / ICE | R31: MINT / ICE | S31: RAO | T31: ACUM | U31: ESMAA | V31: MSG | W31: SOCAN | X31: ASCAP/BMI/SESAC/GMR | Y31: SADAIC | Z31: Latin Autor | AA31: ECAD | AB31: Latin Autor | AC31: Latin Autor | AD31: Latin Autor | AE31: Latin Autor | AF31: SACM | AG31: Latin Autor | AH31: APDAYC | AI31: AGADU | AJ31: APRA-AMCOS | AK31: APRA-AMCOS | AL31: MCSC | AM31: CASH | AN31: IPRS | AO31: JASRAC | AP31: MACP | AQ31: FILSCAP | AR31: VCPMC | AT31: COMPASS | AU31: KOMCA | AV31: WAMI | AW31: MUST | AX31: SAMRO
B32: SUISA | C32: Licensor Pays | D32: AKM | E32: SABAM | F32: SACEM | G32: GEMA | H32: SIAE | I32: BUMA | J32: STIM | K32: SPA | L32: SGAE | M32: STIM | N32: SUISA | O32: MCPS-PRS | P32: HDS ZAMP | Q32: AUTODIA | R32: ZAIKS | S32: Blue Sun | T32: Dalia | U32: Pop Arabia | V32: Zeplin | W32: SOCAN | X32: ASCAP/BMI/SESAC/GMR | Y32: SADAIC | Z32: Latin Autor (Processed by BO) | AA32: ECAD | AB32: Latin Autor (Processed by BO) | AC32: Latin Autor (Processed by BO) | AD32: Latin Autor (Processed by BO) | AE32: Latin Autor (Processed by BO) | AF32: SACM | AG32: Latin Autor (Processed by BO) | AH32: APDAYC | AI32: Latin Autor (Processed by BO) | AJ32: APRA-AMCOS | AK32: APRA-AMCOS | AL32: MCSC | AM32: CASH | AN32: IPRS | AO32: JASRAC | AP32: MACP | AQ32: FILSCAP | AR32: VCPMC | AT32: COMPASS | AU32: KOMCA | AV32: WAMI | AW32: MUST | AX32: SAMRO
B33: SUISA | C33: Kobalt Paid By | D33: AKM | E33: SABAM | F33: SACEM | G33: GEMA | H33: SIAE | I33: BUMA | J33: STIM | K33: SPA | L33: SGAE | M33: STIM | N33: SUISA | O33: MCPS-PRS | P33: IDM | Q33: D-Version | R33: Schubert | S33: Blue Sun | T33: Dalia | U33: Pop Arabia | V33: Zeplin | W33: SOCAN | X33: ASCAP/BMI/SESAC/GMR | Y33: SADAIC | Z33: No Membership | AA33: ABRAMUS | AB33: SCD | AC33: SAYCO | AD33: Briana Music | AE33: SAYCE | AF33: SACM | AG33: No Membership | AH33: APDAYC | AI33: AGADU | AJ33: APRA-AMCOS | AK33: APRA-AMCOS | AL33: CASH | AM33: CASH | AN33: Turnkey | AO33: SMPJ | AP33: Indie Works | AQ33: COMPASS | AR33: COMPASS | AT33: COMPASS | AU33: EKKO | AV33: PT Nadaku | AW33: One Asia | AX33: SAMRO
A34: Anglo-Am Rep
A35: AMRA | B35: AMRA | C35: Licensed By | D35: AMRA | E35: AMRA | F35: AMRA | G35: AMRA | H35: AMRA | I35: AMRA | J35: AMRA | K35: AMRA | L35: AMRA | M35: AMRA | N35: AMRA | O35: AMRA | P35: AMRA | Q35: AMRA | R35: AMRA | S35: AMRA | T35: AMRA | U35: AMRA | V35: AMRA | W35: SOCAN | X35: ASCAP/BMI/SESAC/GMR | Y35: SADAIC | Z35: Latin Autor | AA35: ECAD | AB35: Latin Autor | AC35: Latin Autor | AD35: Latin Autor | AE35: Latin Autor | AF35: SACM | AG35: Latin Autor | AH35: Latin Autor | AI35: Latin Autor | AJ35: AMRA | AK35: AMRA | AL35: AMRA | AM35: AMRA | AN35: AMRA | AO35: AMRA | AP35: AMRA | AQ35: AMRA | AR35: AMRA | AS35: AMRA | AT35: AMRA | AU35: KOMCA | AV35: AMRA | AW35: AMRA | AX35: AMRA | AY35: AMRA
B36: AMRA | C36: Licensor Pays | D36: AMRA | E36: AMRA | F36: AMRA | G36: AMRA | H36: AMRA | I36: AMRA | J36: AMRA | K36: AMRA | L36: AMRA | M36: AMRA | N36: AMRA | O36: AMRA | P36: AMRA | Q36: AMRA | R36: AMRA | S36: AMRA | T36: AMRA | U36: AMRA | V36: AMRA | W36: SOCAN | X36: ASCAP/BMI/SESAC/GMR | Y36: SADAIC | Z36: Latin Autor (Processed by BO) | AA36: ECAD | AB36: Latin Autor (Processed by BO) | AC36: Latin Autor (Processed by BO) | AD36: Latin Autor (Processed by BO) | AE36: Latin Autor (Processed by BO) | AF36: SACM | AG36: Latin Autor (Processed by BO) | AH36: Latin Autor (Processed by BO) | AI36: Latin Autor (Processed by BO) | AJ36: AMRA | AK36: AMRA | AL36: AMRA | AM36: AMRA | AN36: AMRA | AO36: AMRA | AP36: AMRA | AQ36: AMRA | AR36: AMRA | AS36: AMRA | AT36: AMRA | AU36: KOMCA | AV36: AMRA | AW36: AMRA | AX36: AMRA | AY36: AMRA
B37: AMRA | C37: Kobalt Paid By | D37: AMRA | E37: AMRA | F37: AMRA | G37: AMRA | H37: AMRA | I37: AMRA | J37: AMRA | K37: AMRA | L37: AMRA | M37: AMRA | N37: AMRA | O37: AMRA | P37: AMRA | Q37: AMRA | R37: AMRA | S37: AMRA | T37: AMRA | U37: AMRA | V37: AMRA | W37: SOCAN | X37: ASCAP/BMI/SESAC/GMR | Y37: SADAIC | Z37: No Membership | AA37: ABRAMUS | AB37: SCD | AC37: SAYCO | AD37: Briana Music | AE37: SAYCE | AF37: SACM | AG37: No Membership | AH37: APDAYC | AI37: AGADU | AJ37: AMRA | AK37: AMRA | AL37: AMRA | AM37: AMRA | AN37: AMRA | AO37: AMRA | AP37: AMRA | AQ37: AMRA | AR37: AMRA | AS37: AMRA | AT37: AMRA | AU37: EKKO | AV37: AMRA | AW37: AMRA | AX37: AMRA | AY37: AMRA
A38: APRA-AMCOS | B38: APRA-AMCOS | C38: Licensed By | D38: AMRA | E38: AMRA | F38: AMRA | G38: AMRA | H38: AMRA | I38: AMRA | J38: AMRA | K38: AMRA | L38: AMRA | M38: AMRA | N38: AMRA | O38: AMRA | P38: AMRA | Q38: AMRA | R38: AMRA | S38: AMRA | T38: AMRA | U38: AMRA | V38: AMRA | W38: SOCAN | X38: ASCAP/BMI/SESAC/GMR | Y38: SADAIC | Z38: Latin Autor | AA38: ECAD | AB38: Latin Autor | AC38: Latin Autor | AD38: Latin Autor | AE38: Latin Autor | AF38: SACM | AG38: Latin Autor | AH38: Latin Autor | AI38: Latin Autor | AJ38: APRA-AMCOS | AK38: APRA-AMCOS | AL38: AMRA | AM38: AMRA | AN38: AMRA | AO38: AMRA | AP38: AMRA | AQ38: AMRA | AR38: AMRA | AS38: AMRA | AT38: AMRA | AU38: KOMCA | AV38: AMRA | AW38: AMRA | AX38: AMRA | AY38: AMRA
B39: APRA-AMCOS | C39: Licensor Pays | D39: AMRA | E39: AMRA | F39: AMRA | G39: AMRA | H39: AMRA | I39: AMRA | J39: AMRA | K39: AMRA | L39: AMRA | M39: AMRA | N39: AMRA | O39: AMRA | P39: AMRA | Q39: AMRA | R39: AMRA | S39: AMRA | T39: AMRA | U39: AMRA | V39: AMRA | W39: SOCAN | X39: ASCAP/BMI/SESAC/GMR | Y39: SADAIC | Z39: Latin Autor (Processed by BO) | AA39: ECAD | AB39: Latin Autor (Processed by BO) | AC39: Latin Autor (Processed by BO) | AD39: Latin Autor (Processed by BO) | AE39: Latin Autor (Processed by BO) | AF39: SACM | AG39: Latin Autor (Processed by BO) | AH39: Latin Autor (Processed by BO) | AI39: Latin Autor (Processed by BO) | AJ39: APRA-AMCOS | AK39: APRA-AMCOS | AL39: AMRA | AM39: AMRA | AN39: AMRA | AO39: AMRA | AP39: AMRA | AQ39: AMRA | AR39: AMRA | AS39: AMRA | AT39: AMRA | AU39: KOMCA | AV39: AMRA | AW39: AMRA | AX39: AMRA | AY39: AMRA
B40: APRA-AMCOS | C40: Kobalt Paid By | D40: AMRA | E40: AMRA | F40: AMRA | G40: AMRA | H40: AMRA | I40: AMRA | J40: AMRA | K40: AMRA | L40: AMRA | M40: AMRA | N40: AMRA | O40: AMRA | P40: AMRA | Q40: AMRA | R40: AMRA | S40: AMRA | T40: AMRA | U40: AMRA | V40: AMRA | W40: SOCAN | X40: ASCAP/BMI/SESAC/GMR | Y40: SADAIC | Z40: No Membership | AA40: ABRAMUS | AB40: SCD | AC40: SAYCO | AD40: Briana Music | AE40: SAYCE | AF40: SACM | AG40: No Membership | AH40: APDAYC | AI40: AGADU | AJ40: APRA-AMCOS | AK40: APRA-AMCOS | AL40: AMRA | AM40: AMRA | AN40: AMRA | AO40: AMRA | AP40: AMRA | AQ40: AMRA | AR40: AMRA | AS40: AMRA | AT40: AMRA | AU40: EKKO | AV40: AMRA | AW40: AMRA | AX40: AMRA | AY40: AMRA
A41: ASCAP | B41: ASCAP | C41: Licensed By | D41: AMRA | E41: AMRA | F41: AMRA | G41: AMRA | H41: AMRA | I41: AMRA | J41: AMRA | K41: AMRA | L41: AMRA | M41: AMRA | N41: AMRA | O41: AMRA | P41: AMRA | Q41: AMRA | R41: AMRA | S41: AMRA | T41: AMRA | U41: AMRA | V41: AMRA | W41: SOCAN | X41: ASCAP | Y41: SADAIC | Z41: Latin Autor | AA41: ECAD | AB41: Latin Autor | AC41: Latin Autor | AD41: Latin Autor | AE41: Latin Autor | AF41: SACM | AG41: Latin Autor | AH41: Latin Autor | AI41: Latin Autor | AJ41: AMRA | AK41: AMRA | AL41: AMRA | AM41: AMRA | AN41: AMRA | AO41: AMRA | AP41: AMRA | AQ41: AMRA | AR41: AMRA | AS41: AMRA | AT41: AMRA | AU41: KOMCA | AV41: AMRA | AW41: AMRA | AX41: AMRA | AY41: AMRA
B42: ASCAP | C42: Licensor Pays | D42: AMRA | E42: AMRA | F42: AMRA | G42: AMRA | H42: AMRA | I42: AMRA | J42: AMRA | K42: AMRA | L42: AMRA | M42: AMRA | N42: AMRA | O42: AMRA | P42: AMRA | Q42: AMRA | R42: AMRA | S42: AMRA | T42: AMRA | U42: AMRA | V42: AMRA | W42: SOCAN | X42: ASCAP | Y42: SADAIC | Z42: Latin Autor (Processed by BO) | AA42: ECAD | AB42: Latin Autor (Processed by BO) | AC42: Latin Autor (Processed by BO) | AD42: Latin Autor (Processed by BO) | AE42: Latin Autor (Processed by BO) | AF42: SACM | AG42: Latin Autor (Processed by BO) | AH42: Latin Autor (Processed by BO) | AI42: Latin Autor (Processed by BO) | AJ42: AMRA | AK42: AMRA | AL42: AMRA | AM42: AMRA | AN42: AMRA | AO42: AMRA | AP42: AMRA | AQ42: AMRA | AR42: AMRA | AS42: AMRA | AT42: AMRA | AU42: KOMCA | AV42: AMRA | AW42: AMRA | AX42: AMRA | AY42: AMRA
B43: ASCAP | C43: Kobalt Paid By | D43: AMRA | E43: AMRA | F43: AMRA | G43: AMRA | H43: AMRA | I43: AMRA | J43: AMRA | K43: AMRA | L43: AMRA | M43: AMRA | N43: AMRA | O43: AMRA | P43: AMRA | Q43: AMRA | R43: AMRA | S43: AMRA | T43: AMRA | U43: AMRA | V43: AMRA | W43: SOCAN | X43: ASCAP | Y43: SADAIC | Z43: No Membership | AA43: ABRAMUS | AB43: SCD | AC43: SAYCO | AD43: Briana Music | AE43: SAYCE | AF43: SACM | AG43: No Membership | AH43: APDAYC | AI43: AGADU | AJ43: AMRA | AK43: AMRA | AL43: AMRA | AM43: AMRA | AN43: AMRA | AO43: AMRA | AP43: AMRA | AQ43: AMRA | AR43: AMRA | AS43: AMRA | AT43: AMRA | AU43: EKKO | AV43: AMRA | AW43: AMRA | AX43: AMRA | AY43: AMRA
A44: BMI | B44: BMI | C44: Licensed By | D44: AMRA | E44: AMRA | F44: AMRA | G44: AMRA | H44: AMRA | I44: AMRA | J44: AMRA | K44: AMRA | L44: AMRA | M44: AMRA | N44: AMRA | O44: AMRA | P44: AMRA | Q44: AMRA | R44: AMRA | S44: AMRA | T44: AMRA | U44: AMRA | V44: AMRA | W44: SOCAN | X44: BMI | Y44: SADAIC | Z44: Latin Autor | AA44: ECAD | AB44: Latin Autor | AC44: Latin Autor | AD44: Latin Autor | AE44: Latin Autor | AF44: SACM | AG44: Latin Autor | AH44: Latin Autor | AI44: Latin Autor | AJ44: AMRA | AK44: AMRA | AL44: AMRA | AM44: AMRA | AN44: AMRA | AO44: AMRA | AP44: AMRA | AQ44: AMRA | AR44: AMRA | AS44: AMRA | AT44: AMRA | AU44: KOMCA | AV44: AMRA | AW44: AMRA | AX44: AMRA | AY44: AMRA
B45: BMI | C45: Licensor Pays | D45: AMRA | E45: AMRA | F45: AMRA | G45: AMRA | H45: AMRA | I45: AMRA | J45: AMRA | K45: AMRA | L45: AMRA | M45: AMRA | N45: AMRA | O45: AMRA | P45: AMRA | Q45: AMRA | R45: AMRA | S45: AMRA | T45: AMRA | U45: AMRA | V45: AMRA | W45: SOCAN | X45: BMI | Y45: SADAIC | Z45: Latin Autor (Processed by BO) | AA45: ECAD | AB45: Latin Autor (Processed by BO) | AC45: Latin Autor (Processed by BO) | AD45: Latin Autor (Processed by BO) | AE45: Latin Autor (Processed by BO) | AF45: SACM | AG45: Latin Autor (Processed by BO) | AH45: Latin Autor (Processed by BO) | AI45: Latin Autor (Processed by BO) | AJ45: AMRA | AK45: AMRA | AL45: AMRA | AM45: AMRA | AN45: AMRA | AO45: AMRA | AP45: AMRA | AQ45: AMRA | AR45: AMRA | AS45: AMRA | AT45: AMRA | AU45: KOMCA | AV45: AMRA | AW45: AMRA | AX45: AMRA | AY45: AMRA
B46: BMI | C46: Kobalt Paid By | D46: AMRA | E46: AMRA | F46: AMRA | G46: AMRA | H46: AMRA | I46: AMRA | J46: AMRA | K46: AMRA | L46: AMRA | M46: AMRA | N46: AMRA | O46: AMRA | P46: AMRA | Q46: AMRA | R46: AMRA | S46: AMRA | T46: AMRA | U46: AMRA | V46: AMRA | W46: SOCAN | X46: BMI | Y46: SADAIC | Z46: No Membership | AA46: ABRAMUS | AB46: SCD | AC46: SAYCO | AD46: Briana Music | AE46: SAYCE | AF46: SACM | AG46: No Membership | AH46: APDAYC | AI46: AGADU | AJ46: AMRA | AK46: AMRA | AL46: AMRA | AM46: AMRA | AN46: AMRA | AO46: AMRA | AP46: AMRA | AQ46: AMRA | AR46: AMRA | AS46: AMRA | AT46: AMRA | AU46: EKKO | AV46: AMRA | AW46: AMRA | AX46: AMRA | AY46: AMRA
A47: GMR | B47: GMR | C47: Licensed By | D47: AMRA | E47: AMRA | F47: AMRA | G47: AMRA | H47: AMRA | I47: AMRA | J47: AMRA | K47: AMRA | L47: AMRA | M47: AMRA | N47: AMRA | O47: AMRA | P47: AMRA | Q47: AMRA | R47: AMRA | S47: AMRA | T47: AMRA | U47: AMRA | V47: AMRA | W47: SOCAN | X47: GMR | Y47: SADAIC | Z47: Latin Autor | AA47: ECAD | AB47: Latin Autor | AC47: Latin Autor | AD47: Latin Autor | AE47: Latin Autor | AF47: SACM | AG47: Latin Autor | AH47: Latin Autor | AI47: Latin Autor | AJ47: AMRA | AK47: AMRA | AL47: AMRA | AM47: AMRA | AN47: AMRA | AO47: AMRA | AP47: AMRA | AQ47: AMRA | AR47: AMRA | AS47: AMRA | AT47: AMRA | AU47: KOMCA | AV47: AMRA | AW47: AMRA | AX47: AMRA | AY47: AMRA
B48: GMR | C48: Licensor Pays | D48: AMRA | E48: AMRA | F48: AMRA | G48: AMRA | H48: AMRA | I48: AMRA | J48: AMRA | K48: AMRA | L48: AMRA | M48: AMRA | N48: AMRA | O48: AMRA | P48: AMRA | Q48: AMRA | R48: AMRA | S48: AMRA | T48: AMRA | U48: AMRA | V48: AMRA | W48: SOCAN | X48: GMR | Y48: SADAIC | Z48: Latin Autor (Processed by BO) | AA48: ECAD | AB48: Latin Autor (Processed by BO) | AC48: Latin Autor (Processed by BO) | AD48: Latin Autor (Processed by BO) | AE48: Latin Autor (Processed by BO) | AF48: SACM | AG48: Latin Autor (Processed by BO) | AH48: Latin Autor (Processed by BO) | AI48: Latin Autor (Processed by BO) | AJ48: AMRA | AK48: AMRA | AL48: AMRA | AM48: AMRA | AN48: AMRA | AO48: AMRA | AP48: AMRA | AQ48: AMRA | AR48: AMRA | AS48: AMRA | AT48: AMRA | AU48: KOMCA | AV48: AMRA | AW48: AMRA | AX48: AMRA | AY48: AMRA
B49: GMR | C49: Kobalt Paid By | D49: AMRA | E49: AMRA | F49: AMRA | G49: AMRA | H49: AMRA | I49: AMRA | J49: AMRA | K49: AMRA | L49: AMRA | M49: AMRA | N49: AMRA | O49: AMRA | P49: AMRA | Q49: AMRA | R49: AMRA | S49: AMRA | T49: AMRA | U49: AMRA | V49: AMRA | W49: SOCAN | X49: GMR | Y49: SADAIC | Z49: No Membership | AA49: ABRAMUS | AB49: SCD | AC49: SAYCO | AD49: Briana Music | AE49: SAYCE | AF49: SACM | AG49: No Membership | AH49: APDAYC | AI49: AGADU | AJ49: AMRA | AK49: AMRA | AL49: AMRA | AM49: AMRA | AN49: AMRA | AO49: AMRA | AP49: AMRA | AQ49: AMRA | AR49: AMRA | AS49: AMRA | AT49: AMRA | AU49: EKKO | AV49: AMRA | AW49: AMRA | AX49: AMRA | AY49: AMRA
A50: SOCAN | B50: SOCAN | C50: Licensed By | D50: AMRA | E50: AMRA | F50: AMRA | G50: AMRA | H50: AMRA | I50: AMRA | J50: AMRA | K50: AMRA | L50: AMRA | M50: AMRA | N50: AMRA | O50: AMRA | P50: AMRA | Q50: AMRA | R50: AMRA | S50: AMRA | T50: AMRA | U50: AMRA | V50: AMRA | W50: SOCAN | X50: ASCAP/BMI/SESAC/GMR | Y50: SADAIC | Z50: Latin Autor | AA50: ECAD | AB50: Latin Autor | AC50: Latin Autor | AD50: Latin Autor | AE50: Latin Autor | AF50: SACM | AG50: Latin Autor | AH50: Latin Autor | AI50: Latin Autor | AJ50: AMRA | AK50: AMRA | AL50: AMRA | AM50: AMRA | AN50: AMRA | AO50: AMRA | AP50: AMRA | AQ50: AMRA | AR50: AMRA | AS50: AMRA | AT50: AMRA | AU50: KOMCA | AV50: AMRA | AW50: AMRA | AX50: AMRA | AY50: AMRA
B51: SOCAN | C51: Licensor Pays | D51: AMRA | E51: AMRA | F51: AMRA | G51: AMRA | H51: AMRA | I51: AMRA | J51: AMRA | K51: AMRA | L51: AMRA | M51: AMRA | N51: AMRA | O51: AMRA | P51: AMRA | Q51: AMRA | R51: AMRA | S51: AMRA | T51: AMRA | U51: AMRA | V51: AMRA | W51: SOCAN | X51: ASCAP/BMI/SESAC/GMR | Y51: SADAIC | Z51: Latin Autor (Processed by BO) | AA51: ECAD | AB51: Latin Autor (Processed by BO) | AC51: Latin Autor (Processed by BO) | AD51: Latin Autor (Processed by BO) | AE51: Latin Autor (Processed by BO) | AF51: SACM | AG51: Latin Autor (Processed by BO) | AH51: Latin Autor (Processed by BO) | AI51: Latin Autor (Processed by BO) | AJ51: AMRA | AK51: AMRA | AL51: AMRA | AM51: AMRA | AN51: AMRA | AO51: AMRA | AP51: AMRA | AQ51: AMRA | AR51: AMRA | AS51: AMRA | AT51: AMRA | AU51: KOMCA | AV51: AMRA | AW51: AMRA | AX51: AMRA | AY51: AMRA
B52: SOCAN | C52: Kobalt Paid By | D52: AMRA | E52: AMRA | F52: AMRA | G52: AMRA | H52: AMRA | I52: AMRA | J52: AMRA | K52: AMRA | L52: AMRA | M52: AMRA | N52: AMRA | O52: AMRA | P52: AMRA | Q52: AMRA | R52: AMRA | S52: AMRA | T52: AMRA | U52: AMRA | V52: AMRA | W52: SOCAN | X52: ASCAP/BMI/SESAC/GMR | Y52: SADAIC | Z52: No Membership | AA52: ABRAMUS | AB52: SCD | AC52: SAYCO | AD52: Briana Music | AE52: SAYCE | AF52: SACM | AG52: No Membership | AH52: APDAYC | AI52: AGADU | AJ52: AMRA | AK52: AMRA | AL52: AMRA | AM52: AMRA | AN52: AMRA | AO52: AMRA | AP52: AMRA | AQ52: AMRA | AR52: AMRA | AS52: AMRA | AT52: AMRA | AU52: EKKO | AV52: AMRA | AW52: AMRA | AX52: AMRA | AY52: AMRA
A53: MCPS-PRS | B53: MCPS-PRS | C53: Licensed By | D53: AMRA | E53: AMRA | F53: AMRA | G53: AMRA | H53: AMRA | I53: AMRA | J53: AMRA | K53: AMRA | L53: AMRA | M53: AMRA | N53: AMRA | O53: AMRA | P53: AMRA | Q53: AMRA | R53: AMRA | S53: AMRA | T53: AMRA | U53: AMRA | V53: AMRA | W53: SOCAN | X53: ASCAP/BMI/SESAC/GMR | Y53: SADAIC | Z53: Latin Autor | AA53: ECAD | AB53: Latin Autor | AC53: Latin Autor | AD53: Latin Autor | AE53: Latin Autor | AF53: SACM | AG53: Latin Autor | AH53: Latin Autor | AI53: Latin Autor | AJ53: AMRA | AK53: AMRA | AL53: AMRA | AM53: AMRA | AN53: AMRA | AO53: AMRA | AP53: AMRA | AQ53: AMRA | AR53: AMRA | AS53: AMRA | AT53: AMRA | AU53: KOMCA | AV53: AMRA | AW53: AMRA | AX53: AMRA | AY53: AMRA
B54: MCPS-PRS | C54: Licensor Pays | D54: AMRA | E54: AMRA | F54: AMRA | G54: AMRA | H54: AMRA | I54: AMRA | J54: AMRA | K54: AMRA | L54: AMRA | M54: AMRA | N54: AMRA | O54: AMRA | P54: AMRA | Q54: AMRA | R54: AMRA | S54: AMRA | T54: AMRA | U54: AMRA | V54: AMRA | W54: SOCAN | X54: ASCAP/BMI/SESAC | Y54: SADAIC | Z54: Latin Autor (Processed by BO) | AA54: ECAD | AB54: Latin Autor (Processed by BO) | AC54: Latin Autor (Processed by BO) | AD54: Latin Autor (Processed by BO) | AE54: Latin Autor (Processed by BO) | AF54: SACM | AG54: Latin Autor (Processed by BO) | AH54: Latin Autor (Processed by BO) | AI54: Latin Autor (Processed by BO) | AJ54: AMRA | AK54: AMRA | AL54: AMRA | AM54: AMRA | AN54: AMRA | AO54: AMRA | AP54: AMRA | AQ54: AMRA | AR54: AMRA | AS54: AMRA | AT54: AMRA | AU54: KOMCA | AV54: AMRA | AW54: AMRA | AX54: AMRA | AY54: AMRA
B55: MCPS-PRS | C55: Kobalt Paid By | D55: AMRA | E55: AMRA | F55: AMRA | G55: AMRA | H55: AMRA | I55: AMRA | J55: AMRA | K55: AMRA | L55: AMRA | M55: AMRA | N55: AMRA | O55: AMRA | P55: AMRA | Q55: AMRA | R55: AMRA | S55: AMRA | T55: AMRA | U55: AMRA | V55: AMRA | W55: SOCAN | X55: ASCAP/BMI/SESAC | Y55: SADAIC | Z55: No Membership | AA55: ABRAMUS | AB55: SCD | AC55: SAYCO | AD55: Briana Music | AE55: SAYCE | AF55: SACM | AG55: No Membership | AH55: APDAYC | AI55: AGADU | AJ55: AMRA | AK55: AMRA | AL55: AMRA | AM55: AMRA | AN55: AMRA | AO55: AMRA | AP55: AMRA | AQ55: AMRA | AR55: AMRA | AS55: AMRA | AT55: AMRA | AU55: EKKO | AV55: AMRA | AW55: AMRA | AX55: AMRA | AY55: AMRA
A56: SAMRO / CAPASSO | B56: SAMRO | C56: Licensed By | D56: AMRA | E56: AMRA | F56: AMRA | G56: AMRA | H56: AMRA | I56: AMRA | J56: AMRA | K56: AMRA | L56: AMRA | M56: AMRA | N56: AMRA | O56: AMRA | P56: AMRA | Q56: AMRA | R56: AMRA | S56: AMRA | T56: AMRA | U56: AMRA | V56: AMRA | W56: SOCAN | X56: ASCAP/BMI/SESAC/GMR | Y56: SADAIC | Z56: Latin Autor | AA56: ECAD | AB56: Latin Autor | AC56: Latin Autor | AD56: Latin Autor | AE56: Latin Autor | AF56: SACM | AG56: Latin Autor | AH56: Latin Autor | AI56: Latin Autor | AJ56: AMRA | AK56: AMRA | AL56: AMRA | AM56: AMRA | AN56: AMRA | AO56: AMRA | AP56: AMRA | AQ56: AMRA | AR56: AMRA | AS56: AMRA | AT56: AMRA | AU56: KOMCA | AV56: AMRA | AW56: AMRA | AX56: AMRA | AY56: AMRA
B57: SAMRO | C57: Licensor Pays | D57: AMRA | E57: AMRA | F57: AMRA | G57: AMRA | H57: AMRA | I57: AMRA | J57: AMRA | K57: AMRA | L57: AMRA | M57: AMRA | N57: AMRA | O57: AMRA | P57: AMRA | Q57: AMRA | R57: AMRA | S57: AMRA | T57: AMRA | U57: AMRA | V57: AMRA | W57: SOCAN | X57: ASCAP/BMI/SESAC | Y57: SADAIC | Z57: Latin Autor (Processed by BO) | AA57: ECAD | AB57: Latin Autor (Processed by BO) | AC57: Latin Autor (Processed by BO) | AD57: Latin Autor (Processed by BO) | AE57: Latin Autor (Processed by BO) | AF57: SACM | AG57: Latin Autor (Processed by BO) | AI57: Latin Autor (Processed by BO) | AJ57: AMRA | AK57: AMRA | AL57: AMRA | AM57: AMRA | AN57: AMRA | AO57: AMRA | AP57: AMRA | AQ57: AMRA | AR57: AMRA | AS57: AMRA | AT57: AMRA | AU57: KOMCA | AV57: AMRA | AW57: AMRA | AX57: AMRA | AY57: AMRA
B58: SAMRO | C58: Kobalt Paid By | D58: AMRA | E58: AMRA | F58: AMRA | G58: AMRA | H58: AMRA | I58: AMRA | J58: AMRA | K58: AMRA | L58: AMRA | M58: AMRA | N58: AMRA | O58: AMRA | P58: AMRA | Q58: AMRA | R58: AMRA | S58: AMRA | T58: AMRA | U58: AMRA | V58: AMRA | W58: SOCAN | X58: ASCAP/BMI/SESAC | Y58: SADAIC | Z58: No Membership | AA58: ABRAMUS | AB58: SCD | AC58: SAYCO | AD58: Briana Music | AE58: SAYCE | AF58: SACM | AG58: No Membership | AH58: APDAYC | AI58: AGADU | AJ58: AMRA | AK58: AMRA | AL58: AMRA | AM58: AMRA | AN58: AMRA | AO58: AMRA | AP58: AMRA | AQ58: AMRA | AR58: AMRA | AS58: AMRA | AT58: AMRA | AU58: EKKO | AV58: AMRA | AW58: AMRA | AX58: AMRA | AY58: AMRA
A59: SESAC | B59: SESAC | C59: Licensed By | D59: AMRA | E59: AMRA | F59: AMRA | G59: AMRA | H59: AMRA | I59: AMRA | J59: AMRA | K59: AMRA | L59: AMRA | M59: AMRA | N59: AMRA | O59: AMRA | P59: AMRA | Q59: AMRA | R59: AMRA | S59: AMRA | T59: AMRA | U59: AMRA | V59: AMRA | W59: SOCAN | X59: SESAC | Y59: SADAIC | Z59: Latin Autor | AA59: ECAD | AB59: Latin Autor | AC59: Latin Autor | AD59: Latin Autor | AE59: Latin Autor | AF59: SACM | AG59: Latin Autor | AH59: Latin Autor | AI59: Latin Autor | AJ59: AMRA | AK59: AMRA | AL59: AMRA | AM59: AMRA | AN59: AMRA | AO59: AMRA | AP59: AMRA | AQ59: AMRA | AR59: AMRA | AS59: AMRA | AT59: AMRA | AU59: KOMCA | AV59: AMRA | AW59: AMRA | AX59: AMRA | AY59: AMRA
B60: SESAC | C60: Licensor Pays | D60: AMRA | E60: AMRA | F60: AMRA | G60: AMRA | H60: AMRA | I60: AMRA | J60: AMRA | K60: AMRA | L60: AMRA | M60: AMRA | N60: AMRA | O60: AMRA | P60: AMRA | Q60: AMRA | R60: AMRA | S60: AMRA | T60: AMRA | U60: AMRA | V60: AMRA | W60: SOCAN | X60: SESAC | Y60: SADAIC | Z60: Latin Autor (Processed by BO) | AA60: ECAD | AB60: Latin Autor (Processed by BO) | AC60: Latin Autor (Processed by BO) | AD60: Latin Autor (Processed by BO) | AE60: Latin Autor (Processed by BO) | AF60: SACM | AG60: Latin Autor (Processed by BO) | AH60: Latin Autor (Processed by BO) | AI60: Latin Autor (Processed by BO) | AJ60: AMRA | AK60: AMRA | AL60: AMRA | AM60: AMRA | AN60: AMRA | AO60: AMRA | AP60: AMRA | AQ60: AMRA | AR60: AMRA | AS60: AMRA | AT60: AMRA | AU60: KOMCA | AV60: AMRA | AW60: AMRA | AX60: AMRA | AY60: AMRA
B61: SESAC | C61: Kobalt Paid By | D61: AMRA | E61: AMRA | F61: AMRA | G61: AMRA | H61: AMRA | I61: AMRA | J61: AMRA | K61: AMRA | L61: AMRA | M61: AMRA | N61: AMRA | O61: AMRA | P61: AMRA | Q61: AMRA | R61: AMRA | S61: AMRA | T61: AMRA | U61: AMRA | V61: AMRA | W61: SOCAN | X61: SESAC | Y61: SADAIC | Z61: No Membership | AA61: ABRAMUS | AB61: SCD | AC61: SAYCO | AD61: Briana Music | AE61: SAYCE | AF61: SACM | AG61: No Membership | AH61: APDAYC | AI61: AGADU | AJ61: AMRA | AK61: AMRA | AL61: AMRA | AM61: AMRA | AN61: AMRA | AO61: AMRA | AP61: AMRA | AQ61: AMRA | AR61: AMRA | AS61: AMRA | AT61: AMRA | AU61: EKKO | AV61: AMRA | AW61: AMRA | AX61: AMRA | AY61: AMRA
A62: Lat-Am Rep
A63: ABRAMUS | B63: ABRAMUS | C63: Licensed By | D63: MINT | E63: MINT | F63: MINT | G63: MINT | H63: MINT | I63: MINT | J63: MINT | K63: SGAE | L63: SGAE | M63: MINT | N63: SUISA | O63: MINT | P63: MINT | Q63: MINT | R63: MINT | S63: QUERY SOURCE/ TERR OWNER | T63: QUERY SOURCE/ TERR OWNER | U63: QUERY SOURCE/ TERR OWNER | V63: QUERY SOURCE/ TERR OWNER | W63: SOCAN | X63: ASCAP/BMI/SESAC/GMR | Y63: SADAIC | Z63: Latin Autor | AA63: ECAD | AB63: Latin Autor | AC63: Latin Autor | AD63: Latin Autor | AE63: Latin Autor | AF63: SACM | AG63: Latin Autor | AH63: Latin Autor | AI63: Latin Autor | AJ63: AMRA | AK63: AMRA | AL63: QUERY SOURCE/ TERR OWNER | AM63: QUERY SOURCE/ TERR OWNER | AN63: QUERY SOURCE/ TERR OWNER | AO63: QUERY SOURCE/ TERR OWNER | AP63: QUERY SOURCE/ TERR OWNER | AQ63: QUERY SOURCE/ TERR OWNER | AR63: QUERY SOURCE/ TERR OWNER | AS63: QUERY SOURCE/ TERR OWNER | AT63: QUERY SOURCE/ TERR OWNER | AU63: QUERY SOURCE/ TERR OWNER | AV63: QUERY SOURCE/ TERR OWNER | AW63: QUERY SOURCE/ TERR OWNER | AX63: SAMRO | AY63: QUERY SOURCE/ TERR OWNER
B64: ABRAMUS | C64: Licensor Pays | D64: SUISA | E64: SUISA | F64: SUISA | G64: SUISA | H64: SUISA | I64: SUISA | J64: SUISA | K64: SGAE | L64: SGAE | M64: SUISA | N64: SUISA | O64: SUISA | P64: SUISA | Q64: SUISA | R64: SUISA | S64: QUERY SOURCE/ TERR OWNER | T64: QUERY SOURCE/ TERR OWNER | U64: QUERY SOURCE/ TERR OWNER | V64: QUERY SOURCE/ TERR OWNER | W64: SOCAN | X64: ASCAP/BMI/SESAC/GMR | Y64: SADAIC | Z64: Latin Autor (Processed by BO) | AA64: ECAD | AB64: Latin Autor (Processed by BO) | AC64: Latin Autor (Processed by BO) | AD64: Latin Autor (Processed by BO) | AE64: Latin Autor (Processed by BO) | AF64: SACM | AG64: Latin Autor (Processed by BO) | AH64: Latin Autor (Processed by BO) | AI64: Latin Autor (Processed by BO) | AJ64: AMRA | AK64: AMRA | AL64: QUERY SOURCE/ TERR OWNER | AM64: QUERY SOURCE/ TERR OWNER | AN64: QUERY SOURCE/ TERR OWNER | AO64: QUERY SOURCE/ TERR OWNER | AP64: QUERY SOURCE/ TERR OWNER | AQ64: QUERY SOURCE/ TERR OWNER | AR64: QUERY SOURCE/ TERR OWNER | AS64: QUERY SOURCE/ TERR OWNER | AT64: QUERY SOURCE/ TERR OWNER | AU64: QUERY SOURCE/ TERR OWNER | AV64: QUERY SOURCE/ TERR OWNER | AW64: QUERY SOURCE/ TERR OWNER | AX64: SAMRO | AY64: QUERY SOURCE/ TERR OWNER
B65: ABRAMUS | C65: Kobalt Paid By | D65: SUISA | E65: SABAM | F65: SACEM | G65: GEMA | H65: SUISA | I65: BUMA-STEMRA | J65: STIM | K65: SGAE | L65: SGAE | M65: STIM | N65: SUISA | O65: MCPS-PRS | P65: IDM | Q65: D-Version | R65: Schubert | S65: QUERY SOURCE/ TERR OWNER | T65: QUERY SOURCE/ TERR OWNER | U65: QUERY SOURCE/ TERR OWNER | V65: QUERY SOURCE/ TERR OWNER | W65: SOCAN | X65: ASCAP/BMI/SESAC/GMR | Y65: SADAIC | Z65: No Membership | AA65: ABRAMUS | AB65: SCD | AC65: SAYCO | AD65: Briana Music | AE65: SAYCE | AF65: SACM | AG65: No Membership | AH65: APDAYC | AI65: AGADU | AJ65: AMRA | AK65: AMRA | AL65: QUERY SOURCE/ TERR OWNER | AM65: QUERY SOURCE/ TERR OWNER | AN65: QUERY SOURCE/ TERR OWNER | AO65: QUERY SOURCE/ TERR OWNER | AP65: QUERY SOURCE/ TERR OWNER | AQ65: QUERY SOURCE/ TERR OWNER | AR65: QUERY SOURCE/ TERR OWNER | AS65: QUERY SOURCE/ TERR OWNER | AT65: QUERY SOURCE/ TERR OWNER | AU65: QUERY SOURCE/ TERR OWNER | AV65: QUERY SOURCE/ TERR OWNER | AW65: QUERY SOURCE/ TERR OWNER | AX65: SAMRO | AY65: QUERY SOURCE/ TERR OWNER
A66: APDAYC | B66: APDAYC | C66: Licensed By | D66: QUERY SOURCE/ TERR OWNER | E66: ICE | F66: QUERY SOURCE/ TERR OWNER | G66: QUERY SOURCE/ TERR OWNER | H66: QUERY SOURCE/ TERR OWNER | I66: QUERY SOURCE/ TERR OWNER | J66: QUERY SOURCE/ TERR OWNER | K66: QUERY SOURCE/ TERR OWNER | L66: QUERY SOURCE/ TERR OWNER | M66: QUERY SOURCE/ TERR OWNER | N66: QUERY SOURCE/ TERR OWNER | O66: QUERY SOURCE/ TERR OWNER | P66: QUERY SOURCE/ TERR OWNER | Q66: QUERY SOURCE/ TERR OWNER | R66: QUERY SOURCE/ TERR OWNER | S66: QUERY SOURCE/ TERR OWNER | T66: QUERY SOURCE/ TERR OWNER | U66: QUERY SOURCE/ TERR OWNER | V66: QUERY SOURCE/ TERR OWNER | W66: SOCAN | X66: ASCAP/BMI/SESAC/GMR | Y66: SADAIC | Z66: Latin Autor | AA66: ECAD | AB66: Latin Autor | AC66: Latin Autor | AD66: Latin Autor | AE66: Latin Autor | AF66: SACM | AG66: Latin Autor | AH66: Latin Autor | AI66: Latin Autor | AJ66: QUERY SOURCE/ TERR OWNER | AK66: QUERY SOURCE/ TERR OWNER | AL66: QUERY SOURCE/ TERR OWNER | AM66: QUERY SOURCE/ TERR OWNER | AN66: QUERY SOURCE/ TERR OWNER | AO66: QUERY SOURCE/ TERR OWNER | AP66: QUERY SOURCE/ TERR OWNER | AQ66: QUERY SOURCE/ TERR OWNER | AR66: QUERY SOURCE/ TERR OWNER | AS66: QUERY SOURCE/ TERR OWNER | AT66: QUERY SOURCE/ TERR OWNER | AU66: QUERY SOURCE/ TERR OWNER | AV66: QUERY SOURCE/ TERR OWNER | AW66: QUERY SOURCE/ TERR OWNER | AX66: SAMRO | AY66: QUERY SOURCE/ TERR OWNER
B67: APDAYC | C67: Licensor Pays | D67: QUERY SOURCE/ TERR OWNER | E67: SABAM | F67: QUERY SOURCE/ TERR OWNER | G67: QUERY SOURCE/ TERR OWNER | H67: QUERY SOURCE/ TERR OWNER | I67: QUERY SOURCE/ TERR OWNER | J67: QUERY SOURCE/ TERR OWNER | K67: QUERY SOURCE/ TERR OWNER | L67: QUERY SOURCE/ TERR OWNER | M67: QUERY SOURCE/ TERR OWNER | N67: QUERY SOURCE/ TERR OWNER | O67: QUERY SOURCE/ TERR OWNER | P67: QUERY SOURCE/ TERR OWNER | Q67: QUERY SOURCE/ TERR OWNER | R67: QUERY SOURCE/ TERR OWNER | S67: QUERY SOURCE/ TERR OWNER | T67: QUERY SOURCE/ TERR OWNER | U67: QUERY SOURCE/ TERR OWNER | V67: QUERY SOURCE/ TERR OWNER | W67: SOCAN | X67: ASCAP/BMI/SESAC/GMR | Y67: SADAIC | Z67: Latin Autor (Processed by BO) | AA67: ECAD | AB67: Latin Autor (Processed by BO) | AC67: Latin Autor (Processed by BO) | AD67: Latin Autor (Processed by BO) | AE67: Latin Autor (Processed by BO) | AF67: SACM | AG67: Latin Autor (Processed by BO) | AH67: Latin Autor (Processed by BO) | AI67: Latin Autor (Processed by BO) | AJ67: QUERY SOURCE/ TERR OWNER | AK67: QUERY SOURCE/ TERR OWNER | AL67: QUERY SOURCE/ TERR OWNER | AM67: QUERY SOURCE/ TERR OWNER | AN67: QUERY SOURCE/ TERR OWNER | AO67: QUERY SOURCE/ TERR OWNER | AP67: QUERY SOURCE/ TERR OWNER | AQ67: QUERY SOURCE/ TERR OWNER | AR67: QUERY SOURCE/ TERR OWNER | AS67: QUERY SOURCE/ TERR OWNER | AT67: QUERY SOURCE/ TERR OWNER | AU67: QUERY SOURCE/ TERR OWNER | AV67: QUERY SOURCE/ TERR OWNER | AW67: QUERY SOURCE/ TERR OWNER | AX67: SAMRO | AY67: QUERY SOURCE/ TERR OWNER
B68: APDAYC | C68: Kobalt Paid By | D68: QUERY SOURCE/ TERR OWNER | E68: SABAM | F68: QUERY SOURCE/ TERR OWNER | G68: QUERY SOURCE/ TERR OWNER | H68: QUERY SOURCE/ TERR OWNER | I68: QUERY SOURCE/ TERR OWNER | J68: QUERY SOURCE/ TERR OWNER | K68: QUERY SOURCE/ TERR OWNER | L68: QUERY SOURCE/ TERR OWNER | M68: QUERY SOURCE/ TERR OWNER | N68: QUERY SOURCE/ TERR OWNER | O68: QUERY SOURCE/ TERR OWNER | P68: QUERY SOURCE/ TERR OWNER | Q68: QUERY SOURCE/ TERR OWNER | R68: QUERY SOURCE/ TERR OWNER | S68: QUERY SOURCE/ TERR OWNER | T68: QUERY SOURCE/ TERR OWNER | U68: QUERY SOURCE/ TERR OWNER | V68: QUERY SOURCE/ TERR OWNER | W68: SOCAN | X68: ASCAP/BMI/SESAC/GMR | Y68: SADAIC | Z68: No Membership | AA68: ABRAMUS | AB68: SCD | AC68: SAYCO | AD68: Briana Music | AE68: SAYCE | AF68: SACM | AG68: No Membership | AH68: APDAYC | AI68: AGADU | AJ68: QUERY SOURCE/ TERR OWNER | AK68: QUERY SOURCE/ TERR OWNER | AL68: QUERY SOURCE/ TERR OWNER | AM68: QUERY SOURCE/ TERR OWNER | AN68: QUERY SOURCE/ TERR OWNER | AO68: QUERY SOURCE/ TERR OWNER | AP68: QUERY SOURCE/ TERR OWNER | AQ68: QUERY SOURCE/ TERR OWNER | AR68: QUERY SOURCE/ TERR OWNER | AS68: QUERY SOURCE/ TERR OWNER | AT68: QUERY SOURCE/ TERR OWNER | AU68: QUERY SOURCE/ TERR OWNER | AV68: QUERY SOURCE/ TERR OWNER | AW68: QUERY SOURCE/ TERR OWNER | AX68: SAMRO | AY68: QUERY SOURCE/ TERR OWNER
A69: SACM | B69: SACM | C69: Licensed By | D69: ICE | E69: ICE | F69: ICE | G69: ICE | H69: ICE | I69: ICE | J69: ICE | K69: ICE | L69: ICE | M69: ICE | N69: ICE | O69: ICE | P69: ICE | Q69: ICE | R69: ICE | S69: ICE | T69: ICE | U69: ICE | V69: ICE | W69: SOCAN | X69: ASCAP/BMI/SESAC/GMR | Y69: SADAIC | Z69: Latin Autor | AA69: ECAD | AB69: Latin Autor | AC69: Latin Autor | AD69: Latin Autor | AE69: Latin Autor | AF69: SACM | AG69: Latin Autor | AH69: Latin Autor | AI69: Latin Autor | AJ69: QUERY SOURCE/ TERR OWNER | AK69: QUERY SOURCE/ TERR OWNER | AL69: QUERY SOURCE/ TERR OWNER | AM69: QUERY SOURCE/ TERR OWNER | AN69: QUERY SOURCE/ TERR OWNER | AO69: QUERY SOURCE/ TERR OWNER | AP69: QUERY SOURCE/ TERR OWNER | AQ69: QUERY SOURCE/ TERR OWNER | AR69: QUERY SOURCE/ TERR OWNER | AS69: QUERY SOURCE/ TERR OWNER | AT69: QUERY SOURCE/ TERR OWNER | AU69: QUERY SOURCE/ TERR OWNER | AV69: QUERY SOURCE/ TERR OWNER | AW69: QUERY SOURCE/ TERR OWNER | AX69: SAMRO | AY69: QUERY SOURCE/ TERR OWNER
B70: SACM | C70: Licensor Pays | D70: MCPS-PRS | E70: MCPS-PRS | F70: MCPS-PRS | G70: MCPS-PRS | H70: MCPS-PRS | I70: MCPS-PRS | J70: MCPS-PRS | K70: MCPS-PRS | L70: MCPS-PRS | M70: MCPS-PRS | N70: MCPS-PRS | O70: MCPS-PRS | P70: MCPS-PRS | Q70: MCPS-PRS | R70: MCPS-PRS | S70: MCPS-PRS | T70: MCPS-PRS | U70: MCPS-PRS | V70: MCPS-PRS | W70: SOCAN | X70: ASCAP/BMI/SESAC/GMR | Y70: SADAIC | Z70: Latin Autor (Processed by BO) | AA70: ECAD | AB70: Latin Autor (Processed by BO) | AC70: Latin Autor (Processed by BO) | AD70: Latin Autor (Processed by BO) | AE70: Latin Autor (Processed by BO) | AF70: SACM | AG70: Latin Autor (Processed by BO) | AH70: Latin Autor (Processed by BO) | AI70: Latin Autor (Processed by BO) | AJ70: QUERY SOURCE/ TERR OWNER | AK70: QUERY SOURCE/ TERR OWNER | AL70: QUERY SOURCE/ TERR OWNER | AM70: QUERY SOURCE/ TERR OWNER | AN70: QUERY SOURCE/ TERR OWNER | AO70: QUERY SOURCE/ TERR OWNER | AP70: QUERY SOURCE/ TERR OWNER | AQ70: QUERY SOURCE/ TERR OWNER | AR70: QUERY SOURCE/ TERR OWNER | AS70: QUERY SOURCE/ TERR OWNER | AT70: QUERY SOURCE/ TERR OWNER | AU70: QUERY SOURCE/ TERR OWNER | AV70: QUERY SOURCE/ TERR OWNER | AW70: QUERY SOURCE/ TERR OWNER | AX70: SAMRO | AY70: QUERY SOURCE/ TERR OWNER
B71: SACM | C71: Kobalt Paid By | D71: MCPS-PRS | E71: MCPS-PRS | F71: MCPS-PRS | G71: MCPS-PRS | H71: MCPS-PRS | I71: MCPS-PRS | J71: MCPS-PRS | K71: MCPS-PRS | L71: MCPS-PRS | M71: MCPS-PRS | N71: MCPS-PRS | O71: MCPS-PRS | P71: IDM | Q71: D-Version | R71: Schubert | S71: Blue Sun | T71: Dalia | U71: Pop Arabia | V71: Zeplin | W71: SOCAN | X71: ASCAP/BMI/SESAC/GMR | Y71: SADAIC | Z71: No Membership | AA71: ABRAMUS | AB71: SCD | AC71: SAYCO | AD71: Briana Music | AE71: SAYCE | AF71: SACM | AG71: No Membership | AH71: APDAYC | AI71: AGADU | AJ71: QUERY SOURCE/ TERR OWNER | AK71: QUERY SOURCE/ TERR OWNER | AL71: QUERY SOURCE/ TERR OWNER | AM71: QUERY SOURCE/ TERR OWNER | AN71: QUERY SOURCE/ TERR OWNER | AO71: QUERY SOURCE/ TERR OWNER | AP71: QUERY SOURCE/ TERR OWNER | AQ71: QUERY SOURCE/ TERR OWNER | AR71: QUERY SOURCE/ TERR OWNER | AS71: QUERY SOURCE/ TERR OWNER | AT71: QUERY SOURCE/ TERR OWNER | AU71: QUERY SOURCE/ TERR OWNER | AV71: QUERY SOURCE/ TERR OWNER | AW71: QUERY SOURCE/ TERR OWNER | AX71: SAMRO | AY71: QUERY SOURCE/ TERR OWNER
A72: SADAIC | B72: SADAIC | C72: Licensed By | D72: QUERY SOURCE/ TERR OWNER | E72: ICE | F72: QUERY SOURCE/ TERR OWNER | G72: QUERY SOURCE/ TERR OWNER | H72: QUERY SOURCE/ TERR OWNER | I72: QUERY SOURCE/ TERR OWNER | J72: QUERY SOURCE/ TERR OWNER | K72: QUERY SOURCE/ TERR OWNER | L72: QUERY SOURCE/ TERR OWNER | M72: QUERY SOURCE/ TERR OWNER | N72: QUERY SOURCE/ TERR OWNER | O72: QUERY SOURCE/ TERR OWNER | P72: QUERY SOURCE/ TERR OWNER | Q72: QUERY SOURCE/ TERR OWNER | R72: QUERY SOURCE/ TERR OWNER | S72: QUERY SOURCE/ TERR OWNER | T72: QUERY SOURCE/ TERR OWNER | U72: QUERY SOURCE/ TERR OWNER | V72: QUERY SOURCE/ TERR OWNER | W72: SOCAN | X72: ASCAP/BMI/SESAC/GMR | Y72: SADAIC | Z72: Latin Autor | AA72: ECAD | AB72: Latin Autor | AC72: Latin Autor | AD72: Latin Autor | AE72: Latin Autor | AF72: SACM | AG72: Latin Autor | AH72: Latin Autor | AI72: Latin Autor | AJ72: QUERY SOURCE/ TERR OWNER | AK72: QUERY SOURCE/ TERR OWNER | AL72: QUERY SOURCE/ TERR OWNER | AM72: QUERY SOURCE/ TERR OWNER | AN72: QUERY SOURCE/ TERR OWNER | AO72: QUERY SOURCE/ TERR OWNER | AP72: QUERY SOURCE/ TERR OWNER | AQ72: QUERY SOURCE/ TERR OWNER | AR72: QUERY SOURCE/ TERR OWNER | AS72: QUERY SOURCE/ TERR OWNER | AT72: QUERY SOURCE/ TERR OWNER | AU72: QUERY SOURCE/ TERR OWNER | AV72: QUERY SOURCE/ TERR OWNER | AW72: QUERY SOURCE/ TERR OWNER | AX72: SAMRO | AY72: QUERY SOURCE/ TERR OWNER
B73: SADAIC | C73: Licensor Pays | D73: QUERY SOURCE/ TERR OWNER | E73: SABAM | F73: QUERY SOURCE/ TERR OWNER | G73: QUERY SOURCE/ TERR OWNER | H73: QUERY SOURCE/ TERR OWNER | I73: QUERY SOURCE/ TERR OWNER | J73: QUERY SOURCE/ TERR OWNER | K73: QUERY SOURCE/ TERR OWNER | L73: QUERY SOURCE/ TERR OWNER | M73: QUERY SOURCE/ TERR OWNER | N73: QUERY SOURCE/ TERR OWNER | O73: QUERY SOURCE/ TERR OWNER | P73: QUERY SOURCE/ TERR OWNER | Q73: QUERY SOURCE/ TERR OWNER | R73: QUERY SOURCE/ TERR OWNER | S73: QUERY SOURCE/ TERR OWNER | T73: QUERY SOURCE/ TERR OWNER | U73: QUERY SOURCE/ TERR OWNER | V73: QUERY SOURCE/ TERR OWNER | W73: SOCAN | X73: ASCAP/BMI/SESAC/GMR | Y73: SADAIC | Z73: Latin Autor (Processed by BO) | AA73: ECAD | AB73: Latin Autor (Processed by BO) | AC73: Latin Autor (Processed by BO) | AD73: Latin Autor (Processed by BO) | AE73: Latin Autor (Processed by BO) | AF73: SACM | AG73: Latin Autor (Processed by BO) | AH73: Latin Autor (Processed by BO) | AI73: Latin Autor (Processed by BO) | AJ73: QUERY SOURCE/ TERR OWNER | AK73: QUERY SOURCE/ TERR OWNER | AL73: QUERY SOURCE/ TERR OWNER | AM73: QUERY SOURCE/ TERR OWNER | AN73: QUERY SOURCE/ TERR OWNER | AO73: QUERY SOURCE/ TERR OWNER | AP73: QUERY SOURCE/ TERR OWNER | AQ73: QUERY SOURCE/ TERR OWNER | AR73: QUERY SOURCE/ TERR OWNER | AS73: QUERY SOURCE/ TERR OWNER | AT73: QUERY SOURCE/ TERR OWNER | AU73: QUERY SOURCE/ TERR OWNER | AV73: QUERY SOURCE/ TERR OWNER | AW73: QUERY SOURCE/ TERR OWNER | AX73: SAMRO | AY73: QUERY SOURCE/ TERR OWNER
B74: SADAIC | C74: Kobalt Paid By | D74: QUERY SOURCE/ TERR OWNER | E74: SABAM | F74: QUERY SOURCE/ TERR OWNER | G74: QUERY SOURCE/ TERR OWNER | H74: QUERY SOURCE/ TERR OWNER | I74: QUERY SOURCE/ TERR OWNER | J74: QUERY SOURCE/ TERR OWNER | K74: QUERY SOURCE/ TERR OWNER | L74: QUERY SOURCE/ TERR OWNER | M74: QUERY SOURCE/ TERR OWNER | N74: QUERY SOURCE/ TERR OWNER | O74: QUERY SOURCE/ TERR OWNER | P74: QUERY SOURCE/ TERR OWNER | Q74: QUERY SOURCE/ TERR OWNER | R74: QUERY SOURCE/ TERR OWNER | S74: QUERY SOURCE/ TERR OWNER | T74: QUERY SOURCE/ TERR OWNER | U74: QUERY SOURCE/ TERR OWNER | V74: QUERY SOURCE/ TERR OWNER | W74: SOCAN | X74: ASCAP/BMI/SESAC/GMR | Y74: SADAIC | Z74: No Membership | AA74: ABRAMUS | AB74: SCD | AC74: SAYCO | AD74: Briana Music | AE74: SAYCE | AF74: SACM | AG74: No Membership | AH74: APDAYC | AI74: AGADU | AJ74: QUERY SOURCE/ TERR OWNER | AK74: QUERY SOURCE/ TERR OWNER | AL74: QUERY SOURCE/ TERR OWNER | AM74: QUERY SOURCE/ TERR OWNER | AN74: QUERY SOURCE/ TERR OWNER | AO74: QUERY SOURCE/ TERR OWNER | AP74: QUERY SOURCE/ TERR OWNER | AQ74: QUERY SOURCE/ TERR OWNER | AR74: QUERY SOURCE/ TERR OWNER | AS74: QUERY SOURCE/ TERR OWNER | AT74: QUERY SOURCE/ TERR OWNER | AU74: QUERY SOURCE/ TERR OWNER | AV74: QUERY SOURCE/ TERR OWNER | AW74: QUERY SOURCE/ TERR OWNER | AX74: SAMRO | AY74: QUERY SOURCE/ TERR OWNER
A75: SAYCO | B75: SAYCO | C75: Licensed By | D75: QUERY SOURCE/ TERR OWNER | E75: ICE | F75: QUERY SOURCE/ TERR OWNER | G75: QUERY SOURCE/ TERR OWNER | H75: QUERY SOURCE/ TERR OWNER | I75: QUERY SOURCE/ TERR OWNER | J75: QUERY SOURCE/ TERR OWNER | K75: QUERY SOURCE/ TERR OWNER | L75: QUERY SOURCE/ TERR OWNER | M75: QUERY SOURCE/ TERR OWNER | N75: QUERY SOURCE/ TERR OWNER | O75: QUERY SOURCE/ TERR OWNER | P75: QUERY SOURCE/ TERR OWNER | Q75: QUERY SOURCE/ TERR OWNER | R75: QUERY SOURCE/ TERR OWNER | S75: QUERY SOURCE/ TERR OWNER | T75: QUERY SOURCE/ TERR OWNER | U75: QUERY SOURCE/ TERR OWNER | V75: QUERY SOURCE/ TERR OWNER | W75: SOCAN | X75: ASCAP/BMI/SESAC/GMR | Y75: SADAIC | Z75: Latin Autor | AA75: ECAD | AB75: Latin Autor | AC75: Latin Autor | AD75: Latin Autor | AE75: Latin Autor | AF75: SACM | AG75: Latin Autor | AH75: Latin Autor | AI75: Latin Autor | AJ75: AMRA | AK75: AMRA | AL75: QUERY SOURCE/ TERR OWNER | AM75: QUERY SOURCE/ TERR OWNER | AN75: QUERY SOURCE/ TERR OWNER | AO75: QUERY SOURCE/ TERR OWNER | AP75: QUERY SOURCE/ TERR OWNER | AQ75: QUERY SOURCE/ TERR OWNER | AR75: QUERY SOURCE/ TERR OWNER | AS75: QUERY SOURCE/ TERR OWNER | AT75: QUERY SOURCE/ TERR OWNER | AU75: QUERY SOURCE/ TERR OWNER | AV75: QUERY SOURCE/ TERR OWNER | AW75: QUERY SOURCE/ TERR OWNER | AX75: SAMRO | AY75: QUERY SOURCE/ TERR OWNER
B76: SAYCO | C76: Licensor Pays | D76: QUERY SOURCE/ TERR OWNER | E76: SABAM | F76: QUERY SOURCE/ TERR OWNER | G76: QUERY SOURCE/ TERR OWNER | H76: QUERY SOURCE/ TERR OWNER | I76: QUERY SOURCE/ TERR OWNER | J76: QUERY SOURCE/ TERR OWNER | K76: QUERY SOURCE/ TERR OWNER | L76: QUERY SOURCE/ TERR OWNER | M76: QUERY SOURCE/ TERR OWNER | N76: QUERY SOURCE/ TERR OWNER | O76: QUERY SOURCE/ TERR OWNER | P76: QUERY SOURCE/ TERR OWNER | Q76: QUERY SOURCE/ TERR OWNER | R76: QUERY SOURCE/ TERR OWNER | S76: QUERY SOURCE/ TERR OWNER | T76: QUERY SOURCE/ TERR OWNER | U76: QUERY SOURCE/ TERR OWNER | V76: QUERY SOURCE/ TERR OWNER | W76: SOCAN | X76: ASCAP/BMI/SESAC/GMR | Y76: SADAIC | Z76: Latin Autor (Processed by BO) | AA76: ECAD | AB76: Latin Autor (Processed by BO) | AC76: Latin Autor (Processed by BO) | AD76: Latin Autor (Processed by BO) | AE76: Latin Autor (Processed by BO) | AF76: SACM | AG76: Latin Autor (Processed by BO) | AH76: Latin Autor (Processed by BO) | AI76: Latin Autor (Processed by BO) | AJ76: AMRA | AK76: AMRA | AL76: QUERY SOURCE/ TERR OWNER | AM76: QUERY SOURCE/ TERR OWNER | AN76: QUERY SOURCE/ TERR OWNER | AO76: QUERY SOURCE/ TERR OWNER | AP76: QUERY SOURCE/ TERR OWNER | AQ76: QUERY SOURCE/ TERR OWNER | AR76: QUERY SOURCE/ TERR OWNER | AS76: QUERY SOURCE/ TERR OWNER | AT76: QUERY SOURCE/ TERR OWNER | AU76: QUERY SOURCE/ TERR OWNER | AV76: QUERY SOURCE/ TERR OWNER | AW76: QUERY SOURCE/ TERR OWNER | AX76: SAMRO | AY76: QUERY SOURCE/ TERR OWNER
B77: SAYCO | C77: Kobalt Paid By | D77: QUERY SOURCE/ TERR OWNER | E77: SABAM | F77: QUERY SOURCE/ TERR OWNER | G77: QUERY SOURCE/ TERR OWNER | H77: QUERY SOURCE/ TERR OWNER | I77: QUERY SOURCE/ TERR OWNER | J77: QUERY SOURCE/ TERR OWNER | K77: QUERY SOURCE/ TERR OWNER | L77: QUERY SOURCE/ TERR OWNER | M77: QUERY SOURCE/ TERR OWNER | N77: QUERY SOURCE/ TERR OWNER | O77: QUERY SOURCE/ TERR OWNER | P77: QUERY SOURCE/ TERR OWNER | Q77: QUERY SOURCE/ TERR OWNER | R77: QUERY SOURCE/ TERR OWNER | S77: QUERY SOURCE/ TERR OWNER | T77: QUERY SOURCE/ TERR OWNER | U77: QUERY SOURCE/ TERR OWNER | V77: QUERY SOURCE/ TERR OWNER | W77: SOCAN | X77: ASCAP/BMI/SESAC/GMR | Y77: SADAIC | Z77: No Membership | AA77: ABRAMUS | AB77: SCD | AC77: SAYCO | AD77: Briana Music | AE77: SAYCE | AF77: SACM | AG77: No Membership | AH77: APDAYC | AI77: AGADU | AJ77: AMRA | AK77: AMRA | AL77: QUERY SOURCE/ TERR OWNER | AM77: QUERY SOURCE/ TERR OWNER | AN77: QUERY SOURCE/ TERR OWNER | AO77: QUERY SOURCE/ TERR OWNER | AP77: QUERY SOURCE/ TERR OWNER | AQ77: QUERY SOURCE/ TERR OWNER | AR77: QUERY SOURCE/ TERR OWNER | AS77: QUERY SOURCE/ TERR OWNER | AT77: QUERY SOURCE/ TERR OWNER | AU77: QUERY SOURCE/ TERR OWNER | AV77: QUERY SOURCE/ TERR OWNER | AW77: QUERY SOURCE/ TERR OWNER | AX77: SAMRO | AY77: QUERY SOURCE/ TERR OWNER
A78: SCD | B78: SCD | C78: Licensed By | D78: QUERY SOURCE/ TERR OWNER | E78: ICE | F78: QUERY SOURCE/ TERR OWNER | G78: QUERY SOURCE/ TERR OWNER | H78: QUERY SOURCE/ TERR OWNER | I78: QUERY SOURCE/ TERR OWNER | J78: QUERY SOURCE/ TERR OWNER | K78: QUERY SOURCE/ TERR OWNER | L78: QUERY SOURCE/ TERR OWNER | M78: QUERY SOURCE/ TERR OWNER | N78: QUERY SOURCE/ TERR OWNER | O78: QUERY SOURCE/ TERR OWNER | P78: QUERY SOURCE/ TERR OWNER | Q78: QUERY SOURCE/ TERR OWNER | R78: QUERY SOURCE/ TERR OWNER | S78: QUERY SOURCE/ TERR OWNER | T78: QUERY SOURCE/ TERR OWNER | U78: QUERY SOURCE/ TERR OWNER | V78: QUERY SOURCE/ TERR OWNER | W78: SOCAN | X78: ASCAP/BMI/SESAC/GMR | Y78: SADAIC | Z78: Latin Autor | AA78: ECAD | AB78: Latin Autor | AC78: Latin Autor | AD78: Latin Autor | AE78: Latin Autor | AF78: SACM | AG78: Latin Autor | AH78: Latin Autor | AI78: Latin Autor | AJ78: QUERY SOURCE/ TERR OWNER | AK78: QUERY SOURCE/ TERR OWNER | AL78: QUERY SOURCE/ TERR OWNER | AM78: QUERY SOURCE/ TERR OWNER | AN78: QUERY SOURCE/ TERR OWNER | AO78: QUERY SOURCE/ TERR OWNER | AP78: QUERY SOURCE/ TERR OWNER | AQ78: QUERY SOURCE/ TERR OWNER | AR78: QUERY SOURCE/ TERR OWNER | AS78: QUERY SOURCE/ TERR OWNER | AT78: QUERY SOURCE/ TERR OWNER | AU78: QUERY SOURCE/ TERR OWNER | AV78: QUERY SOURCE/ TERR OWNER | AW78: QUERY SOURCE/ TERR OWNER | AX78: SAMRO | AY78: QUERY SOURCE/ TERR OWNER
B79: SCD | C79: Licensor Pays | D79: QUERY SOURCE/ TERR OWNER | E79: SABAM | F79: QUERY SOURCE/ TERR OWNER | G79: QUERY SOURCE/ TERR OWNER | H79: QUERY SOURCE/ TERR OWNER | I79: QUERY SOURCE/ TERR OWNER | J79: QUERY SOURCE/ TERR OWNER | K79: QUERY SOURCE/ TERR OWNER | L79: QUERY SOURCE/ TERR OWNER | M79: QUERY SOURCE/ TERR OWNER | N79: QUERY SOURCE/ TERR OWNER | O79: QUERY SOURCE/ TERR OWNER | P79: QUERY SOURCE/ TERR OWNER | Q79: QUERY SOURCE/ TERR OWNER | R79: QUERY SOURCE/ TERR OWNER | S79: QUERY SOURCE/ TERR OWNER | T79: QUERY SOURCE/ TERR OWNER | U79: QUERY SOURCE/ TERR OWNER | V79: QUERY SOURCE/ TERR OWNER | W79: SOCAN | X79: ASCAP/BMI/SESAC/GMR | Y79: SADAIC | Z79: Latin Autor (Processed by BO) | AA79: ECAD | AB79: Latin Autor (Processed by BO) | AC79: Latin Autor (Processed by BO) | AD79: Latin Autor (Processed by BO) | AE79: Latin Autor (Processed by BO) | AF79: SACM | AG79: Latin Autor (Processed by BO) | AH79: Latin Autor (Processed by BO) | AI79: Latin Autor (Processed by BO) | AJ79: QUERY SOURCE/ TERR OWNER | AK79: QUERY SOURCE/ TERR OWNER | AL79: QUERY SOURCE/ TERR OWNER | AM79: QUERY SOURCE/ TERR OWNER | AN79: QUERY SOURCE/ TERR OWNER | AO79: QUERY SOURCE/ TERR OWNER | AP79: QUERY SOURCE/ TERR OWNER | AQ79: QUERY SOURCE/ TERR OWNER | AR79: QUERY SOURCE/ TERR OWNER | AS79: QUERY SOURCE/ TERR OWNER | AT79: QUERY SOURCE/ TERR OWNER | AU79: QUERY SOURCE/ TERR OWNER | AV79: QUERY SOURCE/ TERR OWNER | AW79: QUERY SOURCE/ TERR OWNER | AX79: SAMRO | AY79: QUERY SOURCE/ TERR OWNER
B80: SCD | C80: Kobalt Paid By | D80: QUERY SOURCE/ TERR OWNER | E80: SABAM | F80: QUERY SOURCE/ TERR OWNER | G80: QUERY SOURCE/ TERR OWNER | H80: QUERY SOURCE/ TERR OWNER | I80: QUERY SOURCE/ TERR OWNER | J80: QUERY SOURCE/ TERR OWNER | K80: QUERY SOURCE/ TERR OWNER | L80: QUERY SOURCE/ TERR OWNER | M80: QUERY SOURCE/ TERR OWNER | N80: QUERY SOURCE/ TERR OWNER | O80: QUERY SOURCE/ TERR OWNER | P80: QUERY SOURCE/ TERR OWNER | Q80: QUERY SOURCE/ TERR OWNER | R80: QUERY SOURCE/ TERR OWNER | S80: QUERY SOURCE/ TERR OWNER | T80: QUERY SOURCE/ TERR OWNER | U80: QUERY SOURCE/ TERR OWNER | V80: QUERY SOURCE/ TERR OWNER | W80: SOCAN | X80: ASCAP/BMI/SESAC/GMR | Y80: SADAIC | Z80: No Membership | AA80: ABRAMUS | AB80: SCD | AC80: SAYCO | AD80: Briana Music | AE80: SAYCE | AF80: SACM | AG80: No Membership | AH80: APDAYC | AI80: AGADU | AJ80: QUERY SOURCE/ TERR OWNER | AK80: QUERY SOURCE/ TERR OWNER | AL80: QUERY SOURCE/ TERR OWNER | AM80: QUERY SOURCE/ TERR OWNER | AN80: QUERY SOURCE/ TERR OWNER | AO80: QUERY SOURCE/ TERR OWNER | AP80: QUERY SOURCE/ TERR OWNER | AQ80: QUERY SOURCE/ TERR OWNER | AR80: QUERY SOURCE/ TERR OWNER | AS80: QUERY SOURCE/ TERR OWNER | AT80: QUERY SOURCE/ TERR OWNER | AU80: QUERY SOURCE/ TERR OWNER | AV80: QUERY SOURCE/ TERR OWNER | AW80: QUERY SOURCE/ TERR OWNER | AX80: SAMRO | AY80: QUERY SOURCE/ TERR OWNER
A81: Asian Rep
A82: CASH | B82: CASH | C82: Licensed By | D82: QUERY SOURCE/ TERR OWNER | E82: ICE | F82: QUERY SOURCE/ TERR OWNER | G82: QUERY SOURCE/ TERR OWNER | H82: QUERY SOURCE/ TERR OWNER | I82: QUERY SOURCE/ TERR OWNER | J82: QUERY SOURCE/ TERR OWNER | K82: QUERY SOURCE/ TERR OWNER | L82: QUERY SOURCE/ TERR OWNER | M82: QUERY SOURCE/ TERR OWNER | N82: QUERY SOURCE/ TERR OWNER | O82: QUERY SOURCE/ TERR OWNER | P82: QUERY SOURCE/ TERR OWNER | Q82: QUERY SOURCE/ TERR OWNER | R82: QUERY SOURCE/ TERR OWNER | S82: QUERY SOURCE/ TERR OWNER | T82: QUERY SOURCE/ TERR OWNER | U82: QUERY SOURCE/ TERR OWNER | V82: QUERY SOURCE/ TERR OWNER | W82: SOCAN | X82: ASCAP/BMI/SESAC/GMR | Y82: SADAIC | Z82: Latin Autor | AA82: ECAD | AB82: Latin Autor | AC82: Latin Autor | AD82: Latin Autor | AE82: Latin Autor | AF82: SACM | AG82: Latin Autor | AH82: Latin Autor | AI82: Latin Autor | AJ82: AMRA | AK82: AMRA | AL82: QUERY SOURCE/ TERR OWNER | AM82: QUERY SOURCE/ TERR OWNER | AN82: QUERY SOURCE/ TERR OWNER | AO82: QUERY SOURCE/ TERR OWNER | AP82: QUERY SOURCE/ TERR OWNER | AQ82: QUERY SOURCE/ TERR OWNER | AR82: QUERY SOURCE/ TERR OWNER | AS82: QUERY SOURCE/ TERR OWNER | AT82: QUERY SOURCE/ TERR OWNER | AU82: QUERY SOURCE/ TERR OWNER | AV82: QUERY SOURCE/ TERR OWNER | AW82: QUERY SOURCE/ TERR OWNER | AX82: SAMRO | AY82: QUERY SOURCE/ TERR OWNER
B83: CASH | C83: Licensor Pays | D83: QUERY SOURCE/ TERR OWNER | E83: SABAM | F83: QUERY SOURCE/ TERR OWNER | G83: QUERY SOURCE/ TERR OWNER | H83: QUERY SOURCE/ TERR OWNER | I83: QUERY SOURCE/ TERR OWNER | J83: QUERY SOURCE/ TERR OWNER | K83: QUERY SOURCE/ TERR OWNER | L83: QUERY SOURCE/ TERR OWNER | M83: QUERY SOURCE/ TERR OWNER | N83: QUERY SOURCE/ TERR OWNER | O83: QUERY SOURCE/ TERR OWNER | P83: QUERY SOURCE/ TERR OWNER | Q83: QUERY SOURCE/ TERR OWNER | R83: QUERY SOURCE/ TERR OWNER | S83: QUERY SOURCE/ TERR OWNER | T83: QUERY SOURCE/ TERR OWNER | U83: QUERY SOURCE/ TERR OWNER | V83: QUERY SOURCE/ TERR OWNER | W83: SOCAN | X83: ASCAP/BMI/SESAC/GMR | Y83: SADAIC | Z83: Latin Autor (Processed by BO) | AA83: ECAD | AB83: Latin Autor (Processed by BO) | AC83: Latin Autor (Processed by BO) | AD83: Latin Autor (Processed by BO) | AE83: Latin Autor (Processed by BO) | AF83: SACM | AG83: Latin Autor (Processed by BO) | AH83: Latin Autor (Processed by BO) | AI83: Latin Autor (Processed by BO) | AJ83: AMRA | AK83: AMRA | AL83: QUERY SOURCE/ TERR OWNER | AM83: QUERY SOURCE/ TERR OWNER | AN83: QUERY SOURCE/ TERR OWNER | AO83: QUERY SOURCE/ TERR OWNER | AP83: QUERY SOURCE/ TERR OWNER | AQ83: QUERY SOURCE/ TERR OWNER | AR83: QUERY SOURCE/ TERR OWNER | AS83: QUERY SOURCE/ TERR OWNER | AT83: QUERY SOURCE/ TERR OWNER | AU83: QUERY SOURCE/ TERR OWNER | AV83: QUERY SOURCE/ TERR OWNER | AW83: QUERY SOURCE/ TERR OWNER | AX83: SAMRO | AY83: QUERY SOURCE/ TERR OWNER
B84: CASH | C84: Kobalt Paid By | D84: QUERY SOURCE/ TERR OWNER | E84: SABAM | F84: QUERY SOURCE/ TERR OWNER | G84: QUERY SOURCE/ TERR OWNER | H84: QUERY SOURCE/ TERR OWNER | I84: QUERY SOURCE/ TERR OWNER | J84: QUERY SOURCE/ TERR OWNER | K84: QUERY SOURCE/ TERR OWNER | L84: QUERY SOURCE/ TERR OWNER | M84: QUERY SOURCE/ TERR OWNER | N84: QUERY SOURCE/ TERR OWNER | O84: QUERY SOURCE/ TERR OWNER | P84: QUERY SOURCE/ TERR OWNER | Q84: QUERY SOURCE/ TERR OWNER | R84: QUERY SOURCE/ TERR OWNER | S84: QUERY SOURCE/ TERR OWNER | T84: QUERY SOURCE/ TERR OWNER | U84: QUERY SOURCE/ TERR OWNER | V84: QUERY SOURCE/ TERR OWNER | W84: SOCAN | X84: ASCAP/BMI/SESAC/GMR | Y84: SADAIC | Z84: No Membership | AA84: ABRAMUS | AB84: SCD | AC84: SAYCO | AD84: Briana Music | AE84: SAYCE | AF84: SACM | AG84: No Membership | AH84: APDAYC | AI84: AGADU | AJ84: AMRA | AK84: AMRA | AL84: QUERY SOURCE/ TERR OWNER | AM84: QUERY SOURCE/ TERR OWNER | AN84: QUERY SOURCE/ TERR OWNER | AO84: QUERY SOURCE/ TERR OWNER | AP84: QUERY SOURCE/ TERR OWNER | AQ84: QUERY SOURCE/ TERR OWNER | AR84: QUERY SOURCE/ TERR OWNER | AS84: QUERY SOURCE/ TERR OWNER | AT84: QUERY SOURCE/ TERR OWNER | AU84: QUERY SOURCE/ TERR OWNER | AV84: QUERY SOURCE/ TERR OWNER | AW84: QUERY SOURCE/ TERR OWNER | AX84: SAMRO | AY84: QUERY SOURCE/ TERR OWNER
A85: JASRAC | B85: JASRAC | C85: Licensed By | D85: QUERY SOURCE/ TERR OWNER | E85: ICE | F85: QUERY SOURCE/ TERR OWNER | G85: QUERY SOURCE/ TERR OWNER | H85: QUERY SOURCE/ TERR OWNER | I85: QUERY SOURCE/ TERR OWNER | J85: QUERY SOURCE/ TERR OWNER | K85: QUERY SOURCE/ TERR OWNER | L85: QUERY SOURCE/ TERR OWNER | M85: QUERY SOURCE/ TERR OWNER | N85: QUERY SOURCE/ TERR OWNER | O85: QUERY SOURCE/ TERR OWNER | P85: QUERY SOURCE/ TERR OWNER | Q85: QUERY SOURCE/ TERR OWNER | R85: QUERY SOURCE/ TERR OWNER | S85: QUERY SOURCE/ TERR OWNER | T85: QUERY SOURCE/ TERR OWNER | U85: QUERY SOURCE/ TERR OWNER | V85: QUERY SOURCE/ TERR OWNER | W85: SOCAN | X85: ASCAP/BMI/SESAC/GMR | Y85: SADAIC | Z85: Latin Autor | AA85: ECAD | AB85: Latin Autor | AC85: Latin Autor | AD85: Latin Autor | AE85: Latin Autor | AF85: SACM | AG85: Latin Autor | AH85: Latin Autor | AI85: Latin Autor | AJ85: AMRA | AK85: AMRA | AL85: QUERY SOURCE/ TERR OWNER | AM85: QUERY SOURCE/ TERR OWNER | AN85: QUERY SOURCE/ TERR OWNER | AO85: QUERY SOURCE/ TERR OWNER | AP85: QUERY SOURCE/ TERR OWNER | AQ85: QUERY SOURCE/ TERR OWNER | AR85: QUERY SOURCE/ TERR OWNER | AS85: QUERY SOURCE/ TERR OWNER | AT85: QUERY SOURCE/ TERR OWNER | AU85: QUERY SOURCE/ TERR OWNER | AV85: QUERY SOURCE/ TERR OWNER | AW85: QUERY SOURCE/ TERR OWNER | AX85: SAMRO | AY85: QUERY SOURCE/ TERR OWNER
B86: JASRAC | C86: Licensor Pays | D86: QUERY SOURCE/ TERR OWNER | E86: SABAM | F86: QUERY SOURCE/ TERR OWNER | G86: QUERY SOURCE/ TERR OWNER | H86: QUERY SOURCE/ TERR OWNER | I86: QUERY SOURCE/ TERR OWNER | J86: QUERY SOURCE/ TERR OWNER | K86: QUERY SOURCE/ TERR OWNER | L86: QUERY SOURCE/ TERR OWNER | M86: QUERY SOURCE/ TERR OWNER | N86: QUERY SOURCE/ TERR OWNER | O86: QUERY SOURCE/ TERR OWNER | P86: QUERY SOURCE/ TERR OWNER | Q86: QUERY SOURCE/ TERR OWNER | R86: QUERY SOURCE/ TERR OWNER | S86: QUERY SOURCE/ TERR OWNER | T86: QUERY SOURCE/ TERR OWNER | U86: QUERY SOURCE/ TERR OWNER | V86: QUERY SOURCE/ TERR OWNER | W86: SOCAN | X86: ASCAP/BMI/SESAC/GMR | Y86: SADAIC | Z86: Latin Autor (Processed by BO) | AA86: ECAD | AB86: Latin Autor (Processed by BO) | AC86: Latin Autor (Processed by BO) | AD86: Latin Autor (Processed by BO) | AE86: Latin Autor (Processed by BO) | AF86: SACM | AG86: Latin Autor (Processed by BO) | AH86: Latin Autor (Processed by BO) | AI86: Latin Autor (Processed by BO) | AJ86: AMRA | AK86: AMRA | AL86: QUERY SOURCE/ TERR OWNER | AM86: QUERY SOURCE/ TERR OWNER | AN86: QUERY SOURCE/ TERR OWNER | AO86: QUERY SOURCE/ TERR OWNER | AP86: QUERY SOURCE/ TERR OWNER | AQ86: QUERY SOURCE/ TERR OWNER | AR86: QUERY SOURCE/ TERR OWNER | AS86: QUERY SOURCE/ TERR OWNER | AT86: QUERY SOURCE/ TERR OWNER | AU86: QUERY SOURCE/ TERR OWNER | AV86: QUERY SOURCE/ TERR OWNER | AW86: QUERY SOURCE/ TERR OWNER | AX86: SAMRO | AY86: QUERY SOURCE/ TERR OWNER
B87: JASRAC | C87: Kobalt Paid By | D87: QUERY SOURCE/ TERR OWNER | E87: SABAM | F87: QUERY SOURCE/ TERR OWNER | G87: QUERY SOURCE/ TERR OWNER | H87: QUERY SOURCE/ TERR OWNER | I87: QUERY SOURCE/ TERR OWNER | J87: QUERY SOURCE/ TERR OWNER | K87: QUERY SOURCE/ TERR OWNER | L87: QUERY SOURCE/ TERR OWNER | M87: QUERY SOURCE/ TERR OWNER | N87: QUERY SOURCE/ TERR OWNER | O87: QUERY SOURCE/ TERR OWNER | P87: QUERY SOURCE/ TERR OWNER | Q87: QUERY SOURCE/ TERR OWNER | R87: QUERY SOURCE/ TERR OWNER | S87: QUERY SOURCE/ TERR OWNER | T87: QUERY SOURCE/ TERR OWNER | U87: QUERY SOURCE/ TERR OWNER | V87: QUERY SOURCE/ TERR OWNER | W87: SOCAN | X87: ASCAP/BMI/SESAC/GMR | Y87: SADAIC | Z87: No Membership | AA87: ABRAMUS | AB87: SCD | AC87: SAYCO | AD87: Briana Music | AE87: SAYCE | AF87: SACM | AG87: No Membership | AH87: APDAYC | AI87: AGADU | AJ87: AMRA | AK87: AMRA | AL87: QUERY SOURCE/ TERR OWNER | AM87: QUERY SOURCE/ TERR OWNER | AN87: QUERY SOURCE/ TERR OWNER | AO87: QUERY SOURCE/ TERR OWNER | AP87: QUERY SOURCE/ TERR OWNER | AQ87: QUERY SOURCE/ TERR OWNER | AR87: QUERY SOURCE/ TERR OWNER | AS87: QUERY SOURCE/ TERR OWNER | AT87: QUERY SOURCE/ TERR OWNER | AU87: QUERY SOURCE/ TERR OWNER | AV87: QUERY SOURCE/ TERR OWNER | AW87: QUERY SOURCE/ TERR OWNER | AX87: SAMRO | AY87: QUERY SOURCE/ TERR OWNER
A88: KOMCA | B88: KOMCA | C88: Licensed By | D88: SACEM | E88: SACEM | F88: SACEM | G88: SACEM | H88: SACEM | I88: SACEM | J88: SACEM | K88: SACEM | L88: SACEM | M88: SACEM | N88: SACEM | O88: SACEM | P88: SACEM | Q88: SACEM | R88: SACEM | S88: QUERY SOURCE/ TERR OWNER | T88: QUERY SOURCE/ TERR OWNER | U88: QUERY SOURCE/ TERR OWNER | V88: QUERY SOURCE/ TERR OWNER | W88: SOCAN | X88: ASCAP/BMI/SESAC/GMR | Y88: SADAIC | Z88: Latin Autor | AA88: ECAD | AB88: Latin Autor | AC88: Latin Autor | AD88: Latin Autor | AE88: Latin Autor | AF88: SACM | AG88: Latin Autor | AH88: Latin Autor | AI88: Latin Autor | AJ88: QUERY SOURCE/ TERR OWNER | AK88: QUERY SOURCE/ TERR OWNER | AL88: QUERY SOURCE/ TERR OWNER | AM88: QUERY SOURCE/ TERR OWNER | AN88: QUERY SOURCE/ TERR OWNER | AO88: QUERY SOURCE/ TERR OWNER | AP88: QUERY SOURCE/ TERR OWNER | AQ88: QUERY SOURCE/ TERR OWNER | AR88: QUERY SOURCE/ TERR OWNER | AS88: QUERY SOURCE/ TERR OWNER | AT88: QUERY SOURCE/ TERR OWNER | AU88: QUERY SOURCE/ TERR OWNER | AV88: QUERY SOURCE/ TERR OWNER | AW88: QUERY SOURCE/ TERR OWNER | AX88: SAMRO | AY88: QUERY SOURCE/ TERR OWNER
B89: KOMCA | C89: Licensor Pays | D89: SACEM | E89: SACEM | F89: SACEM | G89: SACEM | H89: SACEM | I89: SACEM | J89: SACEM | K89: SACEM | L89: SACEM | M89: SACEM | N89: SACEM | O89: SACEM | P89: SACEM | Q89: SACEM | R89: SACEM | S89: QUERY SOURCE/ TERR OWNER | T89: QUERY SOURCE/ TERR OWNER | U89: QUERY SOURCE/ TERR OWNER | V89: QUERY SOURCE/ TERR OWNER | W89: SOCAN | X89: ASCAP/BMI/SESAC/GMR | Y89: SADAIC | Z89: Latin Autor (Processed by BO) | AA89: ECAD | AB89: Latin Autor (Processed by BO) | AC89: Latin Autor (Processed by BO) | AD89: Latin Autor (Processed by BO) | AE89: Latin Autor (Processed by BO) | AF89: SACM | AG89: Latin Autor (Processed by BO) | AH89: Latin Autor (Processed by BO) | AI89: Latin Autor (Processed by BO) | AJ89: QUERY SOURCE/ TERR OWNER | AK89: QUERY SOURCE/ TERR OWNER | AL89: QUERY SOURCE/ TERR OWNER | AM89: QUERY SOURCE/ TERR OWNER | AN89: QUERY SOURCE/ TERR OWNER | AO89: QUERY SOURCE/ TERR OWNER | AP89: QUERY SOURCE/ TERR OWNER | AQ89: QUERY SOURCE/ TERR OWNER | AR89: QUERY SOURCE/ TERR OWNER | AS89: QUERY SOURCE/ TERR OWNER | AT89: QUERY SOURCE/ TERR OWNER | AU89: QUERY SOURCE/ TERR OWNER | AV89: QUERY SOURCE/ TERR OWNER | AW89: QUERY SOURCE/ TERR OWNER | AX89: SAMRO | AY89: QUERY SOURCE/ TERR OWNER
B90: KOMCA | C90: Kobalt Paid By | D90: SACEM | E90: SACEM | F90: SACEM | G90: SACEM | H90: SACEM | I90: SACEM | J90: SACEM | K90: SACEM | L90: SACEM | M90: SACEM | N90: SACEM | O90: SACEM | P90: SACEM | Q90: SACEM | R90: SACEM | S90: QUERY SOURCE/ TERR OWNER | T90: QUERY SOURCE/ TERR OWNER | U90: QUERY SOURCE/ TERR OWNER | V90: QUERY SOURCE/ TERR OWNER | W90: SOCAN | X90: ASCAP/BMI/SESAC/GMR | Y90: SADAIC | Z90: No Membership | AA90: ABRAMUS | AB90: SCD | AC90: SAYCO | AD90: Briana Music | AE90: SAYCE | AF90: SACM | AG90: No Membership | AH90: APDAYC | AI90: AGADU | AJ90: QUERY SOURCE/ TERR OWNER | AK90: QUERY SOURCE/ TERR OWNER | AL90: QUERY SOURCE/ TERR OWNER | AM90: QUERY SOURCE/ TERR OWNER | AN90: QUERY SOURCE/ TERR OWNER | AO90: QUERY SOURCE/ TERR OWNER | AP90: QUERY SOURCE/ TERR OWNER | AQ90: QUERY SOURCE/ TERR OWNER | AR90: QUERY SOURCE/ TERR OWNER | AS90: QUERY SOURCE/ TERR OWNER | AT90: QUERY SOURCE/ TERR OWNER | AU90: QUERY SOURCE/ TERR OWNER | AV90: QUERY SOURCE/ TERR OWNER | AW90: QUERY SOURCE/ TERR OWNER | AX90: SAMRO | AY90: QUERY SOURCE/ TERR OWNER
A91: COMPASS | B91: COMPASS | C91: Licensed By | D91: QUERY SOURCE/ TERR OWNER | E91: ICE | F91: QUERY SOURCE/ TERR OWNER | G91: QUERY SOURCE/ TERR OWNER | H91: QUERY SOURCE/ TERR OWNER | I91: QUERY SOURCE/ TERR OWNER | J91: QUERY SOURCE/ TERR OWNER | K91: QUERY SOURCE/ TERR OWNER | L91: QUERY SOURCE/ TERR OWNER | M91: QUERY SOURCE/ TERR OWNER | N91: QUERY SOURCE/ TERR OWNER | O91: QUERY SOURCE/ TERR OWNER | P91: QUERY SOURCE/ TERR OWNER | Q91: QUERY SOURCE/ TERR OWNER | R91: QUERY SOURCE/ TERR OWNER | S91: QUERY SOURCE/ TERR OWNER | T91: QUERY SOURCE/ TERR OWNER | U91: QUERY SOURCE/ TERR OWNER | V91: QUERY SOURCE/ TERR OWNER | W91: SOCAN | X91: ASCAP/BMI/SESAC/GMR | Y91: SADAIC | Z91: Latin Autor | AA91: ECAD | AB91: Latin Autor | AC91: Latin Autor | AD91: Latin Autor | AE91: Latin Autor | AF91: SACM | AG91: Latin Autor | AH91: Latin Autor | AI91: Latin Autor | AJ91: AMRA | AK91: AMRA | AL91: QUERY SOURCE/ TERR OWNER | AM91: QUERY SOURCE/ TERR OWNER | AN91: QUERY SOURCE/ TERR OWNER | AO91: QUERY SOURCE/ TERR OWNER | AP91: QUERY SOURCE/ TERR OWNER | AQ91: QUERY SOURCE/ TERR OWNER | AR91: QUERY SOURCE/ TERR OWNER | AS91: QUERY SOURCE/ TERR OWNER | AT91: QUERY SOURCE/ TERR OWNER | AU91: QUERY SOURCE/ TERR OWNER | AV91: QUERY SOURCE/ TERR OWNER | AW91: QUERY SOURCE/ TERR OWNER | AX91: SAMRO | AY91: QUERY SOURCE/ TERR OWNER
B92: COMPASS | C92: Licensor Pays | D92: QUERY SOURCE/ TERR OWNER | E92: SABAM | F92: QUERY SOURCE/ TERR OWNER | G92: QUERY SOURCE/ TERR OWNER | H92: QUERY SOURCE/ TERR OWNER | I92: QUERY SOURCE/ TERR OWNER | J92: QUERY SOURCE/ TERR OWNER | K92: QUERY SOURCE/ TERR OWNER | L92: QUERY SOURCE/ TERR OWNER | M92: QUERY SOURCE/ TERR OWNER | N92: QUERY SOURCE/ TERR OWNER | O92: QUERY SOURCE/ TERR OWNER | P92: QUERY SOURCE/ TERR OWNER | Q92: QUERY SOURCE/ TERR OWNER | R92: QUERY SOURCE/ TERR OWNER | S92: QUERY SOURCE/ TERR OWNER | T92: QUERY SOURCE/ TERR OWNER | U92: QUERY SOURCE/ TERR OWNER | V92: QUERY SOURCE/ TERR OWNER | W92: SOCAN | X92: ASCAP/BMI/SESAC/GMR | Y92: SADAIC | Z92: Latin Autor (Processed by BO) | AA92: ECAD | AB92: Latin Autor (Processed by BO) | AC92: Latin Autor (Processed by BO) | AD92: Latin Autor (Processed by BO) | AE92: Latin Autor (Processed by BO) | AF92: SACM | AG92: Latin Autor (Processed by BO) | AH92: Latin Autor (Processed by BO) | AI92: Latin Autor (Processed by BO) | AJ92: AMRA | AK92: AMRA | AL92: QUERY SOURCE/ TERR OWNER | AM92: QUERY SOURCE/ TERR OWNER | AN92: QUERY SOURCE/ TERR OWNER | AO92: QUERY SOURCE/ TERR OWNER | AP92: QUERY SOURCE/ TERR OWNER | AQ92: QUERY SOURCE/ TERR OWNER | AR92: QUERY SOURCE/ TERR OWNER | AS92: QUERY SOURCE/ TERR OWNER | AT92: QUERY SOURCE/ TERR OWNER | AU92: QUERY SOURCE/ TERR OWNER | AV92: QUERY SOURCE/ TERR OWNER | AW92: QUERY SOURCE/ TERR OWNER | AX92: SAMRO | AY92: QUERY SOURCE/ TERR OWNER
B93: COMPASS | C93: Kobalt Paid By | D93: QUERY SOURCE/ TERR OWNER | E93: SABAM | F93: QUERY SOURCE/ TERR OWNER | G93: QUERY SOURCE/ TERR OWNER | H93: QUERY SOURCE/ TERR OWNER | I93: QUERY SOURCE/ TERR OWNER | J93: QUERY SOURCE/ TERR OWNER | K93: QUERY SOURCE/ TERR OWNER | L93: QUERY SOURCE/ TERR OWNER | M93: QUERY SOURCE/ TERR OWNER | N93: QUERY SOURCE/ TERR OWNER | O93: QUERY SOURCE/ TERR OWNER | P93: QUERY SOURCE/ TERR OWNER | Q93: QUERY SOURCE/ TERR OWNER | R93: QUERY SOURCE/ TERR OWNER | S93: QUERY SOURCE/ TERR OWNER | T93: QUERY SOURCE/ TERR OWNER | U93: QUERY SOURCE/ TERR OWNER | V93: QUERY SOURCE/ TERR OWNER | W93: SOCAN | X93: ASCAP/BMI/SESAC/GMR | Y93: SADAIC | Z93: No Membership | AA93: ABRAMUS | AB93: SCD | AC93: SAYCO | AD93: Briana Music | AE93: SAYCE | AF93: SACM | AG93: No Membership | AH93: APDAYC | AI93: AGADU | AJ93: AMRA | AK93: AMRA | AL93: QUERY SOURCE/ TERR OWNER | AM93: QUERY SOURCE/ TERR OWNER | AN93: QUERY SOURCE/ TERR OWNER | AO93: QUERY SOURCE/ TERR OWNER | AP93: QUERY SOURCE/ TERR OWNER | AQ93: QUERY SOURCE/ TERR OWNER | AR93: QUERY SOURCE/ TERR OWNER | AS93: QUERY SOURCE/ TERR OWNER | AT93: QUERY SOURCE/ TERR OWNER | AU93: QUERY SOURCE/ TERR OWNER | AV93: QUERY SOURCE/ TERR OWNER | AW93: QUERY SOURCE/ TERR OWNER | AX93: SAMRO | AY93: QUERY SOURCE/ TERR OWNER
A95: Non- Society | B95: Non-Society | C95: Licensed By | D95: AMRA | E95: AMRA | F95: AMRA | G95: AMRA | H95: AMRA | I95: AMRA | J95: AMRA | K95: AMRA | L95: AMRA | M95: AMRA | N95: AMRA | O95: AMRA | P95: AMRA | Q95: AMRA | R95: AMRA | S95: AMRA | T95: AMRA | U95: AMRA | V95: AMRA | W95: SOCAN | X95: ASCAP/BMI/SESAC/GMR | Y95: SADAIC | Z95: Latin Autor | AA95: ECAD | AB95: Latin Autor | AC95: Latin Autor | AD95: Latin Autor | AE95: Latin Autor | AF95: SACM | AG95: Latin Autor | AH95: Latin Autor | AI95: Latin Autor | AJ95: AMRA | AK95: AMRA | AL95: AMRA | AM95: AMRA | AN95: AMRA | AO95: AMRA | AP95: AMRA | AQ95: AMRA | AR95: AMRA | AS95: AMRA | AT95: AMRA | AU95: QUERY SOURCE/ TERR OWNER | AV95: AMRA | AW95: AMRA | AX95: AMRA | AY95: AMRA
B96: Non-Society | C96: Licensor Pays | D96: AMRA | E96: AMRA | F96: AMRA | G96: AMRA | H96: AMRA | I96: AMRA | J96: AMRA | K96: AMRA | L96: AMRA | M96: AMRA | N96: AMRA | O96: AMRA | P96: AMRA | Q96: AMRA | R96: AMRA | S96: AMRA | T96: AMRA | U96: AMRA | V96: AMRA | W96: SOCAN | X96: ASCAP/BMI/SESAC/GMR | Y96: SADAIC | Z96: Latin Autor (Processed by BO) | AA96: ECAD | AB96: Latin Autor (Processed by BO) | AC96: Latin Autor (Processed by BO) | AD96: Latin Autor (Processed by BO) | AE96: Latin Autor (Processed by BO) | AF96: SACM | AG96: Latin Autor (Processed by BO) | AH96: Latin Autor (Processed by BO) | AI96: Latin Autor (Processed by BO) | AJ96: AMRA | AK96: AMRA | AL96: AMRA | AM96: AMRA | AN96: AMRA | AO96: AMRA | AP96: AMRA | AQ96: AMRA | AR96: AMRA | AS96: AMRA | AT96: AMRA | AU96: QUERY SOURCE/ TERR OWNER | AV96: AMRA | AW96: AMRA | AX96: AMRA | AY96: AMRA
B97: Non-Society | C97: Kobalt Paid By | D97: AMRA | E97: AMRA | F97: AMRA | G97: AMRA | H97: AMRA | I97: AMRA | J97: AMRA | K97: AMRA | L97: AMRA | M97: AMRA | N97: AMRA | O97: AMRA | P97: AMRA | Q97: AMRA | R97: AMRA | S97: AMRA | T97: AMRA | U97: AMRA | V97: AMRA | W97: SOCAN | X97: ASCAP/BMI/SESAC/GMR | Y97: SADAIC | Z97: No Membership | AA97: ABRAMUS | AB97: SCD | AC97: SAYCO | AD97: Briana Music | AE97: SAYCE | AF97: SACM | AG97: No Membership | AH97: APDAYC | AI97: AGADU | AJ97: AMRA | AK97: AMRA | AL97: AMRA | AM97: AMRA | AN97: AMRA | AO97: AMRA | AP97: AMRA | AQ97: AMRA | AR97: AMRA | AS97: AMRA | AT97: AMRA | AU97: QUERY SOURCE/ TERR OWNER | AV97: AMRA | AW97: AMRA | AX97: AMRA | AY97: AMRA

Sheet Matrix - MECH
A1: Licensed By: How our pub share is licensed Licensor Pays: First society income is paid to Kobalt Paid By: Pub share payment made to Kobalt | D1: MECHANICAL INCOME - NOT INCLUDED IN DL
D2: EUROPE | W2: US / Canada | Y2: Latin America | AJ2: Australasia | AL2: Asia | AX2: Africa
A3: BIEM Rep (Example: 1 Writer -> Kobalt) | B3: SOCIETY | D3: Austria | E3: Belgium | F3: France | G3: Germany | H3: Italy | I3: Netherlands | J3: Nordics Finland / Norway / Iceland, etc) | K3: Portugal | L3: Spain | M3: Sweden | N3: Switzerland | O3: United Kingdom | P3: Croatia | Q3: Greece | R3: Poland | S3: Russia | T3: Israel | U3: UAE | V3: Turkey | W3: Canada | X3: United States | Y3: Argentina | Z3: Bolivia | AA3: Brazil | AB3: Chile | AC3: Colombia | AD3: Costa Rica | AE3: Ecuador | AF3: Mexico | AG3: Paraguay | AH3: Peru | AI3: Uruguay | AJ3: Australia | AK3: New Zealand | AL3: China | AM3: HongKong | AN3: India | AO3: Japan | AP3: Malaysia | AQ3: Philippines | AR3: Vietnam | AS3: Thailand | AT3: Singapore | AU3: South Korea | AV3: Indonesia | AW3: Taiwan | AX3: South Africa | AY3: North Africa
A4: AKM-AUME | B4: AKM-AUME | C4: Licensed By | D4: ICE | E4: ICE | F4: ICE | G4: ICE | H4: ICE | I4: ICE | J4: ICE | K4: ICE | L4: ICE | M4: ICE | N4: ICE | O4: ICE | P4: ICE | Q4: ICE | R4: ICE | S4: RAO | T4: ACUM | U4: ESMAA | V4: MSG | W4: CMRRA | X4: MLC | Y4: SADAIC | Z4: Latin Autor | AA4: ABRAMUS | AB4: Latin Autor | AC4: Latin Autor | AD4: Latin Autor | AE4: Latin Autor | AF4: SACM | AG4: Latin Autor | AH4: Latin Autor | AI4: Latin Autor | AJ4: APRA-AMCOS | AK4: APRA-AMCOS | AL4: MCSC | AM4: CASH | AO4: JASRAC | AP4: MCPS | AS4: COMPASS | AT4: MCPS | AX4: CAPASSO | AY4: ICE
B5: AKM-AUME | C5: Licensor Pays | D5: AUME | E5: SABAM | F5: SACEM | G5: GEMA | H5: SIAE | I5: BUMA | J5: STIM | K5: SGAE | L5: SGAE | M5: STIM | N5: SUISA | O5: MCPS-PRS | P5: HDS-ZAMP | Q5: AUME | R5: AUME | S5: Blue Sun | T5: Dalia | U5: Pop Arabia | V5: Zeplin | W5: CMRRA | X5: MLC | Y5: SADAIC | Z5: Latin Autor (Processed by BO) | AA5: ABRAMUS | AB5: Latin Autor (Processed by BO) | AC5: Latin Autor (Processed by BO) | AD5: Latin Autor (Processed by BO) | AE5: Latin Autor (Processed by BO) | AF5: SACM | AG5: Latin Autor (Processed by BO) | AH5: Latin Autor (Processed by BO) | AI5: Latin Autor (Processed by BO) | AJ5: APRA-AMCOS | AK5: APRA-AMCOS | AL5: MCSC | AM5: CASH | AO5: JASRAC | AP5: AMRA | AS5: COMPASS | AT5: AMRA | AX5: CAPASSO | AY5: SACEM
B6: AKM-AUME | C6: Kobalt Paid By | D6: AUME | E6: SABAM | F6: SACEM | G6: GEMA | H6: SIAE | I6: BUMA | J6: STIM | K6: SGAE | L6: SGAE | M6: STIM | N6: SUISA | O6: MCPS-PRS | P6: IDM | Q6: D-Version | R6: Schubert | S6: Blue Sun | T6: Dalia | U6: Pop Arabia | V6: Zeplin | W6: CMRRA | X6: MLC | Y6: SADAIC | Z6: No Membership | AA6: ABRAMUS | AB6: Latin Autor | AC6: Latin Autor | AD6: Latin Autor | AE6: Latin Autor | AF6: SACM | AG6: No Membership | AH6: Latin Autor | AI6: Latin Autor | AJ6: APRA-AMCOS | AK6: APRA-AMCOS | AL6: CASH | AM6: CASH | AO6: SMPJ | AP6: AMRA | AS6: COMPASS | AT6: AMRA | AX6: CAPASSO | AY6: SACEM
A7: BUMA-STEMRA | B7: BUMA-STEMRA | C7: Licensed By | D7: STEMRA | E7: STEMRA | F7: STEMRA | G7: STEMRA | H7: STEMRA | I7: STEMRA | J7: STEMRA | K7: STEMRA | L7: STEMRA | M7: STEMRA | N7: STEMRA | O7: STEMRA | P7: STEMRA | Q7: STEMRA | R7: STEMRA | S7: RAO | T7: ACUM | U7: ESMAA | V7: MSG | W7: CMRRA | X7: MLC | Y7: SADAIC | Z7: Latin Autor | AA7: ABRAMUS | AB7: Latin Autor | AC7: Latin Autor | AD7: Latin Autor | AE7: Latin Autor | AF7: SACM | AG7: Latin Autor | AH7: Latin Autor | AI7: Latin Autor | AJ7: APRA-AMCOS | AK7: APRA-AMCOS | AL7: QUERY SOURCE/ TERR OWNER | AM7: APRA-AMCOS | AN7: APRA-AMCOS | AO7: APRA-AMCOS | AP7: APRA-AMCOS | AQ7: APRA-AMCOS | AR7: APRA-AMCOS | AS7: APRA-AMCOS | AT7: APRA-AMCOS | AU7: KOMCA | AV7: APRA-AMCOS | AW7: APRA-AMCOS | AX7: CAPASSO | AY7: STEMRA
B8: BUMA-STEMRA | C8: Licensor Pays | D8: STEMRA | E8: STEMRA | F8: STEMRA | G8: STEMRA | H8: STEMRA | I8: STEMRA | J8: STEMRA | K8: STEMRA | L8: STEMRA | M8: STEMRA | N8: STEMRA | O8: STEMRA | P8: STEMRA | Q8: STEMRA | R8: STEMRA | S8: Blue Sun | T8: Dalia | U8: Pop Arabia | V8: Zeplin | W8: CMRRA | X8: MLC | Y8: SADAIC | Z8: Latin Autor (Processed by BO) | AA8: ABRAMUS | AB8: Latin Autor (Processed by BO) | AC8: Latin Autor (Processed by BO) | AD8: Latin Autor (Processed by BO) | AE8: Latin Autor (Processed by BO) | AF8: SACM | AG8: Latin Autor (Processed by BO) | AH8: Latin Autor (Processed by BO) | AI8: Latin Autor (Processed by BO) | AJ8: APRA-AMCOS | AK8: APRA-AMCOS | AL8: QUERY SOURCE/ TERR OWNER | AM8: STEMRA | AN8: STEMRA | AO8: STEMRA | AP8: STEMRA | AQ8: STEMRA | AR8: STEMRA | AS8: STEMRA | AT8: STEMRA | AU8: KOMCA | AV8: STEMRA | AW8: STEMRA | AX8: CAPASSO | AY8: STEMRA
B9: BUMA-STEMRA | C9: Kobalt Paid By | D9: AUME | E9: SABAM | F9: SACEM | G9: GEMA | H9: SIAE | I9: BUMA | J9: STIM | K9: SPA | L9: SGAE | M9: STIM | N9: SUISA | O9: MCPS-PRS | P9: IDM | Q9: D-Version | R9: Schubert | S9: Blue Sun | T9: Dalia | U9: Pop Arabia | V9: Zeplin | W9: AMRA | X9: MLC | Y9: SADAIC | Z9: No Membership | AA9: ABRAMUS | AB9: Latin Autor | AC9: Latin Autor | AD9: Latin Autor | AE9: Latin Autor | AF9: SACM | AG9: No Membership | AH9: Latin Autor | AI9: Latin Autor | AJ9: APRA-AMCOS | AK9: APRA-AMCOS | AL9: QUERY SOURCE/ TERR OWNER | AM9: CASH | AN9: Turnkey | AO9: SMPJ | AP9: Indie Works | AQ9: STIM | AR9: STIM | AS9: STIM | AT9: STIM | AU9: EKKO | AV9: PT Nadaku | AW9: One Asia | AX9: CAPASSO | AY9: SACEM
A10: GEMA | B10: GEMA | C10: Licensed By | D10: ICE | E10: ICE | F10: ICE | G10: GEMA | H10: ICE | I10: ICE | J10: ICE | K10: ICE | L10: ICE | M10: ICE | N10: ICE | O10: ICE | P10: ICE | Q10: ICE | R10: ICE | S10: RAO | T10: ACUM | U10: ESMAA | V10: MSG | W10: CMRRA | X10: MLC | Y10: SADAIC | Z10: Latin Autor | AA10: ABRAMUS | AB10: Latin Autor | AC10: Latin Autor | AD10: Latin Autor | AE10: Latin Autor | AF10: SACM | AG10: Latin Autor | AH10: Latin Autor | AI10: Latin Autor | AJ10: APRA-AMCOS | AK10: APRA-AMCOS | AL10: MCSC | AM10: CASH | AN10: IPRS | AO10: JASRAC | AP10: MACP | AQ10: COMPASS | AR10: COMPASS | AS10: COMPASS | AT10: COMPASS | AU10: KOMCA | AV10: WAMI | AW10: MUST | AX10: CAPASSO | AY10: ICE
B11: GEMA | C11: Licensor Pays | D11: AUME | E11: SABAM | F11: SACEM | G11: GEMA | H11: SIAE | I11: BUMA | J11: Nordic Sources | K11: SPA | L11: SGAE | M11: STIM | N11: SUISA | O11: MCPS-PRS | P11: HDS-ZAMP | Q11: GEMA | R11: GEMA | S11: Blue Sun | T11: Dalia | U11: Pop Arabia | V11: Zeplin | W11: CMRRA | X11: MLC | Y11: SADAIC | Z11: Latin Autor (Processed by BO) | AA11: ABRAMUS | AB11: Latin Autor (Processed by BO) | AC11: Latin Autor (Processed by BO) | AD11: Latin Autor (Processed by BO) | AE11: Latin Autor (Processed by BO) | AF11: SACM | AG11: Latin Autor (Processed by BO) | AH11: Latin Autor (Processed by BO) | AI11: Latin Autor (Processed by BO) | AJ11: APRA-AMCOS | AK11: APRA-AMCOS | AL11: MCSC | AM11: CASH | AN11: IPRS | AO11: JASRAC | AP11: MACP | AQ11: COMPASS | AR11: COMPASS | AS11: COMPASS | AT11: COMPASS | AU11: KOMCA | AV11: WAMI | AW11: MUST | AX11: CAPASSO | AY11: GEMA
B12: GEMA | C12: Kobalt Paid By | D12: AUME | E12: SABAM | F12: SACEM | G12: GEMA | H12: SIAE | I12: BUMA | J12: Nordic Sources | K12: SPA | L12: SGAE | M12: STIM | N12: SUISA | O12: MCPS-PRS | P12: IDM | Q12: D-Version | R12: Schubert | S12: Blue Sun | T12: Dalia | U12: Pop Arabia | V12: Zeplin | W12: CMRRA | X12: MLC | Y12: SADAIC | Z12: No Membership | AA12: ABRAMUS | AB12: Latin Autor | AC12: Latin Autor | AD12: Latin Autor | AE12: Latin Autor | AF12: SACM | AG12: No Membership | AH12: Latin Autor | AI12: Latin Autor | AJ12: APRA-AMCOS | AK12: APRA-AMCOS | AL12: CASH | AM12: CASH | AN12: Turnkey | AO12: SMPJ | AP12: Indie Works | AQ12: COMPASS | AR12: COMPASS | AS12: COMPASS | AT12: COMPASS | AU12: EKKO | AV12: PT Nadaku | AW12: One Asia | AX12: CAPASSO | AY12: GEMA
A13: SABAM | B13: SABAM | C13: Licensed By | D13: ICE | E13: ICE | F13: ICE | G13: ICE | H13: ICE | I13: ICE | J13: ICE | K13: ICE | L13: ICE | M13: ICE | N13: ICE | O13: ICE | P13: ICE | Q13: ICE | R13: ICE | S13: RAO | T13: ACUM | U13: ESMAA | V13: MSG | W13: CMRRA | X13: MLC | Y13: SADAIC | Z13: Latin Autor | AA13: ABRAMUS | AB13: Latin Autor | AC13: Latin Autor | AD13: Latin Autor | AE13: Latin Autor | AF13: SACM | AG13: Latin Autor | AH13: Latin Autor | AI13: Latin Autor | AJ13: APRA-AMCOS | AK13: APRA-AMCOS | AL13: MCSC | AM13: CASH | AN13: QUERY SOURCE/ TERR OWNER | AO13: JASRAC | AP13: MACP | AQ13: FILSCAP | AR13: VCPMC | AS13: QUERY SOURCE/ TERR OWNER | AT13: COMPASS | AU13: KOMCA | AV13: QUERY SOURCE/ TERR OWNER | AW13: MUST | AX13: CAPASSO | AY13: ICE
B14: SABAM | C14: Licensor Pays | D14: SABAM | E14: SABAM | F14: SABAM | G14: SABAM | H14: SABAM | I14: SABAM | J14: SABAM | K14: SABAM | L14: SABAM | M14: SABAM | N14: SABAM | O14: SABAM | P14: SABAM | Q14: SABAM | R14: SABAM | S14: Blue Sun | T14: Dalia | U14: Pop Arabia | V14: Zeplin | W14: CMRRA | X14: MLC | Y14: SADAIC | Z14: Latin Autor (Processed by BO) | AA14: ABRAMUS | AB14: Latin Autor (Processed by BO) | AC14: Latin Autor (Processed by BO) | AD14: Latin Autor (Processed by BO) | AE14: Latin Autor (Processed by BO) | AF14: SACM | AG14: Latin Autor (Processed by BO) | AH14: Latin Autor (Processed by BO) | AI14: Latin Autor (Processed by BO) | AJ14: APRA-AMCOS | AK14: APRA-AMCOS | AL14: MCSC | AM14: CASH | AN14: QUERY SOURCE/ TERR OWNER | AO14: JASRAC | AP14: MACP | AQ14: FILSCAP | AR14: VCPMC | AS14: QUERY SOURCE/ TERR OWNER | AT14: COMPASS | AU14: KOMCA | AV14: QUERY SOURCE/ TERR OWNER | AW14: MUST | AX14: CAPASSO | AY14: SABAM
B15: SABAM | C15: Kobalt Paid By | D15: AUME | E15: SABAM | F15: SACEM | G15: GEMA | H15: SIAE | I15: BUMA | J15: STIM | K15: SPA | L15: SGAE | M15: STIM | N15: SUISA | O15: MCPS-PRS | P15: IDM | Q15: D-Version | R15: Schubert | S15: Blue Sun | T15: Dalia | U15: Pop Arabia | V15: Zeplin | W15: CMRRA | X15: MLC | Y15: SADAIC | Z15: No Membership | AA15: ABRAMUS | AB15: Latin Autor | AC15: Latin Autor | AD15: Latin Autor | AE15: Latin Autor | AF15: SACM | AG15: No Membership | AH15: Latin Autor | AI15: Latin Autor | AJ15: APRA-AMCOS | AK15: APRA-AMCOS | AL15: CASH | AM15: CASH | AN15: QUERY SOURCE/ TERR OWNER | AO15: SMPJ | AP15: Indie Works | AQ15: COMPASS | AR15: COMPASS | AS15: QUERY SOURCE/ TERR OWNER | AT15: COMPASS | AU15: EKKO | AV15: QUERY SOURCE/ TERR OWNER | AW15: One Asia | AX15: CAPASSO | AY15: SACEM
A16: SACEM | B16: SACEM | C16: Licensed By | D16: SACEM | E16: SACEM | F16: SACEM | G16: SACEM | H16: SACEM | I16: SACEM | J16: SACEM | K16: SACEM | L16: SACEM | M16: SACEM | N16: SACEM | O16: SACEM | P16: SACEM | Q16: SACEM | R16: SACEM | S16: RAO | T16: ACUM | U16: ESMAA | V16: MSG | W16: CMRRA | X16: MLC | Y16: SADAIC | Z16: Latin Autor | AA16: ABRAMUS | AB16: Latin Autor | AC16: Latin Autor | AD16: Latin Autor | AE16: Latin Autor | AF16: SACM | AG16: Latin Autor | AH16: Latin Autor | AI16: Latin Autor | AJ16: APRA-AMCOS | AK16: APRA-AMCOS | AL16: QUERY SOURCE/ TERR OWNER | AM16: QUERY SOURCE/ TERR OWNER | AN16: QUERY SOURCE/ TERR OWNER | AO16: QUERY SOURCE/ TERR OWNER | AP16: QUERY SOURCE/ TERR OWNER | AQ16: QUERY SOURCE/ TERR OWNER | AR16: QUERY SOURCE/ TERR OWNER | AS16: QUERY SOURCE/ TERR OWNER | AT16: QUERY SOURCE/ TERR OWNER | AU16: KOMCA | AV16: QUERY SOURCE/ TERR OWNER | AW16: QUERY SOURCE/ TERR OWNER | AX16: CAPASSO | AY16: SACEM
B17: SACEM | C17: Licensor Pays | D17: SACEM | E17: SACEM | F17: SACEM | G17: SACEM | H17: SACEM | I17: SACEM | J17: SACEM | K17: SACEM | L17: SACEM | M17: SACEM | N17: SACEM | O17: SACEM | P17: SACEM | Q17: SACEM | R17: SACEM | S17: Blue Sun | T17: Dalia | U17: Pop Arabia | V17: Zeplin | W17: CMRRA | X17: MLC | Y17: SADAIC | Z17: Latin Autor (Processed by BO) | AA17: ABRAMUS | AB17: Latin Autor (Processed by BO) | AC17: Latin Autor (Processed by BO) | AD17: Latin Autor (Processed by BO) | AE17: Latin Autor (Processed by BO) | AF17: SACM | AG17: Latin Autor (Processed by BO) | AH17: Latin Autor (Processed by BO) | AI17: Latin Autor (Processed by BO) | AJ17: APRA-AMCOS | AK17: APRA-AMCOS | AL17: QUERY SOURCE/ TERR OWNER | AM17: QUERY SOURCE/ TERR OWNER | AN17: QUERY SOURCE/ TERR OWNER | AO17: QUERY SOURCE/ TERR OWNER | AP17: QUERY SOURCE/ TERR OWNER | AQ17: QUERY SOURCE/ TERR OWNER | AR17: QUERY SOURCE/ TERR OWNER | AS17: QUERY SOURCE/ TERR OWNER | AT17: QUERY SOURCE/ TERR OWNER | AU17: KOMCA | AV17: QUERY SOURCE/ TERR OWNER | AW17: QUERY SOURCE/ TERR OWNER | AX17: CAPASSO | AY17: SACEM
B18: SACEM | C18: Kobalt Paid By | D18: SACEM | E18: SACEM | F18: SACEM | G18: SACEM | H18: SACEM | I18: SACEM | J18: SACEM | K18: SACEM | L18: SACEM | M18: SACEM | N18: SACEM | O18: SACEM | P18: SACEM | Q18: SACEM | R18: SACEM | S18: Blue Sun | T18: Dalia | U18: Pop Arabia | V18: Zeplin | W18: CMRRA | X18: MLC | Y18: SADAIC | Z18: No Membership | AA18: ABRAMUS | AB18: Latin Autor | AC18: Latin Autor | AD18: Latin Autor | AE18: Latin Autor | AF18: SACM | AG18: No Membership | AH18: Latin Autor | AI18: Latin Autor | AJ18: APRA-AMCOS | AK18: APRA-AMCOS | AL18: QUERY SOURCE/ TERR OWNER | AM18: QUERY SOURCE/ TERR OWNER | AN18: QUERY SOURCE/ TERR OWNER | AO18: QUERY SOURCE/ TERR OWNER | AP18: QUERY SOURCE/ TERR OWNER | AQ18: QUERY SOURCE/ TERR OWNER | AR18: QUERY SOURCE/ TERR OWNER | AS18: QUERY SOURCE/ TERR OWNER | AT18: QUERY SOURCE/ TERR OWNER | AU18: EKKO | AV18: QUERY SOURCE/ TERR OWNER | AW18: QUERY SOURCE/ TERR OWNER | AX18: CAPASSO | AY18: SACEM
A19: SGAE | B19: SGAE | C19: Licensed By | D19: AUME | E19: SABAM | F19: SACEM | G19: GEMA | H19: SIAE | I19: BUMA | J19: Nordic Sources | K19: SPA | L19: SGAE | M19: STIM | N19: SUISA | O19: MCPS-PRS | P19: HDS-ZAMP | Q19: AUTODIA | R19: ZAIKS | S19: RAO | T19: ACUM | U19: ESMAA | V19: MSG | W19: CMRRA | X19: MLC | Y19: SADAIC | Z19: Latin Autor | AA19: ABRAMUS | AB19: Latin Autor | AC19: Latin Autor | AD19: Latin Autor | AE19: Latin Autor | AF19: SACM | AG19: Latin Autor | AH19: Latin Autor | AI19: Latin Autor | AJ19: APRA-AMCOS | AK19: APRA-AMCOS | AL19: MCSC | AM19: CASH | AN19: IPRS | AO19: JASRAC | AP19: MACP | AQ19: FILSCAP | AR19: VCPMC | AS19: MCT | AT19: COMPASS | AU19: KOMCA | AX19: CAPASSO
B20: SGAE | C20: Licensor Pays | D20: AUME | E20: SABAM | F20: SACEM | G20: GEMA | H20: SIAE | I20: BUMA | J20: Nordic Sources | K20: SPA | L20: SGAE | M20: STIM | N20: SUISA | O20: MCPS-PRS | P20: IDM | Q20: D-Version | R20: Schubert | S20: Blue Sun | T20: Dalia | U20: Pop Arabia | V20: Zeplin | W20: CMRRA | X20: MLC | Y20: SADAIC | Z20: Latin Autor (Processed by BO) | AA20: ABRAMUS | AB20: Latin Autor (Processed by BO) | AC20: Latin Autor (Processed by BO) | AD20: Latin Autor (Processed by BO) | AE20: Latin Autor (Processed by BO) | AF20: SACM | AG20: Latin Autor (Processed by BO) | AH20: Latin Autor (Processed by BO) | AI20: Latin Autor (Processed by BO) | AJ20: APRA-AMCOS | AK20: APRA-AMCOS | AL20: MCSC | AM20: CASH | AN20: IPRS | AO20: JASRAC | AP20: MACP | AQ20: FILSCAP | AR20: VCPMC | AS20: MCT | AT20: COMPASS | AU20: KOMCA | AX20: CAPASSO
B21: SGAE | C21: Kobalt Paid By | D21: AUME | E21: SABAM | F21: SACEM | G21: GEMA | H21: SIAE | I21: BUMA | J21: Nordic Sources | K21: SPA | L21: SGAE | M21: STIM | N21: SUISA | O21: MCPS-PRS | P21: IDM | Q21: D-Version | R21: Schubert | S21: Blue Sun | T21: Dalia | U21: Pop Arabia | V21: Zeplin | W21: CMRRA | X21: MLC | Y21: SADAIC | Z21: No Membership | AA21: ABRAMUS | AB21: Latin Autor | AC21: Latin Autor | AD21: Latin Autor | AE21: Latin Autor | AF21: SACM | AG21: No Membership | AH21: Latin Autor | AI21: Latin Autor | AJ21: APRA-AMCOS | AK21: APRA-AMCOS | AL21: CASH | AM21: CASH | AN21: Turnkey | AO21: SMPJ | AP21: Indie Works | AQ21: COMPASS | AR21: COMPASS | AS21: COMPASS | AT21: COMPASS | AU21: EKKO | AX21: CAPASSO
A22: SIAE | B22: SIAE | C22: Licensed By | D22: AKM | E22: SABAM | F22: SACEM | G22: GEMA | H22: SIAE | I22: BUMA | J22: Nordic Sources | K22: SPA | L22: SGAE | M22: STIM | N22: SUISA | O22: MCPS-PRS | P22: QUERY SOURCE/ TERR OWNER | Q22: QUERY SOURCE/ TERR OWNER | R22: QUERY SOURCE/ TERR OWNER | S22: RAO | T22: ACUM | U22: ESMAA | V22: MSG | W22: CMRRA | X22: MLC | Y22: SADAIC | Z22: Latin Autor | AA22: ABRAMUS | AB22: Latin Autor | AC22: Latin Autor | AD22: Latin Autor | AE22: Latin Autor | AF22: SACM | AG22: Latin Autor | AH22: Latin Autor | AI22: Latin Autor | AJ22: APRA-AMCOS | AK22: APRA-AMCOS | AL22: MCSC | AM22: CASH | AN22: IPRS | AO22: JASRAC | AP22: MACP | AQ22: FILSCAP | AR22: VCPMC | AS22: MCT | AT22: COMPASS | AU22: KOMCA | AV22: WAMI | AW22: MUST | AX22: SAMRO | AY22: QUERY SOURCE/ TERR OWNER
B23: SIAE | C23: Licensor Pays | D23: AKM | E23: SABAM | F23: SACEM | G23: GEMA | H23: SIAE | I23: BUMA | J23: Nordic Sources | K23: SPA | L23: SGAE | M23: STIM | N23: SUISA | O23: MCPS-PRS | P23: QUERY SOURCE/ TERR OWNER | Q23: QUERY SOURCE/ TERR OWNER | R23: QUERY SOURCE/ TERR OWNER | S23: Blue Sun | T23: Dalia | U23: Pop Arabia | V23: Zeplin | W23: CMRRA | X23: MLC | Y23: SADAIC | Z23: Latin Autor (Processed by BO) | AA23: ABRAMUS | AB23: Latin Autor (Processed by BO) | AC23: Latin Autor (Processed by BO) | AD23: Latin Autor (Processed by BO) | AE23: Latin Autor (Processed by BO) | AF23: SACM | AG23: Latin Autor (Processed by BO) | AH23: Latin Autor (Processed by BO) | AI23: Latin Autor (Processed by BO) | AJ23: APRA-AMCOS | AK23: APRA-AMCOS | AL23: MCSC | AM23: CASH | AN23: IPRS | AO23: JASRAC | AP23: MACP | AQ23: FILSCAP | AR23: VCPMC | AS23: MCT | AT23: COMPASS | AU23: KOMCA | AV23: WAMI | AW23: MUST | AX23: SAMRO | AY23: QUERY SOURCE/ TERR OWNER
B24: SIAE | C24: Kobalt Paid By | D24: AKM | E24: SABAM | F24: SACEM | G24: GEMA | H24: SIAE | I24: BUMA | J24: Nordic Sources | K24: SPA | L24: SGAE | M24: STIM | N24: SUISA | O24: MCPS-PRS | P24: IDM | Q24: D-Version | R24: Schubert | S24: Blue Sun | T24: Dalia | U24: Pop Arabia | V24: Zeplin | W24: CMRRA | X24: MLC | Y24: SADAIC | Z24: No Membership | AA24: ABRAMUS | AB24: Latin Autor | AC24: Latin Autor | AD24: Latin Autor | AE24: Latin Autor | AF24: SACM | AG24: No Membership | AH24: Latin Autor | AI24: Latin Autor | AJ24: APRA-AMCOS | AK24: APRA-AMCOS | AL24: CASH | AM24: CASH | AN24: Turnkey | AO24: SMPJ | AP24: Indie Works | AQ24: COMPASS | AR24: COMPASS | AS24: COMPASS | AT24: COMPASS | AU24: EKKO | AV24: PT Nadaku | AW24: One Asia | AX24: SAMRO | AY24: QUERY SOURCE/ TERR OWNER
A25: SPA | B25: SPA | C25: Licensed By | D25: AUME | E25: SABAM | F25: SACEM | G25: GEMA | H25: SIAE | I25: BUMA | J25: STIM | K25: SPA | L25: SGAE | M25: STIM | N25: SUISA | O25: MCPS-PRS | P25: HDS-ZAMP | Q25: AUTODIA | R25: ZAIKS | S25: RAO | T25: ACUM | U25: ESMAA | V25: MSG | W25: CMRRA | X25: MLC | Y25: SADAIC | Z25: Latin Autor | AA25: ABRAMUS | AB25: Latin Autor | AC25: Latin Autor | AD25: Latin Autor | AE25: Latin Autor | AF25: SACM | AG25: Latin Autor | AH25: Latin Autor | AI25: Latin Autor | AJ25: APRA-AMCOS | AK25: APRA-AMCOS | AM25: CASH | AO25: JASRAC | AP25: MACP | AQ25: FILSCAP | AR25: VCPMC | AS25: MCT | AU25: KOMCA | AW25: MUST | AX25: CAPASSO
B26: SPA | C26: Licensor Pays | D26: AUME | E26: SABAM | F26: SACEM | G26: GEMA | H26: SIAE | I26: BUMA | J26: STIM | K26: SPA | L26: SGAE | M26: STIM | N26: SUISA | O26: MCPS-PRS | P26: IDM | Q26: D-Version | R26: Schubert | S26: Blue Sun | T26: Dalia | U26: Pop Arabia | V26: Zeplin | W26: CMRRA | X26: MLC | Y26: SADAIC | Z26: Latin Autor (Processed by BO) | AA26: ABRAMUS | AB26: Latin Autor (Processed by BO) | AC26: Latin Autor (Processed by BO) | AD26: Latin Autor (Processed by BO) | AE26: Latin Autor (Processed by BO) | AF26: SACM | AG26: Latin Autor (Processed by BO) | AH26: Latin Autor (Processed by BO) | AI26: Latin Autor (Processed by BO) | AJ26: APRA-AMCOS | AK26: APRA-AMCOS | AM26: CASH | AO26: JASRAC | AP26: MACP | AQ26: FILSCAP | AR26: VCPMC | AS26: MCT | AU26: KOMCA | AW26: MUST | AX26: CAPASSO
B27: SPA | C27: Kobalt Paid By | D27: AUME | E27: SABAM | F27: SACEM | G27: GEMA | H27: SIAE | I27: BUMA | J27: STIM | K27: SPA | L27: SGAE | M27: STIM | N27: SUISA | O27: MCPS-PRS | P27: IDM | Q27: D-Version | R27: Schubert | S27: Blue Sun | T27: Dalia | U27: Pop Arabia | V27: Zeplin | W27: CMRRA | X27: MLC | Y27: SADAIC | Z27: No Membership | AA27: ABRAMUS | AB27: Latin Autor | AC27: Latin Autor | AD27: Latin Autor | AE27: Latin Autor | AF27: SACM | AG27: No Membership | AH27: Latin Autor | AI27: Latin Autor | AJ27: APRA-AMCOS | AK27: APRA-AMCOS | AM27: CASH | AO27: SMPJ | AP27: Indie Works | AQ27: COMPASS | AR27: COMPASS | AS27: Compass | AU27: EKKO | AW27: One Asia | AX27: CAPASSO
A28: STIM-NCB | B28: STIM-NCB | C28: Licensed By | D28: ICE | E28: ICE | F28: ICE | G28: ICE | H28: ICE | I28: ICE | J28: ICE | K28: ICE | L28: ICE | M28: ICE | N28: ICE | O28: ICE | P28: ICE | Q28: ICE | R28: ICE | S28: RAO | T28: ACUM | U28: ESMAA | V28: MSG | W28: CMRRA | X28: MLC | Y28: SADAIC | Z28: Latin Autor | AA28: ABRAMUS | AB28: Latin Autor | AC28: Latin Autor | AD28: Latin Autor | AE28: Latin Autor | AF28: SACM | AG28: Latin Autor | AH28: Latin Autor | AI28: Latin Autor | AJ28: APRA-AMCOS | AK28: APRA-AMCOS | AL28: APRA-AMCOS | AM28: APRA-AMCOS | AN28: APRA-AMCOS | AO28: APRA-AMCOS | AP28: APRA-AMCOS | AQ28: APRA-AMCOS | AR28: APRA-AMCOS | AS28: APRA-AMCOS | AT28: APRA-AMCOS | AU28: APRA-AMCOS | AV28: APRA-AMCOS | AW28: APRA-AMCOS | AX28: CAPASSO | AY28: ICE
B29: STIM-NCB | C29: Licensor Pays | D29: STIM | E29: STIM | F29: STIM | G29: STIM | H29: STIM | I29: STIM | J29: STIM | K29: STIM | L29: STIM | M29: STIM | N29: STIM | O29: STIM | P29: STIM | Q29: STIM | R29: STIM | S29: Blue Sun | T29: Dalia | U29: Pop Arabia | V29: Zeplin | W29: CMRRA | X29: MLC | Y29: SADAIC | Z29: Latin Autor (Processed by BO) | AA29: ABRAMUS | AB29: Latin Autor (Processed by BO) | AC29: Latin Autor (Processed by BO) | AD29: Latin Autor (Processed by BO) | AE29: Latin Autor (Processed by BO) | AF29: SACM | AG29: Latin Autor (Processed by BO) | AH29: Latin Autor (Processed by BO) | AI29: Latin Autor (Processed by BO) | AJ29: APRA-AMCOS | AK29: APRA-AMCOS | AL29: STIM | AM29: STIM | AN29: STIM | AO29: STIM | AP29: STIM | AQ29: STIM | AR29: STIM | AS29: STIM | AT29: STIM | AU29: STIM | AV29: STIM | AW29: STIM | AX29: CAPASSO | AY29: STIM
B30: STIM-NCB | C30: Kobalt Paid By | D30: STIM | E30: STIM | F30: STIM | G30: STIM | H30: STIM | I30: STIM | J30: STIM | K30: STIM | L30: STIM | M30: STIM | N30: STIM | O30: STIM | P30: IDM | Q30: D-Version | R30: Schubert | S30: Blue Sun | T30: Dalia | U30: Pop Arabia | V30: Zeplin | W30: CMRRA | X30: MLC | Y30: SADAIC | Z30: No Membership | AA30: ABRAMUS | AB30: Latin Autor | AC30: Latin Autor | AD30: Latin Autor | AE30: Latin Autor | AF30: SACM | AG30: No Membership | AH30: Latin Autor | AI30: Latin Autor | AJ30: APRA-AMCOS | AK30: APRA-AMCOS | AL30: STIM | AM30: STIM | AN30: Turnkey | AO30: SMPJ | AP30: Indie Works | AQ30: STIM | AR30: STIM | AS30: STIM | AT30: STIM | AU30: EKKO | AV30: PT Nadaku | AW30: One Asia | AX30: CAPASSO | AY30: STIM
A31: SUISA | B31: SUISA | C31: Licensed By | D31: MINT / ICE | E31: MINT / ICE | F31: MINT / ICE | G31: MINT / ICE | H31: MINT / ICE | I31: MINT / ICE | J31: MINT / ICE | K31: MINT / ICE | L31: MINT / ICE | M31: MINT / ICE | N31: SUISA | O31: MINT / ICE | P31: MINT / ICE | Q31: MINT / ICE | R31: MINT / ICE | S31: RAO | T31: ACUM | U31: ESMAA | V31: MSG | W31: CMRRA | X31: MLC | Y31: SADAIC | Z31: Latin Autor | AA31: ABRAMUS | AB31: Latin Autor | AD31: Latin Autor | AE31: Latin Autor | AF31: SACM | AH31: APDAYC | AI31: AGADU | AJ31: APRA-AMCOS | AK31: APRA-AMCOS | AL31: MCSC | AM31: CASH | AN31: IPRS | AO31: JASRAC | AP31: MACP | AR31: VCPMC | AS31: MCT | AT31: COMPASS | AV31: WAMI | AW31: MUST | AX31: CAPASSO
B32: SUISA | C32: Licensor Pays | D32: AUME | E32: SABAM | F32: SACEM | G32: GEMA | H32: SIAE | I32: STEMRA | J32: STIM | K32: SPA | L32: SGAE | M32: STIM | N32: SUISA | O32: MCPS-PRS | P32: HDS ZAMP | Q32: AUTODIA | R32: ZAIKS | S32: Blue Sun | T32: Dalia | U32: Pop Arabia | V32: Zeplin | W32: CMRRA | X32: MLC | Y32: SADAIC | Z32: Latin Autor (Processed by BO) | AA32: ABRAMUS | AB32: Latin Autor (Processed by BO) | AD32: Latin Autor (Processed by BO) | AE32: Latin Autor (Processed by BO) | AF32: SACM | AH32: Latin Autor (Processed by BO) | AI32: Latin Autor (Processed by BO) | AJ32: APRA-AMCOS | AK32: APRA-AMCOS | AL32: MCSC | AM32: CASH | AN32: IPRS | AO32: JASRAC | AP32: MACP | AR32: VCPMC | AS32: MCT | AT32: COMPASS | AV32: WAMI | AW32: MUST | AX32: CAPASSO
B33: SUISA | C33: Kobalt Paid By | D33: AUME | E33: SABAM | F33: SACEM | G33: GEMA | H33: SIAE | I33: STEMRA | J33: STIM | K33: SPA | L33: SGAE | M33: STIM | N33: SUISA | O33: MCPS-PRS | P33: IDM | Q33: D-Version | R33: Schubert | S33: Blue Sun | T33: Dalia | U33: Pop Arabia | V33: Zeplin | W33: CMRRA | X33: MLC | Y33: SADAIC | Z33: No Membership | AA33: ABRAMUS | AB33: Latin Autor | AD33: Latin Autor | AE33: Latin Autor | AF33: SACM | AH33: APDAYC | AI33: AGADU | AJ33: APRA-AMCOS | AK33: APRA-AMCOS | AL33: CASH | AM33: CASH | AN33: Turnkey | AO33: SMPJ | AP33: Indie Works | AR33: COMPASS | AS33: Compass | AT33: COMPASS | AV33: PT Nadaku | AW33: One Asia | AX33: CAPASSO
A34: Anglo-Am Rep
A35: AMRA | B35: AMRA | C35: Licensed By | D35: AMRA | E35: AMRA | F35: AMRA | G35: AMRA | H35: AMRA | I35: AMRA | J35: AMRA | K35: AMRA | L35: AMRA | M35: AMRA | N35: AMRA | O35: AMRA | P35: AMRA | Q35: AMRA | R35: AMRA | S35: AMRA | T35: AMRA | U35: AMRA | V35: AMRA | W35: AMRA | X35: MLC | Y35: SADAIC | Z35: Latin Autor | AA35: AMRA | AB35: Latin Autor | AC35: Latin Autor | AD35: Latin Autor | AE35: Latin Autor | AF35: SACM | AG35: Latin Autor | AH35: Latin Autor | AI35: Latin Autor | AJ35: AMRA | AK35: AMRA | AL35: AMRA | AM35: AMRA | AN35: AMRA | AO35: AMRA | AP35: AMRA | AQ35: AMRA | AR35: AMRA | AS35: AMRA | AT35: AMRA | AU35: KOMCA | AV35: AMRA | AW35: AMRA | AX35: AMRA | AY35: AMRA
B36: AMRA | C36: Licensor Pays | D36: AMRA | E36: AMRA | F36: AMRA | G36: AMRA | H36: AMRA | I36: AMRA | J36: AMRA | K36: AMRA | L36: AMRA | M36: AMRA | N36: AMRA | O36: AMRA | P36: AMRA | Q36: AMRA | R36: AMRA | S36: AMRA | T36: AMRA | U36: AMRA | V36: AMRA | W36: AMRA | X36: MLC | Y36: SADAIC | Z36: Latin Autor (Processed by BO) | AA36: AMRA | AB36: Latin Autor (Processed by BO) | AC36: Latin Autor (Processed by BO) | AD36: Latin Autor (Processed by BO) | AE36: Latin Autor (Processed by BO) | AF36: SACM | AG36: Latin Autor (Processed by BO) | AH36: Latin Autor (Processed by BO) | AI36: Latin Autor (Processed by BO) | AJ36: AMRA | AK36: AMRA | AL36: AMRA | AM36: AMRA | AN36: AMRA | AO36: AMRA | AP36: AMRA | AQ36: AMRA | AR36: AMRA | AS36: AMRA | AT36: AMRA | AU36: KOMCA | AV36: AMRA | AW36: AMRA | AX36: AMRA | AY36: AMRA
B37: AMRA | C37: Kobalt Paid By | D37: AMRA | E37: AMRA | F37: AMRA | G37: AMRA | H37: AMRA | I37: AMRA | J37: AMRA | K37: AMRA | L37: AMRA | M37: AMRA | N37: AMRA | O37: AMRA | P37: AMRA | Q37: AMRA | R37: AMRA | S37: AMRA | T37: AMRA | U37: AMRA | V37: AMRA | W37: AMRA | X37: MLC | Y37: SADAIC | Z37: AMRA | AA37: AMRA | AB37: AMRA | AC37: AMRA | AD37: AMRA | AE37: AMRA | AF37: SACM | AG37: AMRA | AH37: AMRA | AI37: AMRA | AJ37: AMRA | AK37: AMRA | AL37: AMRA | AM37: AMRA | AN37: AMRA | AO37: AMRA | AP37: AMRA | AQ37: AMRA | AR37: AMRA | AS37: AMRA | AT37: AMRA | AU37: EKKO | AV37: AMRA | AW37: AMRA | AX37: AMRA | AY37: AMRA
A38: APRA-AMCOS | B38: APRA-AMCOS | C38: Licensed By | D38: AMRA | E38: AMRA | F38: AMRA | G38: AMRA | H38: AMRA | I38: AMRA | J38: AMRA | K38: AMRA | L38: AMRA | M38: AMRA | N38: AMRA | O38: AMRA | P38: AMRA | Q38: AMRA | R38: AMRA | S38: AMRA | T38: AMRA | U38: AMRA | V38: AMRA | W38: AMRA | X38: MLC | Y38: SADAIC | Z38: Latin Autor | AA38: AMRA | AB38: Latin Autor | AC38: Latin Autor | AD38: Latin Autor | AE38: Latin Autor | AF38: SACM | AG38: Latin Autor | AH38: Latin Autor | AI38: Latin Autor | AJ38: AMRA | AK38: AMRA | AL38: AMRA | AM38: AMRA | AN38: AMRA | AO38: AMRA | AP38: AMRA | AQ38: AMRA | AR38: AMRA | AS38: AMRA | AT38: AMRA | AU38: KOMCA | AV38: AMRA | AW38: AMRA | AX38: AMRA | AY38: AMRA
B39: APRA-AMCOS | C39: Licensor Pays | D39: AMRA | E39: AMRA | F39: AMRA | G39: AMRA | H39: AMRA | I39: AMRA | J39: AMRA | K39: AMRA | L39: AMRA | M39: AMRA | N39: AMRA | O39: AMRA | P39: AMRA | Q39: AMRA | R39: AMRA | S39: AMRA | T39: AMRA | U39: AMRA | V39: AMRA | W39: AMRA | X39: MLC | Y39: SADAIC | Z39: Latin Autor | AA39: AMRA | AB39: Latin Autor | AC39: Latin Autor | AD39: Latin Autor | AE39: Latin Autor | AF39: SACM | AG39: Latin Autor | AH39: Latin Autor | AI39: Latin Autor | AJ39: AMRA | AK39: AMRA | AL39: AMRA | AM39: AMRA | AN39: AMRA | AO39: AMRA | AP39: AMRA | AQ39: AMRA | AR39: AMRA | AS39: AMRA | AT39: AMRA | AU39: KOMCA | AV39: AMRA | AW39: AMRA | AX39: AMRA | AY39: AMRA
B40: APRA-AMCOS | C40: Kobalt Paid By | D40: AMRA | E40: AMRA | F40: AMRA | G40: AMRA | H40: AMRA | I40: AMRA | J40: AMRA | K40: AMRA | L40: AMRA | M40: AMRA | N40: AMRA | O40: AMRA | P40: AMRA | Q40: AMRA | R40: AMRA | S40: AMRA | T40: AMRA | U40: AMRA | V40: AMRA | W40: AMRA | X40: MLC | Y40: SADAIC | Z40: AMRA | AA40: AMRA | AB40: AMRA | AC40: AMRA | AD40: AMRA | AE40: AMRA | AF40: SACM | AG40: AMRA | AH40: AMRA | AI40: AMRA | AJ40: AMRA | AK40: AMRA | AL40: AMRA | AM40: AMRA | AN40: AMRA | AO40: AMRA | AP40: AMRA | AQ40: AMRA | AR40: AMRA | AS40: AMRA | AT40: AMRA | AU40: EKKO | AV40: AMRA | AW40: AMRA | AX40: AMRA | AY40: AMRA
A41: ASCAP | B41: ASCAP | C41: Licensed By | D41: AMRA | E41: AMRA | F41: AMRA | G41: AMRA | H41: AMRA | I41: AMRA | J41: AMRA | K41: AMRA | L41: AMRA | M41: AMRA | N41: AMRA | O41: AMRA | P41: AMRA | Q41: AMRA | R41: AMRA | S41: AMRA | T41: AMRA | U41: AMRA | V41: AMRA | W41: AMRA | X41: MLC | Y41: SADAIC | Z41: Latin Autor | AA41: AMRA | AB41: Latin Autor | AC41: Latin Autor | AD41: Latin Autor | AE41: Latin Autor | AF41: SACM | AG41: Latin Autor | AH41: Latin Autor | AI41: Latin Autor | AJ41: AMRA | AK41: AMRA | AL41: AMRA | AM41: AMRA | AN41: AMRA | AO41: AMRA | AP41: AMRA | AQ41: AMRA | AR41: AMRA | AS41: AMRA | AT41: AMRA | AU41: KOMCA | AV41: AMRA | AW41: AMRA | AX41: AMRA | AY41: AMRA
B42: ASCAP | C42: Licensor Pays | D42: AMRA | E42: AMRA | F42: AMRA | G42: AMRA | H42: AMRA | I42: AMRA | J42: AMRA | K42: AMRA | L42: AMRA | M42: AMRA | N42: AMRA | O42: AMRA | P42: AMRA | Q42: AMRA | R42: AMRA | S42: AMRA | T42: AMRA | U42: AMRA | V42: AMRA | W42: AMRA | X42: MLC | Y42: SADAIC | Z42: Latin Autor | AA42: AMRA | AB42: Latin Autor | AC42: Latin Autor | AD42: Latin Autor | AE42: Latin Autor | AF42: SACM | AG42: Latin Autor | AH42: Latin Autor | AI42: Latin Autor | AJ42: AMRA | AK42: AMRA | AL42: AMRA | AM42: AMRA | AN42: AMRA | AO42: AMRA | AP42: AMRA | AQ42: AMRA | AR42: AMRA | AS42: AMRA | AT42: AMRA | AU42: KOMCA | AV42: AMRA | AW42: AMRA | AX42: AMRA | AY42: AMRA
B43: ASCAP | C43: Kobalt Paid By | D43: AMRA | E43: AMRA | F43: AMRA | G43: AMRA | H43: AMRA | I43: AMRA | J43: AMRA | K43: AMRA | L43: AMRA | M43: AMRA | N43: AMRA | O43: AMRA | P43: AMRA | Q43: AMRA | R43: AMRA | S43: AMRA | T43: AMRA | U43: AMRA | V43: AMRA | W43: AMRA | X43: MLC | Y43: SADAIC | Z43: AMRA | AA43: AMRA | AB43: AMRA | AC43: AMRA | AD43: AMRA | AE43: AMRA | AF43: SACM | AG43: AMRA | AH43: AMRA | AI43: AMRA | AJ43: AMRA | AK43: AMRA | AL43: AMRA | AM43: AMRA | AN43: AMRA | AO43: AMRA | AP43: AMRA | AQ43: AMRA | AR43: AMRA | AS43: AMRA | AT43: AMRA | AU43: EKKO | AV43: AMRA | AW43: AMRA | AX43: AMRA | AY43: AMRA
A44: BMI | B44: BMI | C44: Licensed By | D44: AMRA | E44: AMRA | F44: AMRA | G44: AMRA | H44: AMRA | I44: AMRA | J44: AMRA | K44: AMRA | L44: AMRA | M44: AMRA | N44: AMRA | O44: AMRA | P44: AMRA | Q44: AMRA | R44: AMRA | S44: AMRA | T44: AMRA | U44: AMRA | V44: AMRA | W44: AMRA | X44: MLC | Y44: SADAIC | Z44: Latin Autor | AA44: AMRA | AB44: Latin Autor | AC44: Latin Autor | AD44: Latin Autor | AE44: Latin Autor | AF44: SACM | AG44: Latin Autor | AH44: Latin Autor | AI44: Latin Autor | AJ44: AMRA | AK44: AMRA | AL44: AMRA | AM44: AMRA | AN44: AMRA | AO44: AMRA | AP44: AMRA | AQ44: AMRA | AR44: AMRA | AS44: AMRA | AT44: AMRA | AU44: KOMCA | AV44: AMRA | AW44: AMRA | AX44: AMRA | AY44: AMRA
B45: BMI | C45: Licensor Pays | D45: AMRA | E45: AMRA | F45: AMRA | G45: AMRA | H45: AMRA | I45: AMRA | J45: AMRA | K45: AMRA | L45: AMRA | M45: AMRA | N45: AMRA | O45: AMRA | P45: AMRA | Q45: AMRA | R45: AMRA | S45: AMRA | T45: AMRA | U45: AMRA | V45: AMRA | W45: AMRA | X45: MLC | Y45: SADAIC | Z45: Latin Autor | AA45: AMRA | AB45: Latin Autor | AC45: Latin Autor | AD45: Latin Autor | AE45: Latin Autor | AF45: SACM | AG45: Latin Autor | AH45: Latin Autor | AI45: Latin Autor | AJ45: AMRA | AK45: AMRA | AL45: AMRA | AM45: AMRA | AN45: AMRA | AO45: AMRA | AP45: AMRA | AQ45: AMRA | AR45: AMRA | AS45: AMRA | AT45: AMRA | AU45: KOMCA | AV45: AMRA | AW45: AMRA | AX45: AMRA | AY45: AMRA
B46: BMI | C46: Kobalt Paid By | D46: AMRA | E46: AMRA | F46: AMRA | G46: AMRA | H46: AMRA | I46: AMRA | J46: AMRA | K46: AMRA | L46: AMRA | M46: AMRA | N46: AMRA | O46: AMRA | P46: AMRA | Q46: AMRA | R46: AMRA | S46: AMRA | T46: AMRA | U46: AMRA | V46: AMRA | W46: AMRA | X46: MLC | Y46: SADAIC | Z46: AMRA | AA46: AMRA | AB46: AMRA | AC46: AMRA | AD46: AMRA | AE46: AMRA | AF46: SACM | AG46: AMRA | AH46: AMRA | AI46: AMRA | AJ46: AMRA | AK46: AMRA | AL46: AMRA | AM46: AMRA | AN46: AMRA | AO46: AMRA | AP46: AMRA | AQ46: AMRA | AR46: AMRA | AS46: AMRA | AT46: AMRA | AU46: EKKO | AV46: AMRA | AW46: AMRA | AX46: AMRA | AY46: AMRA
A47: GMR | B47: GMR | C47: Licensed By | D47: AMRA | E47: AMRA | F47: AMRA | G47: AMRA | H47: AMRA | I47: AMRA | J47: AMRA | K47: AMRA | L47: AMRA | M47: AMRA | N47: AMRA | O47: AMRA | P47: AMRA | Q47: AMRA | R47: AMRA | S47: AMRA | T47: AMRA | U47: AMRA | V47: AMRA | W47: AMRA | X47: MLC | Y47: SADAIC | Z47: Latin Autor | AA47: AMRA | AB47: Latin Autor | AC47: Latin Autor | AD47: Latin Autor | AE47: Latin Autor | AF47: SACM | AG47: Latin Autor | AH47: Latin Autor | AI47: Latin Autor | AJ47: AMRA | AK47: AMRA | AL47: AMRA | AM47: AMRA | AN47: AMRA | AO47: AMRA | AP47: AMRA | AQ47: AMRA | AR47: AMRA | AS47: AMRA | AT47: AMRA | AU47: KOMCA | AV47: AMRA | AW47: AMRA | AX47: AMRA | AY47: AMRA
B48: GMR | C48: Licensor Pays | D48: AMRA | E48: AMRA | F48: AMRA | G48: AMRA | H48: AMRA | I48: AMRA | J48: AMRA | K48: AMRA | L48: AMRA | M48: AMRA | N48: AMRA | O48: AMRA | P48: AMRA | Q48: AMRA | R48: AMRA | S48: AMRA | T48: AMRA | U48: AMRA | V48: AMRA | W48: AMRA | X48: MLC | Y48: SADAIC | Z48: Latin Autor | AA48: AMRA | AB48: Latin Autor | AC48: Latin Autor | AD48: Latin Autor | AE48: Latin Autor | AF48: SACM | AG48: Latin Autor | AH48: Latin Autor | AI48: Latin Autor | AJ48: AMRA | AK48: AMRA | AL48: AMRA | AM48: AMRA | AN48: AMRA | AO48: AMRA | AP48: AMRA | AQ48: AMRA | AR48: AMRA | AS48: AMRA | AT48: AMRA | AU48: KOMCA | AV48: AMRA | AW48: AMRA | AX48: AMRA | AY48: AMRA
B49: GMR | C49: Kobalt Paid By | D49: AMRA | E49: AMRA | F49: AMRA | G49: AMRA | H49: AMRA | I49: AMRA | J49: AMRA | K49: AMRA | L49: AMRA | M49: AMRA | N49: AMRA | O49: AMRA | P49: AMRA | Q49: AMRA | R49: AMRA | S49: AMRA | T49: AMRA | U49: AMRA | V49: AMRA | W49: AMRA | X49: MLC | Y49: SADAIC | Z49: AMRA | AA49: AMRA | AB49: AMRA | AC49: AMRA | AD49: AMRA | AE49: AMRA | AF49: SACM | AG49: AMRA | AH49: AMRA | AI49: AMRA | AJ49: AMRA | AK49: AMRA | AL49: AMRA | AM49: AMRA | AN49: AMRA | AO49: AMRA | AP49: AMRA | AQ49: AMRA | AR49: AMRA | AS49: AMRA | AT49: AMRA | AU49: EKKO | AV49: AMRA | AW49: AMRA | AX49: AMRA | AY49: AMRA
A50: SOCAN | B50: SOCAN | C50: Licensed By | D50: AMRA | E50: AMRA | F50: AMRA | G50: AMRA | H50: AMRA | I50: AMRA | J50: AMRA | K50: AMRA | L50: AMRA | M50: AMRA | N50: AMRA | O50: AMRA | P50: AMRA | Q50: AMRA | R50: AMRA | S50: AMRA | T50: AMRA | U50: AMRA | V50: AMRA | W50: AMRA | X50: MLC | Y50: SADAIC | Z50: Latin Autor | AA50: AMRA | AB50: Latin Autor | AC50: Latin Autor | AD50: Latin Autor | AE50: Latin Autor | AF50: SACM | AG50: Latin Autor | AH50: Latin Autor | AI50: Latin Autor | AJ50: AMRA | AK50: AMRA | AL50: AMRA | AM50: AMRA | AN50: AMRA | AO50: AMRA | AP50: AMRA | AQ50: AMRA | AR50: AMRA | AS50: AMRA | AT50: AMRA | AU50: KOMCA | AV50: AMRA | AW50: AMRA | AX50: AMRA | AY50: AMRA
B51: SOCAN | C51: Licensor Pays | D51: AMRA | E51: AMRA | F51: AMRA | G51: AMRA | H51: AMRA | I51: AMRA | J51: AMRA | K51: AMRA | L51: AMRA | M51: AMRA | N51: AMRA | O51: AMRA | P51: AMRA | Q51: AMRA | R51: AMRA | S51: AMRA | T51: AMRA | U51: AMRA | V51: AMRA | W51: AMRA | X51: MLC | Y51: SADAIC | Z51: Latin Autor | AA51: AMRA | AB51: Latin Autor | AC51: Latin Autor | AD51: Latin Autor | AE51: Latin Autor | AF51: SACM | AG51: Latin Autor | AH51: Latin Autor | AI51: Latin Autor | AJ51: AMRA | AK51: AMRA | AL51: AMRA | AM51: AMRA | AN51: AMRA | AO51: AMRA | AP51: AMRA | AQ51: AMRA | AR51: AMRA | AS51: AMRA | AT51: AMRA | AU51: KOMCA | AV51: AMRA | AW51: AMRA | AX51: AMRA | AY51: AMRA
B52: SOCAN | C52: Kobalt Paid By | D52: AMRA | E52: AMRA | F52: AMRA | G52: AMRA | H52: AMRA | I52: AMRA | J52: AMRA | K52: AMRA | L52: AMRA | M52: AMRA | N52: AMRA | O52: AMRA | P52: AMRA | Q52: AMRA | R52: AMRA | S52: AMRA | T52: AMRA | U52: AMRA | V52: AMRA | W52: AMRA | X52: MLC | Y52: SADAIC | Z52: AMRA | AA52: AMRA | AB52: AMRA | AC52: AMRA | AD52: AMRA | AE52: AMRA | AF52: SACM | AG52: AMRA | AH52: AMRA | AI52: AMRA | AJ52: AMRA | AK52: AMRA | AL52: AMRA | AM52: AMRA | AN52: AMRA | AO52: AMRA | AP52: AMRA | AQ52: AMRA | AR52: AMRA | AS52: AMRA | AT52: AMRA | AU52: EKKO | AV52: AMRA | AW52: AMRA | AX52: AMRA | AY52: AMRA
A53: MCPS-PRS | B53: MCPS-PRS | C53: Licensed By | D53: AMRA | E53: AMRA | F53: AMRA | G53: AMRA | H53: AMRA | I53: AMRA | J53: AMRA | K53: AMRA | L53: AMRA | M53: AMRA | N53: AMRA | O53: AMRA | P53: AMRA | Q53: AMRA | R53: AMRA | S53: AMRA | T53: AMRA | U53: AMRA | V53: AMRA | W53: AMRA | X53: MLC | Y53: SADAIC | Z53: Latin Autor | AA53: AMRA | AB53: Latin Autor | AC53: Latin Autor | AD53: Latin Autor | AE53: Latin Autor | AF53: SACM | AG53: Latin Autor | AH53: Latin Autor | AI53: Latin Autor | AJ53: AMRA | AK53: AMRA | AL53: AMRA | AM53: AMRA | AN53: AMRA | AO53: AMRA | AP53: AMRA | AQ53: AMRA | AR53: AMRA | AS53: AMRA | AT53: AMRA | AU53: KOMCA | AV53: AMRA | AW53: AMRA | AX53: AMRA | AY53: AMRA
B54: MCPS-PRS | C54: Licensor Pays | D54: AMRA | E54: AMRA | F54: AMRA | G54: AMRA | H54: AMRA | I54: AMRA | J54: AMRA | K54: AMRA | L54: AMRA | M54: AMRA | N54: AMRA | O54: AMRA | P54: AMRA | Q54: AMRA | R54: AMRA | S54: AMRA | T54: AMRA | U54: AMRA | V54: AMRA | W54: AMRA | X54: MLC | Y54: SADAIC | Z54: Latin Autor | AA54: AMRA | AB54: Latin Autor | AC54: Latin Autor | AD54: Latin Autor | AE54: Latin Autor | AF54: SACM | AG54: Latin Autor | AH54: Latin Autor | AI54: Latin Autor | AJ54: AMRA | AK54: AMRA | AL54: AMRA | AM54: AMRA | AN54: AMRA | AO54: AMRA | AP54: AMRA | AQ54: AMRA | AR54: AMRA | AS54: AMRA | AT54: AMRA | AU54: KOMCA | AV54: AMRA | AW54: AMRA | AX54: AMRA | AY54: AMRA
B55: MCPS-PRS | C55: Kobalt Paid By | D55: AMRA | E55: AMRA | F55: AMRA | G55: AMRA | H55: AMRA | I55: AMRA | J55: AMRA | K55: AMRA | L55: AMRA | M55: AMRA | N55: AMRA | O55: AMRA | P55: AMRA | Q55: AMRA | R55: AMRA | S55: AMRA | T55: AMRA | U55: AMRA | V55: AMRA | W55: AMRA | X55: MLC | Y55: SADAIC | Z55: AMRA | AA55: AMRA | AB55: AMRA | AC55: AMRA | AD55: AMRA | AE55: AMRA | AF55: SACM | AG55: AMRA | AH55: AMRA | AI55: AMRA | AJ55: AMRA | AK55: AMRA | AL55: AMRA | AM55: AMRA | AN55: AMRA | AO55: AMRA | AP55: AMRA | AQ55: AMRA | AR55: AMRA | AS55: AMRA | AT55: AMRA | AU55: EKKO | AV55: AMRA | AW55: AMRA | AX55: AMRA | AY55: AMRA
A56: SAMRO / CAPASSO | B56: SAMRO | C56: Licensed By | D56: AMRA | E56: AMRA | F56: AMRA | G56: AMRA | H56: AMRA | I56: AMRA | J56: AMRA | K56: AMRA | L56: AMRA | M56: AMRA | N56: AMRA | O56: AMRA | P56: AMRA | Q56: AMRA | R56: AMRA | S56: AMRA | T56: AMRA | U56: AMRA | V56: AMRA | W56: AMRA | X56: MLC | Y56: SADAIC | Z56: Latin Autor | AA56: AMRA | AB56: Latin Autor | AC56: Latin Autor | AD56: Latin Autor | AE56: Latin Autor | AF56: SACM | AG56: Latin Autor | AH56: Latin Autor | AI56: Latin Autor | AJ56: AMRA | AK56: AMRA | AL56: AMRA | AM56: AMRA | AN56: AMRA | AO56: AMRA | AP56: AMRA | AQ56: AMRA | AR56: AMRA | AS56: AMRA | AT56: AMRA | AU56: KOMCA | AV56: AMRA | AW56: AMRA | AX56: AMRA | AY56: AMRA
B57: SAMRO | C57: Licensor Pays | D57: AMRA | E57: AMRA | F57: AMRA | G57: AMRA | H57: AMRA | I57: AMRA | J57: AMRA | K57: AMRA | L57: AMRA | M57: AMRA | N57: AMRA | O57: AMRA | P57: AMRA | Q57: AMRA | R57: AMRA | S57: AMRA | T57: AMRA | U57: AMRA | V57: AMRA | W57: AMRA | X57: MLC | Y57: SADAIC | Z57: Latin Autor | AA57: AMRA | AB57: Latin Autor | AC57: Latin Autor | AD57: Latin Autor | AE57: Latin Autor | AF57: SACM | AG57: Latin Autor | AH57: Latin Autor | AI57: Latin Autor | AJ57: AMRA | AK57: AMRA | AL57: AMRA | AM57: AMRA | AN57: AMRA | AO57: AMRA | AP57: AMRA | AQ57: AMRA | AR57: AMRA | AS57: AMRA | AT57: AMRA | AU57: KOMCA | AV57: AMRA | AW57: AMRA | AX57: AMRA | AY57: AMRA
B58: SAMRO | C58: Kobalt Paid By | D58: AMRA | E58: AMRA | F58: AMRA | G58: AMRA | H58: AMRA | I58: AMRA | J58: AMRA | K58: AMRA | L58: AMRA | M58: AMRA | N58: AMRA | O58: AMRA | P58: AMRA | Q58: AMRA | R58: AMRA | S58: AMRA | T58: AMRA | U58: AMRA | V58: AMRA | W58: AMRA | X58: MLC | Y58: SADAIC | Z58: AMRA | AA58: AMRA | AB58: AMRA | AC58: AMRA | AD58: AMRA | AE58: AMRA | AF58: SACM | AG58: AMRA | AH58: AMRA | AI58: AMRA | AJ58: AMRA | AK58: AMRA | AL58: AMRA | AM58: AMRA | AN58: AMRA | AO58: AMRA | AP58: AMRA | AQ58: AMRA | AR58: AMRA | AS58: AMRA | AT58: AMRA | AU58: EKKO | AV58: AMRA | AW58: AMRA | AX58: AMRA | AY58: AMRA
A59: SESAC | B59: SESAC | C59: Licensed By | D59: AMRA | E59: AMRA | F59: AMRA | G59: AMRA | H59: AMRA | I59: AMRA | J59: AMRA | K59: AMRA | L59: AMRA | M59: AMRA | N59: AMRA | O59: AMRA | P59: AMRA | Q59: AMRA | R59: AMRA | S59: AMRA | T59: AMRA | U59: AMRA | V59: AMRA | W59: AMRA | X59: MLC | Y59: SADAIC | Z59: Latin Autor | AA59: AMRA | AB59: Latin Autor | AC59: Latin Autor | AD59: Latin Autor | AE59: Latin Autor | AF59: SACM | AG59: Latin Autor | AH59: Latin Autor | AI59: Latin Autor | AJ59: AMRA | AK59: AMRA | AL59: AMRA | AM59: AMRA | AN59: AMRA | AO59: AMRA | AP59: AMRA | AQ59: AMRA | AR59: AMRA | AS59: AMRA | AT59: AMRA | AU59: KOMCA | AV59: AMRA | AW59: AMRA | AX59: AMRA | AY59: AMRA
B60: SESAC | C60: Licensor Pays | D60: AMRA | E60: AMRA | F60: AMRA | G60: AMRA | H60: AMRA | I60: AMRA | J60: AMRA | K60: AMRA | L60: AMRA | M60: AMRA | N60: AMRA | O60: AMRA | P60: AMRA | Q60: AMRA | R60: AMRA | S60: AMRA | T60: AMRA | U60: AMRA | V60: AMRA | W60: AMRA | X60: MLC | Y60: SADAIC | Z60: Latin Autor | AA60: AMRA | AB60: Latin Autor | AC60: Latin Autor | AD60: Latin Autor | AE60: Latin Autor | AF60: SACM | AG60: Latin Autor | AH60: Latin Autor | AI60: Latin Autor | AJ60: AMRA | AK60: AMRA | AL60: AMRA | AM60: AMRA | AN60: AMRA | AO60: AMRA | AP60: AMRA | AQ60: AMRA | AR60: AMRA | AS60: AMRA | AT60: AMRA | AU60: KOMCA | AV60: AMRA | AW60: AMRA | AX60: AMRA | AY60: AMRA
B61: SESAC | C61: Kobalt Paid By | D61: AMRA | E61: AMRA | F61: AMRA | G61: AMRA | H61: AMRA | I61: AMRA | J61: AMRA | K61: AMRA | L61: AMRA | M61: AMRA | N61: AMRA | O61: AMRA | P61: AMRA | Q61: AMRA | R61: AMRA | S61: AMRA | T61: AMRA | U61: AMRA | V61: AMRA | W61: AMRA | X61: MLC | Y61: SADAIC | Z61: AMRA | AA61: AMRA | AB61: AMRA | AC61: AMRA | AD61: AMRA | AE61: AMRA | AF61: SACM | AG61: AMRA | AH61: AMRA | AI61: AMRA | AJ61: AMRA | AK61: AMRA | AL61: AMRA | AM61: AMRA | AN61: AMRA | AO61: AMRA | AP61: AMRA | AQ61: AMRA | AR61: AMRA | AS61: AMRA | AT61: AMRA | AU61: EKKO | AV61: AMRA | AW61: AMRA | AX61: AMRA | AY61: AMRA
A62: Lat-Am Rep
A63: ABRAMUS | B63: ABRAMUS | C63: Licensed By | D63: MINT | E63: MINT | F63: MINT | G63: MINT | H63: SGAE | I63: SGAE | J63: MINT | K63: SUISA | L63: MINT | M63: MINT | N63: MINT | O63: MINT | P63: QUERY SOURCE/ TERR OWNER | Q63: QUERY SOURCE/ TERR OWNER | R63: QUERY SOURCE/ TERR OWNER | S63: RAO | T63: ACUM | U63: ESMAA | V63: MSG | W63: CMRRA | X63: MLC | Y63: SADAIC | Z63: Latin Autor | AA63: ABRAMUS | AB63: Latin Autor | AC63: Latin Autor | AD63: Latin Autor | AE63: Latin Autor | AF63: SACM | AG63: Latin Autor | AH63: Latin Autor | AI63: Latin Autor | AJ63: AMRA | AK63: AMRA | AL63: QUERY SOURCE/ TERR OWNER | AM63: QUERY SOURCE/ TERR OWNER | AN63: QUERY SOURCE/ TERR OWNER | AO63: QUERY SOURCE/ TERR OWNER | AP63: QUERY SOURCE/ TERR OWNER | AQ63: QUERY SOURCE/ TERR OWNER | AR63: QUERY SOURCE/ TERR OWNER | AS63: QUERY SOURCE/ TERR OWNER | AT63: QUERY SOURCE/ TERR OWNER | AU63: KOMCA | AV63: QUERY SOURCE/ TERR OWNER | AW63: QUERY SOURCE/ TERR OWNER | AX63: CAPASSO | AY63: QUERY SOURCE/ TERR OWNER
B64: ABRAMUS | C64: Licensor Pays | D64: SUISA | E64: SUISA | F64: SUISA | G64: SUISA | H64: SGAE | I64: SGAE | J64: SUISA | K64: SUISA | L64: SUISA | M64: SUISA | N64: SUISA | O64: SUISA | P64: QUERY SOURCE/ TERR OWNER | Q64: QUERY SOURCE/ TERR OWNER | R64: QUERY SOURCE/ TERR OWNER | S64: Blue Sun | T64: Dalia | U64: Pop Arabia | V64: Zeplin | W64: CMRRA | X64: MLC | Y64: SADAIC | Z64: Latin Autor (Processed by BO) | AA64: ABRAMUS | AB64: Latin Autor (Processed by BO) | AC64: Latin Autor (Processed by BO) | AD64: Latin Autor (Processed by BO) | AE64: Latin Autor (Processed by BO) | AF64: SACM | AG64: Latin Autor (Processed by BO) | AH64: Latin Autor (Processed by BO) | AI64: Latin Autor (Processed by BO) | AJ64: AMRA | AK64: AMRA | AL64: QUERY SOURCE/ TERR OWNER | AM64: QUERY SOURCE/ TERR OWNER | AN64: QUERY SOURCE/ TERR OWNER | AO64: QUERY SOURCE/ TERR OWNER | AP64: QUERY SOURCE/ TERR OWNER | AQ64: QUERY SOURCE/ TERR OWNER | AR64: QUERY SOURCE/ TERR OWNER | AS64: QUERY SOURCE/ TERR OWNER | AT64: QUERY SOURCE/ TERR OWNER | AU64: KOMCA | AV64: QUERY SOURCE/ TERR OWNER | AW64: QUERY SOURCE/ TERR OWNER | AX64: CAPASSO | AY64: QUERY SOURCE/ TERR OWNER
B65: ABRAMUS | C65: Kobalt Paid By | D65: GEMA | E65: SIAE | F65: BUMA-STEMRA | G65: STIM | H65: SGAE | I65: SGAE | J65: STIM | K65: SUISA | L65: MCPS-PRS | M65: IDM | N65: D-Version | O65: Schubert | P65: QUERY SOURCE/ TERR OWNER | Q65: QUERY SOURCE/ TERR OWNER | R65: QUERY SOURCE/ TERR OWNER | S65: Blue Sun | T65: Dalia | U65: Pop Arabia | V65: Zeplin | W65: CMRRA | X65: MLC | Y65: SADAIC | Z65: No Membership | AA65: ABRAMUS | AB65: Latin Autor | AC65: Latin Autor | AD65: Latin Autor | AE65: Latin Autor | AF65: SACM | AG65: No Membership | AH65: Latin Autor | AI65: Latin Autor | AJ65: AMRA | AK65: AMRA | AL65: QUERY SOURCE/ TERR OWNER | AM65: QUERY SOURCE/ TERR OWNER | AN65: QUERY SOURCE/ TERR OWNER | AO65: QUERY SOURCE/ TERR OWNER | AP65: QUERY SOURCE/ TERR OWNER | AQ65: QUERY SOURCE/ TERR OWNER | AR65: QUERY SOURCE/ TERR OWNER | AS65: QUERY SOURCE/ TERR OWNER | AT65: QUERY SOURCE/ TERR OWNER | AU65: EKKO | AV65: QUERY SOURCE/ TERR OWNER | AW65: QUERY SOURCE/ TERR OWNER | AX65: CAPASSO | AY65: QUERY SOURCE/ TERR OWNER
A66: APDAYC | B66: APDAYC | C66: Licensed By | D66: AMRA | E66: AMRA | F66: AMRA | G66: AMRA | H66: AMRA | I66: AMRA | J66: AMRA | K66: AMRA | L66: AMRA | M66: AMRA | N66: AMRA | O66: AMRA | P66: AMRA | Q66: AMRA | R66: AMRA | S66: AMRA | T66: AMRA | U66: AMRA | V66: AMRA | W66: CMRRA | X66: MLC | Y66: SADAIC | Z66: Latin Autor | AA66: AMRA | AB66: Latin Autor | AC66: Latin Autor | AD66: Latin Autor | AE66: Latin Autor | AF66: SACM | AG66: Latin Autor | AH66: Latin Autor | AI66: Latin Autor | AJ66: AMRA | AK66: AMRA | AL66: AMRA | AM66: AMRA | AN66: AMRA | AO66: AMRA | AP66: AMRA | AQ66: AMRA | AR66: AMRA | AS66: AMRA | AT66: AMRA | AU66: KOMCA | AV66: AMRA | AW66: AMRA | AX66: AMRA | AY66: AMRA
B67: APDAYC | C67: Licensor Pays | D67: AMRA | E67: AMRA | F67: AMRA | G67: AMRA | H67: AMRA | I67: AMRA | J67: AMRA | K67: AMRA | L67: AMRA | M67: AMRA | N67: AMRA | O67: AMRA | P67: AMRA | Q67: AMRA | R67: AMRA | S67: AMRA | T67: AMRA | U67: AMRA | V67: AMRA | W67: CMRRA | X67: MLC | Y67: SADAIC | Z67: Latin Autor (Processed by BO) | AA67: AMRA | AB67: Latin Autor (Processed by BO) | AC67: Latin Autor (Processed by BO) | AD67: Latin Autor (Processed by BO) | AE67: Latin Autor (Processed by BO) | AF67: SACM | AG67: Latin Autor (Processed by BO) | AH67: Latin Autor (Processed by BO) | AI67: Latin Autor (Processed by BO) | AJ67: AMRA | AK67: AMRA | AL67: AMRA | AM67: AMRA | AN67: AMRA | AO67: AMRA | AP67: AMRA | AQ67: AMRA | AR67: AMRA | AS67: AMRA | AT67: AMRA | AU67: KOMCA | AV67: AMRA | AW67: AMRA | AX67: AMRA | AY67: AMRA
B68: APDAYC | C68: Kobalt Paid By | D68: AMRA | E68: AMRA | F68: AMRA | G68: AMRA | H68: AMRA | I68: AMRA | J68: AMRA | K68: AMRA | L68: AMRA | M68: AMRA | N68: AMRA | O68: AMRA | P68: AMRA | Q68: AMRA | R68: AMRA | S68: AMRA | T68: AMRA | U68: AMRA | V68: AMRA | W68: CMRRA | X68: MLC | Y68: SADAIC | Z68: No Membership | AA68: AMRA | AB68: Latin Autor | AC68: Latin Autor | AD68: Latin Autor | AE68: Latin Autor | AF68: SACM | AG68: No Membership | AH68: Latin Autor | AI68: Latin Autor | AJ68: AMRA | AK68: AMRA | AL68: AMRA | AM68: AMRA | AN68: AMRA | AO68: AMRA | AP68: AMRA | AQ68: AMRA | AR68: AMRA | AS68: AMRA | AT68: AMRA | AU68: EKKO | AV68: AMRA | AW68: AMRA | AX68: AMRA | AY68: AMRA
A69: SACM | B69: SACM | C69: Licensed By | D69: ICE | E69: ICE | F69: ICE | G69: ICE | H69: ICE | I69: ICE | J69: ICE | K69: ICE | L69: ICE | M69: ICE | N69: ICE | O69: ICE | P69: ICE | Q69: ICE | R69: ICE | S69: ICE | T69: ICE | U69: ICE | V69: ICE | W69: CMRRA | X69: MLC | Y69: SADAIC | Z69: Latin Autor | AA69: ABRAMUS | AB69: Latin Autor | AC69: Latin Autor | AD69: Latin Autor | AE69: Latin Autor | AF69: SACM | AG69: Latin Autor | AH69: Latin Autor | AI69: Latin Autor | AJ69: AMRA | AK69: AMRA | AL69: QUERY SOURCE/ TERR OWNER | AM69: QUERY SOURCE/ TERR OWNER | AN69: QUERY SOURCE/ TERR OWNER | AO69: QUERY SOURCE/ TERR OWNER | AP69: QUERY SOURCE/ TERR OWNER | AQ69: QUERY SOURCE/ TERR OWNER | AR69: QUERY SOURCE/ TERR OWNER | AS69: QUERY SOURCE/ TERR OWNER | AT69: QUERY SOURCE/ TERR OWNER | AU69: KOMCA | AV69: QUERY SOURCE/ TERR OWNER | AW69: QUERY SOURCE/ TERR OWNER | AX69: CAPASSO | AY69: QUERY SOURCE/ TERR OWNER
B70: SACM | C70: Licensor Pays | D70: MCPS-PRS | E70: MCPS-PRS | F70: MCPS-PRS | G70: MCPS-PRS | H70: MCPS-PRS | I70: MCPS-PRS | J70: MCPS-PRS | K70: MCPS-PRS | L70: MCPS-PRS | M70: MCPS-PRS | N70: MCPS-PRS | O70: MCPS-PRS | P70: MCPS-PRS | Q70: MCPS-PRS | R70: MCPS-PRS | S70: MCPS-PRS | T70: MCPS-PRS | U70: MCPS-PRS | V70: MCPS-PRS | W70: CMRRA | X70: MLC | Y70: SADAIC | Z70: Latin Autor (Processed by BO) | AA70: ABRAMUS | AB70: Latin Autor (Processed by BO) | AC70: Latin Autor (Processed by BO) | AD70: Latin Autor (Processed by BO) | AE70: Latin Autor (Processed by BO) | AF70: SACM | AG70: Latin Autor (Processed by BO) | AH70: Latin Autor (Processed by BO) | AI70: Latin Autor (Processed by BO) | AJ70: AMRA | AK70: AMRA | AL70: QUERY SOURCE/ TERR OWNER | AM70: QUERY SOURCE/ TERR OWNER | AN70: QUERY SOURCE/ TERR OWNER | AO70: QUERY SOURCE/ TERR OWNER | AP70: QUERY SOURCE/ TERR OWNER | AQ70: QUERY SOURCE/ TERR OWNER | AR70: QUERY SOURCE/ TERR OWNER | AS70: QUERY SOURCE/ TERR OWNER | AT70: QUERY SOURCE/ TERR OWNER | AU70: KOMCA | AV70: QUERY SOURCE/ TERR OWNER | AW70: QUERY SOURCE/ TERR OWNER | AX70: CAPASSO | AY70: QUERY SOURCE/ TERR OWNER
B71: SACM | C71: Kobalt Paid By | D71: MCPS-PRS | E71: MCPS-PRS | F71: MCPS-PRS | G71: MCPS-PRS | H71: MCPS-PRS | I71: MCPS-PRS | J71: MCPS-PRS | K71: MCPS-PRS | L71: MCPS-PRS | M71: MCPS-PRS | N71: MCPS-PRS | O71: MCPS-PRS | P71: IDM | Q71: D-Version | R71: Schubert | S71: Blue Sun | T71: Dalia | U71: Pop Arabia | V71: Zeplin | W71: CMRRA | X71: MLC | Y71: SADAIC | Z71: No Membership | AA71: ABRAMUS | AB71: Latin Autor | AC71: Latin Autor | AD71: Latin Autor | AE71: Latin Autor | AF71: SACM | AG71: No Membership | AH71: Latin Autor | AI71: Latin Autor | AJ71: AMRA | AK71: AMRA | AL71: QUERY SOURCE/ TERR OWNER | AM71: QUERY SOURCE/ TERR OWNER | AN71: QUERY SOURCE/ TERR OWNER | AO71: QUERY SOURCE/ TERR OWNER | AP71: QUERY SOURCE/ TERR OWNER | AQ71: QUERY SOURCE/ TERR OWNER | AR71: QUERY SOURCE/ TERR OWNER | AS71: QUERY SOURCE/ TERR OWNER | AT71: QUERY SOURCE/ TERR OWNER | AU71: EKKO | AV71: QUERY SOURCE/ TERR OWNER | AW71: QUERY SOURCE/ TERR OWNER | AX71: CAPASSO | AY71: QUERY SOURCE/ TERR OWNER
A72: SADAIC | B72: SADIAC | C72: Licensed By | D72: AMRA | E72: AMRA | F72: AMRA | G72: AMRA | H72: AMRA | I72: AMRA | J72: AMRA | K72: AMRA | L72: AMRA | M72: AMRA | N72: AMRA | O72: AMRA | P72: AMRA | Q72: AMRA | R72: AMRA | S72: AMRA | T72: AMRA | U72: AMRA | V72: AMRA | W72: CMRRA | X72: MLC | Y72: SADAIC | Z72: Latin Autor | AA72: AMRA | AB72: Latin Autor | AC72: Latin Autor | AD72: Latin Autor | AE72: Latin Autor | AF72: SACM | AG72: Latin Autor | AH72: Latin Autor | AI72: Latin Autor | AJ72: AMRA | AK72: AMRA | AL72: AMRA | AM72: AMRA | AN72: AMRA | AO72: AMRA | AP72: AMRA | AQ72: AMRA | AR72: AMRA | AS72: AMRA | AT72: AMRA | AU72: KOMCA | AV72: AMRA | AW72: AMRA | AX72: AMRA | AY72: AMRA
B73: SADIAC | C73: Licensor Pays | D73: AMRA | E73: AMRA | F73: AMRA | G73: AMRA | H73: AMRA | I73: AMRA | J73: AMRA | K73: AMRA | L73: AMRA | M73: AMRA | N73: AMRA | O73: AMRA | P73: AMRA | Q73: AMRA | R73: AMRA | S73: AMRA | T73: AMRA | U73: AMRA | V73: AMRA | W73: CMRRA | X73: MLC | Y73: SADAIC | Z73: Latin Autor (Processed by BO) | AA73: AMRA | AB73: Latin Autor (Processed by BO) | AC73: Latin Autor (Processed by BO) | AD73: Latin Autor (Processed by BO) | AE73: Latin Autor (Processed by BO) | AF73: SACM | AG73: Latin Autor (Processed by BO) | AH73: Latin Autor (Processed by BO) | AI73: Latin Autor (Processed by BO) | AJ73: AMRA | AK73: AMRA | AL73: AMRA | AM73: AMRA | AN73: AMRA | AO73: AMRA | AP73: AMRA | AQ73: AMRA | AR73: AMRA | AS73: AMRA | AT73: AMRA | AU73: KOMCA | AV73: AMRA | AW73: AMRA | AX73: AMRA | AY73: AMRA
B74: SADIAC | C74: Kobalt Paid By | D74: AMRA | E74: AMRA | F74: AMRA | G74: AMRA | H74: AMRA | I74: AMRA | J74: AMRA | K74: AMRA | L74: AMRA | M74: AMRA | N74: AMRA | O74: AMRA | P74: AMRA | Q74: AMRA | R74: AMRA | S74: AMRA | T74: AMRA | U74: AMRA | V74: AMRA | W74: CMRRA | X74: MLC | Y74: SADAIC | Z74: No Membership | AA74: AMRA | AB74: Latin Autor | AC74: Latin Autor | AD74: Latin Autor | AE74: Latin Autor | AF74: SACM | AG74: No Membership | AH74: Latin Autor | AI74: Latin Autor | AJ74: AMRA | AK74: AMRA | AL74: AMRA | AM74: AMRA | AN74: AMRA | AO74: AMRA | AP74: AMRA | AQ74: AMRA | AR74: AMRA | AS74: AMRA | AT74: AMRA | AU74: EKKO | AV74: AMRA | AW74: AMRA | AX74: AMRA | AY74: AMRA
A75: SAYCO | B75: SAYCO | C75: Licensed By | D75: AMRA | E75: AMRA | F75: AMRA | G75: AMRA | H75: AMRA | I75: AMRA | J75: AMRA | K75: AMRA | L75: AMRA | M75: AMRA | N75: AMRA | O75: AMRA | P75: AMRA | Q75: AMRA | R75: AMRA | S75: AMRA | T75: AMRA | U75: AMRA | V75: AMRA | W75: CMRRA | X75: MLC | Y75: SADAIC | Z75: Latin Autor | AA75: AMRA | AB75: Latin Autor | AC75: Latin Autor | AD75: Latin Autor | AE75: Latin Autor | AF75: SACM | AG75: Latin Autor | AH75: Latin Autor | AI75: Latin Autor | AJ75: AMRA | AK75: AMRA | AL75: AMRA | AM75: AMRA | AN75: AMRA | AO75: AMRA | AP75: AMRA | AQ75: AMRA | AR75: AMRA | AS75: AMRA | AT75: AMRA | AU75: KOMCA | AV75: AMRA | AW75: AMRA | AX75: AMRA | AY75: AMRA
B76: SAYCO | C76: Licensor Pays | D76: AMRA | E76: AMRA | F76: AMRA | G76: AMRA | H76: AMRA | I76: AMRA | J76: AMRA | K76: AMRA | L76: AMRA | M76: AMRA | N76: AMRA | O76: AMRA | P76: AMRA | Q76: AMRA | R76: AMRA | S76: AMRA | T76: AMRA | U76: AMRA | V76: AMRA | W76: CMRRA | X76: MLC | Y76: SADAIC | Z76: Latin Autor (Processed by BO) | AA76: AMRA | AB76: Latin Autor (Processed by BO) | AC76: Latin Autor (Processed by BO) | AD76: Latin Autor (Processed by BO) | AE76: Latin Autor (Processed by BO) | AF76: SACM | AG76: Latin Autor (Processed by BO) | AH76: Latin Autor (Processed by BO) | AI76: Latin Autor (Processed by BO) | AJ76: AMRA | AK76: AMRA | AL76: AMRA | AM76: AMRA | AN76: AMRA | AO76: AMRA | AP76: AMRA | AQ76: AMRA | AR76: AMRA | AS76: AMRA | AT76: AMRA | AU76: KOMCA | AV76: AMRA | AW76: AMRA | AX76: AMRA | AY76: AMRA
B77: SAYCO | C77: Kobalt Paid By | D77: AMRA | E77: AMRA | F77: AMRA | G77: AMRA | H77: AMRA | I77: AMRA | J77: AMRA | K77: AMRA | L77: AMRA | M77: AMRA | N77: AMRA | O77: AMRA | P77: AMRA | Q77: AMRA | R77: AMRA | S77: AMRA | T77: AMRA | U77: AMRA | V77: AMRA | W77: CMRRA | X77: MLC | Y77: SADAIC | Z77: No Membership | AA77: AMRA | AB77: Latin Autor | AC77: Latin Autor | AD77: Latin Autor | AE77: Latin Autor | AF77: SACM | AG77: No Membership | AH77: Latin Autor | AI77: Latin Autor | AJ77: AMRA | AK77: AMRA | AL77: AMRA | AM77: AMRA | AN77: AMRA | AO77: AMRA | AP77: AMRA | AQ77: AMRA | AR77: AMRA | AS77: AMRA | AT77: AMRA | AU77: EKKO | AV77: AMRA | AW77: AMRA | AX77: AMRA | AY77: AMRA
A78: SCD | B78: SCD | C78: Licensed By | D78: AMRA | E78: AMRA | F78: AMRA | G78: AMRA | H78: AMRA | I78: AMRA | J78: AMRA | K78: AMRA | L78: AMRA | M78: AMRA | N78: AMRA | O78: AMRA | P78: AMRA | Q78: AMRA | R78: AMRA | S78: AMRA | T78: AMRA | U78: AMRA | V78: AMRA | W78: CMRRA | X78: MLC | Y78: SADAIC | Z78: Latin Autor | AA78: AMRA | AB78: Latin Autor | AC78: Latin Autor | AD78: Latin Autor | AE78: Latin Autor | AF78: SACM | AG78: Latin Autor | AH78: Latin Autor | AI78: Latin Autor | AJ78: AMRA | AK78: AMRA | AL78: AMRA | AM78: AMRA | AN78: AMRA | AO78: AMRA | AP78: AMRA | AQ78: AMRA | AR78: AMRA | AS78: AMRA | AT78: AMRA | AU78: KOMCA | AV78: AMRA | AW78: AMRA | AX78: AMRA | AY78: AMRA
B79: SCD | C79: Licensor Pays | D79: AMRA | E79: AMRA | F79: AMRA | G79: AMRA | H79: AMRA | I79: AMRA | J79: AMRA | K79: AMRA | L79: AMRA | M79: AMRA | N79: AMRA | O79: AMRA | P79: AMRA | Q79: AMRA | R79: AMRA | S79: AMRA | T79: AMRA | U79: AMRA | V79: AMRA | W79: CMRRA | X79: MLC | Y79: SADAIC | Z79: Latin Autor (Processed by BO) | AA79: AMRA | AB79: Latin Autor (Processed by BO) | AC79: Latin Autor (Processed by BO) | AD79: Latin Autor (Processed by BO) | AE79: Latin Autor (Processed by BO) | AF79: SACM | AG79: Latin Autor (Processed by BO) | AH79: Latin Autor (Processed by BO) | AI79: Latin Autor (Processed by BO) | AJ79: AMRA | AK79: AMRA | AL79: AMRA | AM79: AMRA | AN79: AMRA | AO79: AMRA | AP79: AMRA | AQ79: AMRA | AR79: AMRA | AS79: AMRA | AT79: AMRA | AU79: KOMCA | AV79: AMRA | AW79: AMRA | AX79: AMRA | AY79: AMRA
B80: SCD | C80: Kobalt Paid By | D80: AMRA | E80: AMRA | F80: AMRA | G80: AMRA | H80: AMRA | I80: AMRA | J80: AMRA | K80: AMRA | L80: AMRA | M80: AMRA | N80: AMRA | O80: AMRA | P80: AMRA | Q80: AMRA | R80: AMRA | S80: AMRA | T80: AMRA | U80: AMRA | V80: AMRA | W80: CMRRA | X80: MLC | Y80: SADAIC | Z80: No Membership | AA80: AMRA | AB80: Latin Autor | AC80: Latin Autor | AD80: Latin Autor | AE80: Latin Autor | AF80: SACM | AG80: No Membership | AH80: Latin Autor | AI80: Latin Autor | AJ80: AMRA | AK80: AMRA | AL80: AMRA | AM80: AMRA | AN80: AMRA | AO80: AMRA | AP80: AMRA | AQ80: AMRA | AR80: AMRA | AS80: AMRA | AT80: AMRA | AU80: EKKO | AV80: AMRA | AW80: AMRA | AX80: AMRA | AY80: AMRA
A81: Asian Rep
A82: CASH | B82: CASH | C82: Licensed By | D82: AMRA | E82: AMRA | F82: AMRA | G82: AMRA | H82: AMRA | I82: AMRA | J82: AMRA | K82: AMRA | L82: AMRA | M82: AMRA | N82: AMRA | O82: AMRA | P82: AMRA | Q82: AMRA | R82: AMRA | S82: AMRA | T82: AMRA | U82: AMRA | V82: AMRA | W82: CMRRA | X82: MLC | Y82: SADAIC | Z82: Latin Autor | AA82: AMRA | AB82: Latin Autor | AC82: Latin Autor | AD82: Latin Autor | AE82: Latin Autor | AF82: SACM | AG82: Latin Autor | AH82: Latin Autor | AI82: Latin Autor | AJ82: AMRA | AK82: AMRA | AL82: AMRA | AM82: AMRA | AN82: AMRA | AO82: AMRA | AP82: AMRA | AQ82: AMRA | AR82: AMRA | AS82: AMRA | AT82: AMRA | AU82: KOMCA | AV82: AMRA | AW82: AMRA | AX82: AMRA | AY82: QUERY SOURCE/ TERR OWNER
B83: CASH | C83: Licensor Pays | D83: AMRA | E83: AMRA | F83: AMRA | G83: AMRA | H83: AMRA | I83: AMRA | J83: AMRA | K83: AMRA | L83: AMRA | M83: AMRA | N83: AMRA | O83: AMRA | P83: AMRA | Q83: AMRA | R83: AMRA | S83: AMRA | T83: AMRA | U83: AMRA | V83: AMRA | W83: CMRRA | X83: MLC | Y83: SADAIC | Z83: Latin Autor (Processed by BO) | AA83: AMRA | AB83: Latin Autor (Processed by BO) | AC83: Latin Autor (Processed by BO) | AD83: Latin Autor (Processed by BO) | AE83: Latin Autor (Processed by BO) | AF83: SACM | AG83: Latin Autor (Processed by BO) | AH83: Latin Autor (Processed by BO) | AI83: Latin Autor (Processed by BO) | AJ83: AMRA | AK83: AMRA | AL83: AMRA | AM83: AMRA | AN83: AMRA | AO83: AMRA | AP83: AMRA | AQ83: AMRA | AR83: AMRA | AS83: AMRA | AT83: AMRA | AU83: KOMCA | AV83: AMRA | AW83: AMRA | AX83: AMRA | AY83: QUERY SOURCE/ TERR OWNER
B84: CASH | C84: Kobalt Paid By | D84: AMRA | E84: AMRA | F84: AMRA | G84: AMRA | H84: AMRA | I84: AMRA | J84: AMRA | K84: AMRA | L84: AMRA | M84: AMRA | N84: AMRA | O84: AMRA | P84: AMRA | Q84: AMRA | R84: AMRA | S84: AMRA | T84: AMRA | U84: AMRA | V84: AMRA | W84: CMRRA | X84: MLC | Y84: SADAIC | Z84: No Membership | AA84: AMRA | AB84: Latin Autor | AC84: Latin Autor | AD84: Latin Autor | AE84: Latin Autor | AF84: SACM | AG84: No Membership | AH84: Latin Autor | AI84: Latin Autor | AJ84: AMRA | AK84: AMRA | AL84: AMRA | AM84: AMRA | AN84: AMRA | AO84: AMRA | AP84: AMRA | AQ84: AMRA | AR84: AMRA | AS84: AMRA | AT84: AMRA | AU84: EKKO | AV84: AMRA | AW84: AMRA | AX84: AMRA | AY84: QUERY SOURCE/ TERR OWNER
A85: JASRAC | B85: JASRAC | C85: Licensed By | D85: AMRA | E85: AMRA | F85: AMRA | G85: AMRA | H85: AMRA | I85: AMRA | J85: AMRA | K85: AMRA | L85: AMRA | M85: AMRA | N85: AMRA | O85: AMRA | P85: AMRA | Q85: AMRA | R85: AMRA | S85: AMRA | T85: AMRA | U85: AMRA | V85: AMRA | W85: CMRRA | X85: MLC | Y85: SADAIC | Z85: Latin Autor | AA85: AMRA | AB85: Latin Autor | AC85: Latin Autor | AD85: Latin Autor | AE85: Latin Autor | AF85: SACM | AG85: Latin Autor | AH85: Latin Autor | AI85: Latin Autor | AJ85: AMRA | AK85: AMRA | AL85: AMRA | AM85: AMRA | AN85: AMRA | AO85: AMRA | AP85: AMRA | AQ85: AMRA | AR85: AMRA | AS85: AMRA | AT85: AMRA | AU85: KOMCA | AV85: AMRA | AW85: AMRA | AX85: AMRA | AY85: QUERY SOURCE/ TERR OWNER
B86: JASRAC | C86: Licensor Pays | D86: AMRA | E86: AMRA | F86: AMRA | G86: AMRA | H86: AMRA | I86: AMRA | J86: AMRA | K86: AMRA | L86: AMRA | M86: AMRA | N86: AMRA | O86: AMRA | P86: AMRA | Q86: AMRA | R86: AMRA | S86: AMRA | T86: AMRA | U86: AMRA | V86: AMRA | W86: CMRRA | X86: MLC | Y86: SADAIC | Z86: Latin Autor (Processed by BO) | AA86: AMRA | AB86: Latin Autor (Processed by BO) | AC86: Latin Autor (Processed by BO) | AD86: Latin Autor (Processed by BO) | AE86: Latin Autor (Processed by BO) | AF86: SACM | AG86: Latin Autor (Processed by BO) | AH86: Latin Autor (Processed by BO) | AI86: Latin Autor (Processed by BO) | AJ86: AMRA | AK86: AMRA | AL86: AMRA | AM86: AMRA | AN86: AMRA | AO86: AMRA | AP86: AMRA | AQ86: AMRA | AR86: AMRA | AS86: AMRA | AT86: AMRA | AU86: KOMCA | AV86: AMRA | AW86: AMRA | AX86: AMRA | AY86: QUERY SOURCE/ TERR OWNER
B87: JASRAC | C87: Kobalt Paid By | D87: AMRA | E87: AMRA | F87: AMRA | G87: AMRA | H87: AMRA | I87: AMRA | J87: AMRA | K87: AMRA | L87: AMRA | M87: AMRA | N87: AMRA | O87: AMRA | P87: AMRA | Q87: AMRA | R87: AMRA | S87: AMRA | T87: AMRA | U87: AMRA | V87: AMRA | W87: CMRRA | X87: MLC | Y87: SADAIC | Z87: No Membership | AA87: AMRA | AB87: Latin Autor | AC87: Latin Autor | AD87: Latin Autor | AE87: Latin Autor | AF87: SACM | AG87: No Membership | AH87: Latin Autor | AI87: Latin Autor | AJ87: AMRA | AK87: AMRA | AL87: AMRA | AM87: AMRA | AN87: AMRA | AO87: AMRA | AP87: AMRA | AQ87: AMRA | AR87: AMRA | AS87: AMRA | AT87: AMRA | AU87: EKKO | AV87: AMRA | AW87: AMRA | AX87: AMRA | AY87: QUERY SOURCE/ TERR OWNER
A88: KOMCA | B88: KOMCA | C88: Licensed By | D88: AMRA | E88: AMRA | F88: AMRA | G88: AMRA | H88: AMRA | I88: AMRA | J88: AMRA | K88: AMRA | L88: AMRA | M88: AMRA | N88: AMRA | O88: AMRA | P88: AMRA | Q88: AMRA | R88: AMRA | S88: AMRA | T88: AMRA | U88: AMRA | V88: AMRA | W88: CMRRA | X88: MLC | Y88: SADAIC | Z88: Latin Autor | AA88: AMRA | AB88: Latin Autor | AC88: Latin Autor | AD88: Latin Autor | AE88: Latin Autor | AF88: SACM | AG88: Latin Autor | AH88: Latin Autor | AI88: Latin Autor | AJ88: AMRA | AK88: AMRA | AL88: AMRA | AM88: AMRA | AN88: AMRA | AO88: AMRA | AP88: AMRA | AQ88: AMRA | AR88: AMRA | AS88: AMRA | AT88: AMRA | AU88: KOMCA | AV88: AMRA | AW88: AMRA | AX88: AMRA | AY88: QUERY SOURCE/ TERR OWNER
B89: KOMCA | C89: Licensor Pays | D89: AMRA | E89: AMRA | F89: AMRA | G89: AMRA | H89: AMRA | I89: AMRA | J89: AMRA | K89: AMRA | L89: AMRA | M89: AMRA | N89: AMRA | O89: AMRA | P89: AMRA | Q89: AMRA | R89: AMRA | S89: AMRA | T89: AMRA | U89: AMRA | V89: AMRA | W89: CMRRA | X89: MLC | Y89: SADAIC | Z89: Latin Autor (Processed by BO) | AA89: AMRA | AB89: Latin Autor (Processed by BO) | AC89: Latin Autor (Processed by BO) | AD89: Latin Autor (Processed by BO) | AE89: Latin Autor (Processed by BO) | AF89: SACM | AG89: Latin Autor (Processed by BO) | AH89: Latin Autor (Processed by BO) | AI89: Latin Autor (Processed by BO) | AJ89: AMRA | AK89: AMRA | AL89: AMRA | AM89: AMRA | AN89: AMRA | AO89: AMRA | AP89: AMRA | AQ89: AMRA | AR89: AMRA | AS89: AMRA | AT89: AMRA | AU89: KOMCA | AV89: AMRA | AW89: AMRA | AX89: AMRA | AY89: QUERY SOURCE/ TERR OWNER
B90: KOMCA | C90: Kobalt Paid By | D90: AMRA | E90: AMRA | F90: AMRA | G90: AMRA | H90: AMRA | I90: AMRA | J90: AMRA | K90: AMRA | L90: AMRA | M90: AMRA | N90: AMRA | O90: AMRA | P90: AMRA | Q90: AMRA | R90: AMRA | S90: AMRA | T90: AMRA | U90: AMRA | V90: AMRA | W90: CMRRA | X90: MLC | Y90: SADAIC | Z90: No Membership | AA90: AMRA | AB90: Latin Autor | AC90: Latin Autor | AD90: Latin Autor | AE90: Latin Autor | AF90: SACM | AG90: No Membership | AH90: Latin Autor | AI90: Latin Autor | AJ90: AMRA | AK90: AMRA | AL90: AMRA | AM90: AMRA | AN90: AMRA | AO90: AMRA | AP90: AMRA | AQ90: AMRA | AR90: AMRA | AS90: AMRA | AT90: AMRA | AU90: EKKO | AV90: AMRA | AW90: AMRA | AX90: AMRA | AY90: QUERY SOURCE/ TERR OWNER
A91: COMPASS | B91: COMPASS | C91: Licensed By | D91: AMRA | E91: AMRA | F91: AMRA | G91: AMRA | H91: AMRA | I91: AMRA | J91: AMRA | K91: AMRA | L91: AMRA | M91: AMRA | N91: AMRA | O91: AMRA | P91: AMRA | Q91: AMRA | R91: AMRA | S91: AMRA | T91: AMRA | U91: AMRA | V91: AMRA | W91: CMRRA | X91: MLC | Y91: SADAIC | Z91: Latin Autor | AA91: AMRA | AB91: Latin Autor | AC91: Latin Autor | AD91: Latin Autor | AE91: Latin Autor | AF91: SACM | AG91: Latin Autor | AH91: Latin Autor | AI91: Latin Autor | AJ91: AMRA | AK91: AMRA | AL91: AMRA | AM91: AMRA | AN91: AMRA | AO91: AMRA | AP91: AMRA | AQ91: AMRA | AR91: AMRA | AS91: AMRA | AT91: AMRA | AU91: KOMCA | AV91: AMRA | AW91: AMRA | AX91: AMRA | AY91: QUERY SOURCE/ TERR OWNER
B92: COMPASS | C92: Licensor Pays | D92: AMRA | E92: AMRA | F92: AMRA | G92: AMRA | H92: AMRA | I92: AMRA | J92: AMRA | K92: AMRA | L92: AMRA | M92: AMRA | N92: AMRA | O92: AMRA | P92: AMRA | Q92: AMRA | R92: AMRA | S92: AMRA | T92: AMRA | U92: AMRA | V92: AMRA | W92: CMRRA | X92: MLC | Y92: SADAIC | Z92: Latin Autor (Processed by BO) | AA92: AMRA | AB92: Latin Autor (Processed by BO) | AC92: Latin Autor (Processed by BO) | AD92: Latin Autor (Processed by BO) | AE92: Latin Autor (Processed by BO) | AF92: SACM | AG92: Latin Autor (Processed by BO) | AH92: Latin Autor (Processed by BO) | AI92: Latin Autor (Processed by BO) | AJ92: AMRA | AK92: AMRA | AL92: AMRA | AM92: AMRA | AN92: AMRA | AO92: AMRA | AP92: AMRA | AQ92: AMRA | AR92: AMRA | AS92: AMRA | AT92: AMRA | AU92: KOMCA | AV92: AMRA | AW92: AMRA | AX92: AMRA | AY92: QUERY SOURCE/ TERR OWNER
B93: COMPASS | C93: Kobalt Paid By | D93: AMRA | E93: AMRA | F93: AMRA | G93: AMRA | H93: AMRA | I93: AMRA | J93: AMRA | K93: AMRA | L93: AMRA | M93: AMRA | N93: AMRA | O93: AMRA | P93: AMRA | Q93: AMRA | R93: AMRA | S93: AMRA | T93: AMRA | U93: AMRA | V93: AMRA | W93: CMRRA | X93: MLC | Y93: SADAIC | Z93: No Membership | AA93: AMRA | AB93: Latin Autor | AC93: Latin Autor | AD93: Latin Autor | AE93: Latin Autor | AF93: SACM | AG93: No Membership | AH93: Latin Autor | AI93: Latin Autor | AJ93: AMRA | AK93: AMRA | AL93: AMRA | AM93: AMRA | AN93: AMRA | AO93: AMRA | AP93: AMRA | AQ93: AMRA | AR93: AMRA | AS93: AMRA | AT93: AMRA | AU93: EKKO | AV93: AMRA | AW93: AMRA | AX93: AMRA | AY93: QUERY SOURCE/ TERR OWNER
A95: Non- Society | B95: Non-Society | C95: Licensed By | D95: AMRA | E95: AMRA | F95: AMRA | G95: AMRA | H95: AMRA | I95: AMRA | J95: AMRA | K95: AMRA | L95: AMRA | M95: AMRA | N95: AMRA | O95: AMRA | P95: AMRA | Q95: AMRA | R95: AMRA | S95: AMRA | T95: AMRA | U95: AMRA | V95: AMRA | W95: CMRRA | X95: MLC | Y95: SADAIC | Z95: Latin Autor | AA95: AMRA | AB95: Latin Autor | AC95: Latin Autor | AD95: Latin Autor | AE95: Latin Autor | AF95: SACM | AG95: Latin Autor | AH95: Latin Autor | AI95: Latin Autor | AJ95: APRA-AMCOS | AK95: APRA-AMCOS | AL95: AMRA | AM95: AMRA | AN95: AMRA | AO95: AMRA | AP95: AMRA | AQ95: AMRA | AR95: AMRA | AS95: AMRA | AT95: AMRA | AU95: KOMCA | AV95: AMRA | AW95: AMRA | AX95: CAPASSO | AY95: AMRA
B96: Non-Society | C96: Licensor Pays | D96: AMRA | E96: AMRA | F96: AMRA | G96: AMRA | H96: AMRA | I96: AMRA | J96: AMRA | K96: AMRA | L96: AMRA | M96: AMRA | N96: AMRA | O96: AMRA | P96: AMRA | Q96: AMRA | R96: AMRA | S96: AMRA | T96: AMRA | U96: AMRA | V96: AMRA | W96: CMRRA | X96: MLC | Y96: SADAIC | Z96: Latin Autor | AA96: AMRA | AB96: Latin Autor | AC96: Latin Autor | AD96: Latin Autor | AE96: Latin Autor | AF96: SACM | AG96: Latin Autor | AH96: Latin Autor | AI96: Latin Autor | AJ96: APRA-AMCOS | AK96: APRA-AMCOS | AL96: AMRA | AM96: AMRA | AN96: AMRA | AO96: AMRA | AP96: AMRA | AQ96: AMRA | AR96: AMRA | AS96: AMRA | AT96: AMRA | AU96: KOMCA | AV96: AMRA | AW96: AMRA | AX96: CAPASSO | AY96: AMRA
B97: Non-Society | C97: Kobalt Paid By | D97: AMRA | E97: AMRA | F97: AMRA | G97: AMRA | H97: AMRA | I97: AMRA | J97: AMRA | K97: AMRA | L97: AMRA | M97: AMRA | N97: AMRA | O97: AMRA | P97: AMRA | Q97: AMRA | R97: AMRA | S97: AMRA | T97: AMRA | U97: AMRA | V97: AMRA | W97: CMRRA | X97: MLC | Y97: SADAIC | Z97: AMRA | AA97: AMRA | AB97: AMRA | AC97: AMRA | AD97: AMRA | AE97: AMRA | AF97: SACM | AG97: AMRA | AH97: AMRA | AI97: AMRA | AJ97: APRA-AMCOS | AK97: APRA-AMCOS | AL97: AMRA | AM97: AMRA | AN97: AMRA | AO97: AMRA | AP97: AMRA | AQ97: AMRA | AR97: AMRA | AS97: AMRA | AT97: AMRA | AU97: EKKO | AV97: AMRA | AW97: AMRA | AX97: CAPASSO | AY97: AMRA

Sheet MECH - Paid By
A1: SOCIETY | C1: Austria | D1: Belgium | E1: France | F1: Germany | G1: Italy | H1: Netherlands | I1: Nordics Finland / Norway / Iceland, etc) | J1: Portugal | K1: Spain | L1: Sweden | M1: Switzerland | N1: United Kingdom | O1: Croatia | P1: Greece | Q1: Poland | R1: Russia | S1: Israel | T1: UAE | U1: Turkey | V1: Canada | W1: United States | X1: Argentina | Y1: Bolivia | Z1: Brazil | AA1: Chile | AB1: Colombia | AC1: Costa Rica | AD1: Ecuador | AE1: Mexico | AF1: Paraguay | AG1: Peru | AH1: Uruguay | AI1: Australia | AJ1: New Zealand | AK1: China | AL1: HongKong | AM1: India | AN1: Japan | AO1: Malaysia | AP1: Philippines | AQ1: Vietnam | AR1: Thailand | AS1: Singapore | AT1: South Korea | AU1: Indonesia | AV1: Taiwan | AW1: South Africa | AX1: North Africa
A2: AKM-AUME | B2: Kobalt Paid By | C2: AUME | D2: SABAM | E2: SACEM | F2: GEMA | G2: SIAE | H2: BUMA | I2: STIM | J2: SGAE | K2: SGAE | L2: STIM | M2: SUISA | N2: MCPS-PRS | O2: IDM | P2: D-Version | Q2: Schubert | R2: Blue Sun | S2: Dalia | T2: Pop Arabia | U2: Zeplin | V2: CMRRA | W2: MLC | X2: SADAIC | Y2: No Membership | Z2: ABRAMUS | AA2: Latin Autor | AB2: Latin Autor | AC2: Latin Autor | AD2: Latin Autor | AE2: SACM | AF2: No Membership | AG2: Latin Autor | AH2: Latin Autor | AI2: APRA-AMCOS | AJ2: APRA-AMCOS | AK2: CASH | AL2: CASH | AM2: Turnkey | AN2: SMPJ | AO2: Indie Works | AP2: COMPASS | AQ2: COMPASS | AR2: COMPASS | AS2: COMPASS | AT2: EKKO | AU2: PT Nadaku | AV2: One Asia | AW2: CAPASSO | AX2: SACEM
A3: BUMA | B3: Kobalt Paid By | C3: AKM | D3: SABAM | E3: SACEM | F3: GEMA | G3: SIAE | H3: BUMA | I3: Nordic Sources | J3: SPA | K3: SGAE | L3: STIM | M3: SUISA | N3: MCPS-PRS | O3: IDM | P3: D-Version | Q3: Schubert | R3: Blue Sun | S3: Dalia | T3: Pop Arabia | U3: Zeplin | V3: CMRRA | W3: MLC | X3: SADAIC | Y3: No Membership | Z3: ABRAMUS | AA3: Latin Autor | AB3: Latin Autor | AC3: Latin Autor | AD3: Latin Autor | AE3: SACM | AF3: No Membership | AG3: Latin Autor | AH3: Latin Autor | AI3: APRA-AMCOS | AJ3: APRA-AMCOS | AK3: QUERY SOURCE/ TERR OWNER | AL3: CASH | AM3: Turnkey | AN3: SMPJ | AO3: Indie Works | AP3: STIM | AQ3: STIM | AR3: STIM | AS3: STIM | AT3: EKKO | AU3: PT Nadaku | AV3: One Asia | AW3: CAPASSO | AX3: SACEM
A4: GEMA | B4: Kobalt Paid By | C4: AUME | D4: SABAM | E4: SACEM | F4: GEMA | G4: SIAE | H4: BUMA | I4: Nordic Sources | J4: SPA | K4: GEMA | L4: STIM | M4: SUISA | N4: MCPS-PRS | O4: IDM | P4: D-Version | Q4: Schubert | R4: Blue Sun | S4: Dalia | T4: Pop Arabia | U4: Zeplin | V4: CMRRA | W4: MLC | X4: SADAIC | Y4: No Membership | Z4: ABRAMUS | AA4: Latin Autor | AB4: Latin Autor | AC4: Latin Autor | AD4: Latin Autor | AE4: SACM | AF4: No Membership | AG4: Latin Autor | AH4: Latin Autor | AI4: APRA-AMCOS | AJ4: APRA-AMCOS | AK4: CASH | AL4: CASH | AM4: Turnkey | AN4: SMPJ | AO4: Indie Works | AP4: COMPASS | AQ4: COMPASS | AR4: COMPASS | AS4: COMPASS | AT4: EKKO | AU4: PT Nadaku | AV4: One Asia | AW4: CAPASSO | AX4: GEMA
A5: SABAM | B5: Kobalt Paid By | C5: AUME | D5: SABAM | E5: SACEM | F5: GEMA | G5: SIAE | H5: BUMA | I5: Nordic Sources | J5: SPA | K5: SGAE | L5: STIM | M5: SUISA | N5: MCPS-PRS | O5: IDM | P5: D-Version | Q5: Schubert | R5: Blue Sun | S5: Dalia | T5: Pop Arabia | U5: Zeplin | V5: CMRRA | W5: MLC | X5: SADAIC | Y5: No Membership | Z5: ABRAMUS | AA5: Latin Autor | AB5: Latin Autor | AC5: Latin Autor | AD5: Latin Autor | AE5: SACM | AF5: No Membership | AG5: Latin Autor | AH5: Latin Autor | AI5: APRA-AMCOS | AJ5: APRA-AMCOS | AK5: QUERY SOURCE/ TERR OWNER | AL5: CASH | AM5: QUERY SOURCE/ TERR OWNER | AN5: SMPJ | AO5: Indie Works | AP5: QUERY SOURCE/ TERR OWNER | AQ5: QUERY SOURCE/ TERR OWNER | AR5: QUERY SOURCE/ TERR OWNER | AS5: QUERY SOURCE/ TERR OWNER | AT5: EKKO | AU5: QUERY SOURCE/ TERR OWNER | AV5: One Asia | AW5: CAPASSO | AX5: SACEM
A6: SACEM | B6: Kobalt Paid By | C6: SACEM | D6: SACEM | E6: SACEM | F6: SACEM | G6: SACEM | H6: SACEM | I6: SACEM | J6: SACEM | K6: SACEM | L6: SACEM | M6: SACEM | N6: SACEM | O6: SACEM | P6: SACEM | Q6: SACEM | R6: Blue Sun | S6: Dalia | T6: Pop Arabia | U6: Zeplin | V6: CMRRA | W6: MLC | X6: SADAIC | Y6: No Membership | Z6: ABRAMUS | AA6: Latin Autor | AB6: Latin Autor | AC6: Latin Autor | AD6: Latin Autor | AE6: SACM | AF6: No Membership | AG6: Latin Autor | AH6: Latin Autor | AI6: APRA-AMCOS | AJ6: APRA-AMCOS | AK6: QUERY SOURCE/ TERR OWNER | AL6: QUERY SOURCE/ TERR OWNER | AM6: QUERY SOURCE/ TERR OWNER | AN6: QUERY SOURCE/ TERR OWNER | AO6: QUERY SOURCE/ TERR OWNER | AP6: QUERY SOURCE/ TERR OWNER | AQ6: QUERY SOURCE/ TERR OWNER | AR6: QUERY SOURCE/ TERR OWNER | AS6: QUERY SOURCE/ TERR OWNER | AT6: EKKO | AU6: QUERY SOURCE/ TERR OWNER | AV6: QUERY SOURCE/ TERR OWNER | AW6: CAPASSO | AX6: SACEM
A7: SGAE | B7: Kobalt Paid By | C7: SGAE | D7: SABAM | E7: SGAE | F7: SGAE | G7: SGAE | H7: SGAE | I7: SGAE | J7: SGAE | K7: SGAE | L7: STIM | M7: SUISA | N7: MCPS-PRS | O7: IDM | P7: D-Version | Q7: Schubert | R7: Blue Sun | S7: Dalia | T7: Pop Arabia | U7: Zeplin | V7: CMRRA | W7: MLC | X7: SADAIC | Y7: No Membership | Z7: ABRAMUS | AA7: Latin Autor | AB7: Latin Autor | AC7: Latin Autor | AD7: Latin Autor | AE7: SACM | AF7: No Membership | AG7: Latin Autor | AH7: Latin Autor | AI7: APRA-AMCOS | AJ7: APRA-AMCOS | AK7: QUERY SOURCE/ TERR OWNER | AL7: QUERY SOURCE/ TERR OWNER | AM7: QUERY SOURCE/ TERR OWNER | AN7: QUERY SOURCE/ TERR OWNER | AO7: QUERY SOURCE/ TERR OWNER | AP7: QUERY SOURCE/ TERR OWNER | AQ7: QUERY SOURCE/ TERR OWNER | AR7: QUERY SOURCE/ TERR OWNER | AS7: QUERY SOURCE/ TERR OWNER | AT7: EKKO | AU7: QUERY SOURCE/ TERR OWNER | AV7: QUERY SOURCE/ TERR OWNER | AW7: CAPASSO | AX7: QUERY SOURCE/ TERR OWNER
A8: SIAE | B8: Kobalt Paid By | C8: NOT LICENSED | D8: NOT LICENSED | E8: NOT LICENSED | F8: NOT LICENSED | G8: NOT LICENSED | H8: NOT LICENSED | I8: NOT LICENSED | J8: NOT LICENSED | K8: NOT LICENSED | L8: NOT LICENSED | M8: NOT LICENSED | N8: NOT LICENSED | O8: IDM | P8: D-Version | Q8: Schubert | R8: Blue Sun | S8: Dalia | T8: Pop Arabia | U8: Zeplin | V8: CMRRA | W8: MLC | X8: SADAIC | Y8: No Membership | Z8: ABRAMUS | AA8: Latin Autor | AB8: Latin Autor | AC8: Latin Autor | AD8: Latin Autor | AE8: SACM | AF8: No Membership | AG8: Latin Autor | AH8: Latin Autor | AI8: APRA-AMCOS | AJ8: APRA-AMCOS | AK8: QUERY SOURCE/ TERR OWNER | AL8: QUERY SOURCE/ TERR OWNER | AM8: QUERY SOURCE/ TERR OWNER | AN8: QUERY SOURCE/ TERR OWNER | AO8: QUERY SOURCE/ TERR OWNER | AP8: QUERY SOURCE/ TERR OWNER | AQ8: QUERY SOURCE/ TERR OWNER | AR8: QUERY SOURCE/ TERR OWNER | AS8: QUERY SOURCE/ TERR OWNER | AT8: EKKO | AU8: QUERY SOURCE/ TERR OWNER | AV8: QUERY SOURCE/ TERR OWNER | AW8: CAPASSO | AX8: QUERY SOURCE/ TERR OWNER
A9: SPA | B9: Kobalt Paid By | C9: SPA | D9: SABAM | E9: SACEM | F9: GEMA | G9: SPA | H9: SPA | I9: SPA | J9: SPA | K9: SGAE | L9: SPA | M9: SUISA | N9: MCPS-PRS | O9: IDM | P9: D-Version | Q9: Schubert | R9: Blue Sun | S9: Dalia | T9: Pop Arabia | U9: Zeplin | V9: CMRRA | W9: MLC | X9: SADAIC | Y9: No Membership | Z9: ABRAMUS | AA9: Latin Autor | AB9: Latin Autor | AC9: Latin Autor | AD9: Latin Autor | AE9: SACM | AF9: No Membership | AG9: Latin Autor | AH9: Latin Autor | AI9: APRA-AMCOS | AJ9: APRA-AMCOS | AK9: QUERY SOURCE/ TERR OWNER | AL9: QUERY SOURCE/ TERR OWNER | AM9: QUERY SOURCE/ TERR OWNER | AN9: QUERY SOURCE/ TERR OWNER | AO9: QUERY SOURCE/ TERR OWNER | AP9: QUERY SOURCE/ TERR OWNER | AQ9: QUERY SOURCE/ TERR OWNER | AR9: QUERY SOURCE/ TERR OWNER | AS9: QUERY SOURCE/ TERR OWNER | AT9: EKKO | AU9: QUERY SOURCE/ TERR OWNER | AV9: QUERY SOURCE/ TERR OWNER | AW9: CAPASSO | AX9: QUERY SOURCE/ TERR OWNER
A10: STIM-NCB | B10: Kobalt Paid By | C10: STIM | D10: STIM | E10: STIM | F10: STIM | G10: STIM | H10: STIM | I10: STIM | J10: STIM | K10: STIM | L10: STIM | M10: STIM | N10: STIM | O10: IDM | P10: D-Version | Q10: Schubert | R10: Blue Sun | S10: Dalia | T10: Pop Arabia | U10: Zeplin | V10: CMRRA | W10: MLC | X10: SADAIC | Y10: No Membership | Z10: ABRAMUS | AA10: Latin Autor | AB10: Latin Autor | AC10: Latin Autor | AD10: Latin Autor | AE10: SACM | AF10: No Membership | AG10: Latin Autor | AH10: Latin Autor | AI10: APRA-AMCOS | AJ10: APRA-AMCOS | AK10: STIM | AL10: STIM | AM10: Turnkey | AN10: SMPJ | AO10: Indie Works | AP10: STIM | AQ10: STIM | AR10: STIM | AS10: STIM | AT10: EKKO | AU10: PT Nadaku | AV10: One Asia | AW10: CAPASSO | AX10: STIM
A11: SUISA | B11: Kobalt Paid By | C11: SUISA | D11: SABAM | E11: SUISA | F11: GEMA | G11: SIAE | H11: BUMA-STEMRA | I11: STIM | J11: SPA | K11: SGAE | L11: STIM | M11: SUISA | N11: MCPS-PRS | O11: IDM | P11: D-Version | Q11: Schubert | R11: Blue Sun | S11: Dalia | T11: Pop Arabia | U11: Zeplin | V11: CMRRA | W11: MLC | X11: SADAIC | Y11: No Membership | Z11: ABRAMUS | AA11: Latin Autor | AB11: Latin Autor | AC11: Latin Autor | AD11: Latin Autor | AE11: SACM | AF11: No Membership | AG11: Latin Autor | AH11: Latin Autor | AI11: APRA-AMCOS | AJ11: APRA-AMCOS | AK11: QUERY SOURCE/ TERR OWNER | AL11: CASH | AM11: QUERY SOURCE/ TERR OWNER | AN11: QUERY SOURCE/ TERR OWNER | AO11: QUERY SOURCE/ TERR OWNER | AP11: QUERY SOURCE/ TERR OWNER | AQ11: QUERY SOURCE/ TERR OWNER | AR11: QUERY SOURCE/ TERR OWNER | AS11: QUERY SOURCE/ TERR OWNER | AT11: QUERY SOURCE/ TERR OWNER | AU11: QUERY SOURCE/ TERR OWNER | AV11: QUERY SOURCE/ TERR OWNER | AW11: CAPASSO | AX11: QUERY SOURCE/ TERR OWNER
A13: AMRA | B13: Kobalt Paid By | C13: AMRA | D13: AMRA | E13: AMRA | F13: AMRA | G13: AMRA | H13: AMRA | I13: AMRA | J13: AMRA | K13: AMRA | L13: AMRA | M13: AMRA | N13: AMRA | O13: AMRA | P13: AMRA | Q13: AMRA | R13: AMRA | S13: AMRA | T13: AMRA | U13: AMRA | V13: AMRA | W13: MLC | X13: SADAIC | Y13: AMRA | Z13: AMRA | AA13: AMRA | AB13: AMRA | AC13: AMRA | AD13: AMRA | AE13: SACM | AF13: AMRA | AG13: AMRA | AH13: AMRA | AI13: AMRA | AJ13: AMRA | AK13: AMRA | AL13: AMRA | AM13: AMRA | AN13: AMRA | AO13: AMRA | AP13: AMRA | AQ13: AMRA | AR13: AMRA | AS13: AMRA | AT13: EKKO | AU13: AMRA | AV13: AMRA | AW13: AMRA | AX13: AMRA
A14: APRA-AMCOS | B14: Kobalt Paid By | C14: AMRA | D14: AMRA | E14: AMRA | F14: AMRA | G14: AMRA | H14: AMRA | I14: AMRA | J14: AMRA | K14: AMRA | L14: AMRA | M14: AMRA | N14: AMRA | O14: AMRA | P14: AMRA | Q14: AMRA | R14: AMRA | S14: AMRA | T14: AMRA | U14: AMRA | V14: AMRA | W14: MLC | X14: SADAIC | Y14: AMRA | Z14: AMRA | AA14: AMRA | AB14: AMRA | AC14: AMRA | AD14: AMRA | AE14: SACM | AF14: AMRA | AG14: AMRA | AH14: AMRA | AI14: AMRA | AJ14: AMRA | AK14: AMRA | AL14: AMRA | AM14: AMRA | AN14: AMRA | AO14: AMRA | AP14: AMRA | AQ14: AMRA | AR14: AMRA | AS14: AMRA | AT14: EKKO | AU14: AMRA | AV14: AMRA | AW14: AMRA | AX14: AMRA
... A35: Non-Society | B35: Kobalt Paid By | C35: AMRA | D35: AMRA | E35: AMRA | F35: AMRA | G35: AMRA | H35: AMRA | I35: AMRA | J35: AMRA | K35: AMRA | L35: AMRA | M35: AMRA | N35: AMRA | O35: AMRA | P35: AMRA | Q35: AMRA | R35: AMRA | S35: AMRA | T35: AMRA | U35: AMRA | V35: CMRRA | W35: MLC | X35: SADAIC | Y35: AMRA | Z35: AMRA | AA35: AMRA | AB35: AMRA | AC35: AMRA | AD35: AMRA | AE35: SACM | AF35: AMRA | AG35: AMRA | AH35: AMRA | AI35: APRA-AMCOS | AJ35: APRA-AMCOS | AK35: AMRA | AL35: AMRA | AM35: AMRA | AN35: AMRA | AO35: AMRA | AP35: AMRA | AQ35: AMRA | AR35: AMRA | AS35: AMRA | AT35: EKKO | AU35: AMRA | AV35: AMRA | AW35: CAPASSO | AX35: AMRA

Sheet MECH - Licensor Pays
A1: SOCIETY | C1: Austria | D1: Belgium | E1: France | F1: Germany | G1: Italy | H1: Netherlands | I1: Nordics Finland / Norway / Iceland, etc) | J1: Portugal | K1: Spain | L1: Sweden | M1: Switzerland | N1: United Kingdom | O1: Croatia | P1: Greece | Q1: Poland | R1: Russia | S1: Israel | T1: UAE | U1: Turkey | V1: Canada | W1: United States | X1: Argentina | Y1: Bolivia | Z1: Brazil | AA1: Chile | AB1: Colombia | AC1: Costa Rica | AD1: Ecuador | AE1: Mexico | AF1: Paraguay | AG1: Peru | AH1: Uruguay | AI1: Australia | AJ1: New Zealand | AK1: China | AL1: HongKong | AM1: India | AN1: Japan | AO1: Malaysia | AP1: Philippines | AQ1: Vietnam | AR1: Thailand | AS1: Singapore | AT1: South Korea | AU1: Indonesia | AV1: Taiwan | AW1: South Africa | AX1: North Africa
A2: AKM-AUME | B2: Licensor Pays | C2: AUME | D2: AUME | E2: AUME | F2: AUME | G2: AUME | H2: AUME | I2: AUME | J2: AUME | K2: AUME | L2: AUME | M2: AUME | N2: AUME | O2: AUME | P2: AUME | Q2: AUME | R2: Blue Sun | S2: Dalia | T2: Pop Arabia | U2: Zeplin | V2: CMRRA | W2: MLC | X2: SADAIC | Y2: Latin Autor (Processed by BO) | Z2: ABRAMUS | AA2: Latin Autor (Processed by BO) | AB2: Latin Autor (Processed by BO) | AC2: Latin Autor (Processed by BO) | AD2: Latin Autor (Processed by BO) | AE2: SACM | AF2: Latin Autor (Processed by BO) | AG2: Latin Autor (Processed by BO) | AH2: Latin Autor (Processed by BO) | AI2: APRA-AMCOS | AJ2: APRA-AMCOS | AK2: MCSC | AL2: CASH | AM2: IPRS | AN2: JASRAC | AO2: MACP | AP2: COMPASS | AQ2: COMPASS | AR2: COMPASS | AS2: COMPASS | AT2: KOMCA | AU2: WAMI | AV2: MUST | AW2: CAPASSO | AX2: AKM
A3: BUMA | B3: Licensor Pays | C3: BUMA | D3: BUMA | E3: BUMA | F3: BUMA | G3: BUMA | H3: BUMA | I3: BUMA | J3: BUMA | K3: BUMA | L3: BUMA | M3: BUMA | N3: BUMA | O3: BUMA | P3: BUMA | Q3: BUMA | R3: Blue Sun | S3: Dalia | T3: Pop Arabia | U3: Zeplin | V3: CMRRA | W3: MLC | X3: SADAIC | Y3: Latin Autor (Processed by BO) | Z3: ABRAMUS | AA3: Latin Autor (Processed by BO) | AB3: Latin Autor (Processed by BO) | AC3: Latin Autor (Processed by BO) | AD3: Latin Autor (Processed by BO) | AE3: SACM | AF3: Latin Autor (Processed by BO) | AG3: Latin Autor (Processed by BO) | AH3: Latin Autor (Processed by BO) | AI3: APRA-AMCOS | AJ3: APRA-AMCOS | AK3: QUERY SOURCE/ TERR OWNER | AL3: BUMA | AM3: BUMA | AN3: BUMA | AO3: BUMA | AP3: BUMA | AQ3: BUMA | AR3: BUMA | AS3: BUMA | AT3: KOMCA | AU3: BUMA | AV3: BUMA | AW3: CAPASSO | AX3: BUMA
A4: GEMA | B4: Licensor Pays | C4: GEMA | D4: GEMA | E4: GEMA | F4: GEMA | G4: GEMA | H4: GEMA | I4: GEMA | J4: GEMA | K4: GEMA | L4: GEMA | M4: GEMA | N4: GEMA | O4: GEMA | P4: GEMA | Q4: GEMA | R4: Blue Sun | S4: Dalia | T4: Pop Arabia | U4: Zeplin | V4: CMRRA | W4: MLC | X4: SADAIC | Y4: Latin Autor (Processed by BO) | Z4: ABRAMUS | AA4: Latin Autor (Processed by BO) | AB4: Latin Autor (Processed by BO) | AC4: Latin Autor (Processed by BO) | AD4: Latin Autor (Processed by BO) | AE4: SACM | AF4: Latin Autor (Processed by BO) | AG4: Latin Autor (Processed by BO) | AH4: Latin Autor (Processed by BO) | AI4: APRA-AMCOS | AJ4: APRA-AMCOS | AK4: MCSC | AL4: CASH | AM4: IPRS | AN4: JASRAC | AO4: MACP | AP4: COMPASS | AQ4: COMPASS | AR4: COMPASS | AS4: COMPASS | AT4: KOMCA | AU4: WAMI | AV4: MUST | AW4: CAPASSO | AX4: GEMA
A5: SABAM | B5: Licensor Pays | C5: SABAM | D5: SABAM | E5: SABAM | F5: SABAM | G5: SABAM | H5: SABAM | I5: SABAM | J5: SABAM | K5: SABAM | L5: SABAM | M5: SABAM | N5: SABAM | O5: SABAM | P5: SABAM | Q5: SABAM | R5: Blue Sun | S5: Dalia | T5: Pop Arabia | U5: Zeplin | V5: CMRRA | W5: MLC | X5: SADAIC | Y5: Latin Autor (Processed by BO) | Z5: ABRAMUS | AA5: Latin Autor (Processed by BO) | AB5: Latin Autor (Processed by BO) | AC5: Latin Autor (Processed by BO) | AD5: Latin Autor (Processed by BO) | AE5: SACM | AF5: Latin Autor (Processed by BO) | AG5: Latin Autor (Processed by BO) | AH5: Latin Autor (Processed by BO) | AI5: APRA-AMCOS | AJ5: APRA-AMCOS | AK5: QUERY SOURCE/ TERR OWNER | AL5: CASH | AM5: QUERY SOURCE/ TERR OWNER | AN5: JASRAC | AO5: MACP | AP5: QUERY SOURCE/ TERR OWNER | AQ5: QUERY SOURCE/ TERR OWNER | AR5: QUERY SOURCE/ TERR OWNER | AS5: QUERY SOURCE/ TERR OWNER | AT5: KOMCA | AU5: QUERY SOURCE/ TERR OWNER | AV5: MUST | AW5: CAPASSO | AX5: SABAM
A6: SACEM | B6: Licensor Pays | C6: SACEM | D6: SACEM | E6: SACEM | F6: SACEM | G6: SACEM | H6: SACEM | I6: SACEM | J6: SACEM | K6: SACEM | L6: SACEM | M6: SACEM | N6: SACEM | O6: SACEM | P6: SACEM | Q6: SACEM | R6: Blue Sun | S6: Dalia | T6: Pop Arabia | U6: Zeplin | V6: CMRRA | W6: MLC | X6: SADAIC | Y6: Latin Autor (Processed by BO) | Z6: ABRAMUS | AA6: Latin Autor (Processed by BO) | AB6: Latin Autor (Processed by BO) | AC6: Latin Autor (Processed by BO) | AD6: Latin Autor (Processed by BO) | AE6: SACM | AF6: Latin Autor (Processed by BO) | AG6: Latin Autor (Processed by BO) | AH6: Latin Autor (Processed by BO) | AI6: APRA-AMCOS | AJ6: APRA-AMCOS | AK6: QUERY SOURCE/ TERR OWNER | AL6: QUERY SOURCE/ TERR OWNER | AM6: QUERY SOURCE/ TERR OWNER | AN6: QUERY SOURCE/ TERR OWNER | AO6: QUERY SOURCE/ TERR OWNER | AP6: QUERY SOURCE/ TERR OWNER | AQ6: QUERY SOURCE/ TERR OWNER | AR6: QUERY SOURCE/ TERR OWNER | AS6: QUERY SOURCE/ TERR OWNER | AT6: KOMCA | AU6: QUERY SOURCE/ TERR OWNER | AV6: QUERY SOURCE/ TERR OWNER | AW6: CAPASSO | AX6: SACEM
A7: SGAE | B7: Licensor Pays | C7: SGAE | D7: SGAE | E7: SGAE | F7: SGAE | G7: SGAE | H7: SGAE | I7: SGAE | J7: SGAE | K7: SGAE | L7: SGAE | M7: SGAE | N7: SGAE | O7: SGAE | P7: SGAE | Q7: SGAE | R7: Blue Sun | S7: Dalia | T7: Pop Arabia | U7: Zeplin | V7: CMRRA | W7: MLC | X7: SADAIC | Y7: Latin Autor (Processed by BO) | Z7: ABRAMUS | AA7: Latin Autor (Processed by BO) | AB7: Latin Autor (Processed by BO) | AC7: Latin Autor (Processed by BO) | AD7: Latin Autor (Processed by BO) | AE7: SACM | AF7: Latin Autor (Processed by BO) | AG7: Latin Autor (Processed by BO) | AH7: Latin Autor (Processed by BO) | AI7: APRA-AMCOS | AJ7: APRA-AMCOS | AK7: QUERY SOURCE/ TERR OWNER | AL7: QUERY SOURCE/ TERR OWNER | AM7: QUERY SOURCE/ TERR OWNER | AN7: QUERY SOURCE/ TERR OWNER | AO7: QUERY SOURCE/ TERR OWNER | AP7: QUERY SOURCE/ TERR OWNER | AQ7: QUERY SOURCE/ TERR OWNER | AR7: QUERY SOURCE/ TERR OWNER | AS7: QUERY SOURCE/ TERR OWNER | AT7: KOMCA | AU7: QUERY SOURCE/ TERR OWNER | AV7: QUERY SOURCE/ TERR OWNER | AW7: CAPASSO | AX7: QUERY SOURCE/ TERR OWNER
A8: SIAE | B8: Licensor Pays | C8: NOT LICENSED | D8: NOT LICENSED | E8: NOT LICENSED | F8: NOT LICENSED | G8: NOT LICENSED | H8: NOT LICENSED | I8: NOT LICENSED | J8: NOT LICENSED | K8: NOT LICENSED | L8: NOT LICENSED | M8: NOT LICENSED | N8: NOT LICENSED | O8: QUERY SOURCE/ TERR OWNER | P8: QUERY SOURCE/ TERR OWNER | Q8: QUERY SOURCE/ TERR OWNER | R8: Blue Sun | S8: Dalia | T8: Pop Arabia | U8: Zeplin | V8: CMRRA | W8: MLC | X8: SADAIC | Y8: Latin Autor (Processed by BO) | Z8: ABRAMUS | AA8: Latin Autor (Processed by BO) | AB8: Latin Autor (Processed by BO) | AC8: Latin Autor (Processed by BO) | AD8: Latin Autor (Processed by BO) | AE8: SACM | AF8: Latin Autor (Processed by BO) | AG8: Latin Autor (Processed by BO) | AH8: Latin Autor (Processed by BO) | AI8: APRA-AMCOS | AJ8: APRA-AMCOS | AK8: QUERY SOURCE/ TERR OWNER | AL8: QUERY SOURCE/ TERR OWNER | AM8: QUERY SOURCE/ TERR OWNER | AN8: QUERY SOURCE/ TERR OWNER | AO8: QUERY SOURCE/ TERR OWNER | AP8: QUERY SOURCE/ TERR OWNER | AQ8: QUERY SOURCE/ TERR OWNER | AR8: QUERY SOURCE/ TERR OWNER | AS8: QUERY SOURCE/ TERR OWNER | AT8: KOMCA | AU8: QUERY SOURCE/ TERR OWNER | AV8: QUERY SOURCE/ TERR OWNER | AW8: CAPASSO | AX8: QUERY SOURCE/ TERR OWNER
A9: SPA | B9: Licensor Pays | C9: SPA | D9: SPA | E9: SPA | F9: SPA | G9: SPA | H9: SPA | I9: SPA | J9: SPA | K9: SPA | L9: SPA | M9: SPA | N9: SPA | O9: SPA | P9: SPA | Q9: SPA | R9: Blue Sun | S9: Dalia | T9: Pop Arabia | U9: Zeplin | V9: CMRRA | W9: MLC | X9: SADAIC | Y9: Latin Autor (Processed by BO) | Z9: ABRAMUS | AA9: Latin Autor (Processed by BO) | AB9: Latin Autor (Processed by BO) | AC9: Latin Autor (Processed by BO) | AD9: Latin Autor (Processed by BO) | AE9: SACM | AF9: Latin Autor (Processed by BO) | AG9: Latin Autor (Processed by BO) | AH9: Latin Autor (Processed by BO) | AI9: APRA-AMCOS | AJ9: APRA-AMCOS | AK9: QUERY SOURCE/ TERR OWNER | AL9: QUERY SOURCE/ TERR OWNER | AM9: QUERY SOURCE/ TERR OWNER | AN9: QUERY SOURCE/ TERR OWNER | AO9: QUERY SOURCE/ TERR OWNER | AP9: QUERY SOURCE/ TERR OWNER | AQ9: QUERY SOURCE/ TERR OWNER | AR9: QUERY SOURCE/ TERR OWNER | AS9: QUERY SOURCE/ TERR OWNER | AT9: KOMCA | AU9: QUERY SOURCE/ TERR OWNER | AV9: QUERY SOURCE/ TERR OWNER | AW9: CAPASSO | AX9: QUERY SOURCE/ TERR OWNER
A10: STIM-NCB | B10: Licensor Pays | C10: STIM | D10: STIM | E10: STIM | F10: STIM | G10: STIM | H10: STIM | I10: STIM | J10: STIM | K10: STIM | L10: STIM | M10: STIM | N10: STIM | O10: STIM | P10: STIM | Q10: STIM | R10: Blue Sun | S10: Dalia | T10: Pop Arabia | U10: Zeplin | V10: CMRRA | W10: MLC | X10: SADAIC | Y10: Latin Autor (Processed by BO) | Z10: ABRAMUS | AA10: Latin Autor (Processed by BO) | AB10: Latin Autor (Processed by BO) | AC10: Latin Autor (Processed by BO) | AD10: Latin Autor (Processed by BO) | AE10: SACM | AF10: Latin Autor (Processed by BO) | AG10: Latin Autor (Processed by BO) | AH10: Latin Autor (Processed by BO) | AI10: APRA-AMCOS | AJ10: APRA-AMCOS | AK10: STIM | AL10: STIM | AM10: STIM | AN10: STIM | AO10: STIM | AP10: STIM | AQ10: STIM | AR10: STIM | AS10: STIM | AT10: STIM | AU10: STIM | AV10: STIM | AW10: CAPASSO | AX10: STIM
A11: SUISA | B11: Licensor Pays | C11: SUISA | D11: SUISA | E11: SUISA | F11: SUISA | G11: SUISA | H11: SUISA | I11: SUISA | J11: SUISA | K11: SUISA | L11: SUISA | M11: SUISA | N11: SUISA | O11: SUISA | P11: SUISA | Q11: SUISA | R11: Blue Sun | S11: Dalia | T11: Pop Arabia | U11: Zeplin | V11: CMRRA | W11: MLC | X11: SADAIC | Y11: Latin Autor (Processed by BO) | Z11: ABRAMUS | AA11: Latin Autor (Processed by BO) | AB11: Latin Autor (Processed by BO) | AC11: Latin Autor (Processed by BO) | AD11: Latin Autor (Processed by BO) | AE11: SACM | AF11: Latin Autor (Processed by BO) | AG11: Latin Autor (Processed by BO) | AH11: Latin Autor (Processed by BO) | AI11: APRA-AMCOS | AJ11: APRA-AMCOS | AK11: QUERY SOURCE/ TERR OWNER | AL11: CASH | AM11: QUERY SOURCE/ TERR OWNER | AN11: QUERY SOURCE/ TERR OWNER | AO11: QUERY SOURCE/ TERR OWNER | AP11: QUERY SOURCE/ TERR OWNER | AQ11: QUERY SOURCE/ TERR OWNER | AR11: QUERY SOURCE/ TERR OWNER | AS11: QUERY SOURCE/ TERR OWNER | AT11: QUERY SOURCE/ TERR OWNER | AU11: QUERY SOURCE/ TERR OWNER | AV11: QUERY SOURCE/ TERR OWNER | AW11: CAPASSO | AX11: QUERY SOURCE/ TERR OWNER
A13: AMRA | B13: Licensor Pays | C13: AMRA | D13: AMRA | E13: AMRA | F13: AMRA | G13: AMRA | H13: AMRA | I13: AMRA | J13: AMRA | K13: AMRA | L13: AMRA | M13: AMRA | N13: AMRA | O13: AMRA | P13: AMRA | Q13: AMRA | R13: AMRA | S13: AMRA | T13: AMRA | U13: AMRA | V13: AMRA | W13: MLC | X13: SADAIC | Y13: Latin Autor (Processed by BO) | Z13: AMRA | AA13: Latin Autor (Processed by BO) | AB13: Latin Autor (Processed by BO) | AC13: Latin Autor (Processed by BO) | AD13: Latin Autor (Processed by BO) | AE13: SACM | AF13: Latin Autor (Processed by BO) | AG13: Latin Autor (Processed by BO) | AH13: Latin Autor (Processed by BO) | AI13: AMRA | AJ13: AMRA | AK13: AMRA | AL13: AMRA | AM13: AMRA | AN13: AMRA | AO13: AMRA | AP13: AMRA | AQ13: AMRA | AR13: AMRA | AS13: AMRA | AT13: KOMCA | AU13: AMRA | AV13: AMRA | AW13: AMRA | AX13: AMRA
A14: APRA-AMCOS | B14: Licensor Pays | C14: AMRA | D14: AMRA | E14: AMRA | F14: AMRA | G14: AMRA | H14: AMRA | I14: AMRA | J14: AMRA | K14: AMRA | L14: AMRA | M14: AMRA | N14: AMRA | O14: AMRA | P14: AMRA | Q14: AMRA | R14: AMRA | S14: AMRA | T14: AMRA | U14: AMRA | V14: AMRA | W14: MLC | X14: SADAIC | Y14: Latin Autor | Z14: AMRA | AA14: Latin Autor | AB14: Latin Autor | AC14: Latin Autor | AD14: Latin Autor | AE14: SACM | AF14: Latin Autor | AG14: Latin Autor | AH14: Latin Autor | AI14: AMRA | AJ14: AMRA | AK14: AMRA | AL14: AMRA | AM14: AMRA | AN14: AMRA | AO14: AMRA | AP14: AMRA | AQ14: AMRA | AR14: AMRA | AS14: AMRA | AT14: KOMCA | AU14: AMRA | AV14: AMRA | AW14: AMRA | AX14: AMRA
... A35: Non-Society | B35: Licensor Pays | C35: AMRA | D35: AMRA | E35: AMRA | F35: AMRA | G35: AMRA | H35: AMRA | I35: AMRA | J35: AMRA | K35: AMRA | L35: AMRA | M35: AMRA | N35: AMRA | O35: AMRA | P35: AMRA | Q35: AMRA | R35: AMRA | S35: AMRA | T35: AMRA | U35: AMRA | V35: CMRRA | W35: MLC | X35: SADAIC | Y35: Latin Autor | Z35: AMRA | AA35: Latin Autor | AB35: Latin Autor | AC35: Latin Autor | AD35: Latin Autor | AE35: SACM | AF35: Latin Autor | AG35: Latin Autor | AH35: Latin Autor | AI35: APRA-AMCOS | AJ35: APRA-AMCOS | AK35: AMRA | AL35: AMRA | AM35: AMRA | AN35: AMRA | AO35: AMRA | AP35: AMRA | AQ35: AMRA | AR35: AMRA | AS35: AMRA | AT35: KOMCA | AU35: AMRA | AV35: AMRA | AW35: CAPASSO | AX35: AMRA

Sheet MECH - Licensed By
A1: SOCIETY | C1: Austria | D1: Belgium | E1: France | F1: Germany | G1: Italy | H1: Netherlands | I1: Nordics Finland / Norway / Iceland, etc) | J1: Portugal | K1: Spain | L1: Sweden | M1: Switzerland | N1: United Kingdom | O1: Croatia | P1: Greece | Q1: Poland | R1: Russia | S1: Israel | T1: UAE | U1: Turkey | V1: Canada | W1: United States | X1: Argentina | Y1: Bolivia | Z1: Brazil | AA1: Chile | AB1: Colombia | AC1: Costa Rica | AD1: Ecuador | AE1: Mexico | AF1: Paraguay | AG1: Peru | AH1: Uruguay | AI1: Australia | AJ1: New Zealand | AK1: China | AL1: HongKong | AM1: India | AN1: Japan | AO1: Malaysia | AP1: Philippines | AQ1: Vietnam | AR1: Thailand | AS1: Singapore | AT1: South Korea | AU1: Indonesia | AV1: Taiwan | AW1: South Africa | AX1: North Africa
A2: AKM-AUME | B2: Licensed By | C2: ICE | D2: ICE | E2: ICE | F2: ICE | G2: ICE | H2: ICE | I2: ICE | J2: ICE | K2: ICE | L2: ICE | M2: ICE | N2: ICE | O2: ICE | P2: ICE | Q2: ICE | R2: RAO | S2: ACUM | T2: ESMAA | U2: MSG | V2: CMRRA | W2: MLC | X2: SADAIC | Y2: Latin Autor | Z2: ABRAMUS | AA2: Latin Autor | AB2: Latin Autor | AC2: Latin Autor | AD2: Latin Autor | AE2: SACM | AF2: Latin Autor | AG2: Latin Autor | AH2: Latin Autor | AI2: APRA-AMCOS | AJ2: APRA-AMCOS | AK2: MCSC | AL2: CASH | AM2: IPRS | AN2: JASRAC | AO2: MACP | AP2: COMPASS | AQ2: COMPASS | AR2: COMPASS | AS2: COMPASS | AT2: KOMCA | AU2: WAMI | AV2: MUST | AW2: CAPASSO | AX2: ICE
A3: BUMA | B3: Licensed By | C3: ICE | D3: ICE | E3: ICE | F3: ICE | G3: ICE | H3: ICE | I3: ICE | J3: ICE | K3: ICE | L3: ICE | M3: ICE | N3: ICE | O3: ICE | P3: ICE | Q3: ICE | R3: RAO | S3: ACUM | T3: ESMAA | U3: MSG | V3: CMRRA | W3: MLC | X3: SADAIC | Y3: Latin Autor | Z3: ABRAMUS | AA3: Latin Autor | AB3: Latin Autor | AC3: Latin Autor | AD3: Latin Autor | AE3: SACM | AF3: Latin Autor | AG3: Latin Autor | AH3: Latin Autor | AI3: APRA-AMCOS | AJ3: APRA-AMCOS | AK3: QUERY SOURCE/ TERR OWNER | AL3: APRA-AMCOS | AM3: APRA-AMCOS | AN3: APRA-AMCOS | AO3: APRA-AMCOS | AP3: APRA-AMCOS | AQ3: APRA-AMCOS | AR3: APRA-AMCOS | AS3: APRA-AMCOS | AT3: KOMCA | AU3: APRA-AMCOS | AV3: APRA-AMCOS | AW3: CAPASSO | AX3: ICE
A4: GEMA | B4: Licensed By | C4: ICE | D4: ICE | E4: ICE | F4: GEMA | G4: ICE | H4: ICE | I4: ICE | J4: ICE | K4: ICE | L4: ICE | M4: ICE | N4: ICE | O4: ICE | P4: ICE | Q4: ICE | R4: RAO | S4: ACUM | T4: ESMAA | U4: MSG | V4: CMRRA | W4: MLC | X4: SADAIC | Y4: Latin Autor | Z4: ABRAMUS | AA4: Latin Autor | AB4: Latin Autor | AC4: Latin Autor | AD4: Latin Autor | AE4: SACM | AF4: Latin Autor | AG4: Latin Autor | AH4: Latin Autor | AI4: APRA-AMCOS | AJ4: APRA-AMCOS | AK4: MCSC | AL4: CASH | AM4: IPRS | AN4: JASRAC | AO4: MACP | AP4: COMPASS | AQ4: COMPASS | AR4: COMPASS | AS4: COMPASS | AT4: KOMCA | AU4: WAMI | AV4: MUST | AW4: CAPASSO | AX4: ICE
A5: SABAM | B5: Licensed By | C5: ICE | D5: ICE | E5: ICE | F5: ICE | G5: ICE | H5: ICE | I5: ICE | J5: ICE | K5: ICE | L5: ICE | M5: ICE | N5: ICE | O5: ICE | P5: ICE | Q5: ICE | R5: RAO | S5: ACUM | T5: ESMAA | U5: MSG | V5: CMRRA | W5: MLC | X5: SADAIC | Y5: Latin Autor | Z5: ABRAMUS | AA5: Latin Autor | AB5: Latin Autor | AC5: Latin Autor | AD5: Latin Autor | AE5: SACM | AF5: Latin Autor | AG5: Latin Autor | AH5: Latin Autor | AI5: APRA-AMCOS | AJ5: APRA-AMCOS | AK5: QUERY SOURCE/ TERR OWNER | AL5: CASH | AM5: QUERY SOURCE/ TERR OWNER | AN5: JASRAC | AO5: MACP | AP5: QUERY SOURCE/ TERR OWNER | AQ5: QUERY SOURCE/ TERR OWNER | AR5: QUERY SOURCE/ TERR OWNER | AS5: QUERY SOURCE/ TERR OWNER | AT5: KOMCA | AU5: QUERY SOURCE/ TERR OWNER | AV5: MUST | AW5: CAPASSO | AX5: ICE
A6: SACEM | B6: Licensed By | C6: SACEM | D6: SACEM | E6: SACEM | F6: SACEM | G6: SACEM | H6: SACEM | I6: SACEM | J6: SACEM | K6: SACEM | L6: SACEM | M6: SACEM | N6: SACEM | O6: SACEM | P6: SACEM | Q6: SACEM | R6: RAO | S6: ACUM | T6: ESMAA | U6: MSG | V6: CMRRA | W6: MLC | X6: SADAIC | Y6: Latin Autor | Z6: ABRAMUS | AA6: Latin Autor | AB6: Latin Autor | AC6: Latin Autor | AD6: Latin Autor | AE6: SACM | AF6: Latin Autor | AG6: Latin Autor | AH6: Latin Autor | AI6: APRA-AMCOS | AJ6: APRA-AMCOS | AK6: QUERY SOURCE/ TERR OWNER | AL6: QUERY SOURCE/ TERR OWNER | AM6: QUERY SOURCE/ TERR OWNER | AN6: QUERY SOURCE/ TERR OWNER | AO6: QUERY SOURCE/ TERR OWNER | AP6: QUERY SOURCE/ TERR OWNER | AQ6: QUERY SOURCE/ TERR OWNER | AR6: QUERY SOURCE/ TERR OWNER | AS6: QUERY SOURCE/ TERR OWNER | AT6: KOMCA | AU6: QUERY SOURCE/ TERR OWNER | AV6: QUERY SOURCE/ TERR OWNER | AW6: CAPASSO | AX6: SACEM
A7: SGAE | B7: Licensed By | C7: SGAE | D7: SGAE | E7: SGAE | F7: SGAE | G7: SGAE | H7: SGAE | I7: SGAE | J7: SGAE | K7: SGAE | L7: SGAE | M7: SGAE | N7: SGAE | O7: SGAE | P7: SGAE | Q7: SGAE | R7: RAO | S7: ACUM | T7: ESMAA | U7: MSG | V7: CMRRA | W7: MLC | X7: SADAIC | Y7: Latin Autor | Z7: ABRAMUS | AA7: Latin Autor | AB7: Latin Autor | AC7: Latin Autor | AD7: Latin Autor | AE7: SACM | AF7: Latin Autor | AG7: Latin Autor | AH7: Latin Autor | AI7: APRA-AMCOS | AJ7: APRA-AMCOS | AK7: QUERY SOURCE/ TERR OWNER | AL7: QUERY SOURCE/ TERR OWNER | AM7: QUERY SOURCE/ TERR OWNER | AN7: QUERY SOURCE/ TERR OWNER | AO7: QUERY SOURCE/ TERR OWNER | AP7: QUERY SOURCE/ TERR OWNER | AQ7: QUERY SOURCE/ TERR OWNER | AR7: QUERY SOURCE/ TERR OWNER | AS7: QUERY SOURCE/ TERR OWNER | AT7: KOMCA | AU7: QUERY SOURCE/ TERR OWNER | AV7: QUERY SOURCE/ TERR OWNER | AW7: CAPASSO | AX7: QUERY SOURCE/ TERR OWNER
A8: SIAE | B8: Licensed By | C8: NOT LICENSED | D8: NOT LICENSED | E8: NOT LICENSED | F8: NOT LICENSED | G8: NOT LICENSED | H8: NOT LICENSED | I8: NOT LICENSED | J8: NOT LICENSED | K8: NOT LICENSED | L8: NOT LICENSED | M8: NOT LICENSED | N8: NOT LICENSED | O8: QUERY SOURCE/ TERR OWNER | P8: QUERY SOURCE/ TERR OWNER | Q8: QUERY SOURCE/ TERR OWNER | R8: RAO | S8: ACUM | T8: ESMAA | U8: MSG | V8: CMRRA | W8: MLC | X8: SADAIC | Y8: Latin Autor | Z8: ABRAMUS | AA8: Latin Autor | AB8: Latin Autor | AC8: Latin Autor | AD8: Latin Autor | AE8: SACM | AF8: Latin Autor | AG8: Latin Autor | AH8: Latin Autor | AI8: APRA-AMCOS | AJ8: APRA-AMCOS | AK8: QUERY SOURCE/ TERR OWNER | AL8: QUERY SOURCE/ TERR OWNER | AM8: QUERY SOURCE/ TERR OWNER | AN8: QUERY SOURCE/ TERR OWNER | AO8: QUERY SOURCE/ TERR OWNER | AP8: QUERY SOURCE/ TERR OWNER | AQ8: QUERY SOURCE/ TERR OWNER | AR8: QUERY SOURCE/ TERR OWNER | AS8: QUERY SOURCE/ TERR OWNER | AT8: KOMCA | AU8: QUERY SOURCE/ TERR OWNER | AV8: QUERY SOURCE/ TERR OWNER | AW8: CAPASSO | AX8: QUERY SOURCE/ TERR OWNER
A9: SPA | B9: Licensed By | C9: SPA | D9: SPA | E9: SPA | F9: SPA | G9: SPA | H9: SPA | I9: SPA | J9: SPA | K9: SPA | L9: SPA | M9: SPA | N9: SPA | O9: SPA | P9: SPA | Q9: SPA | R9: RAO | S9: ACUM | T9: ESMAA | U9: MSG | V9: CMRRA | W9: MLC | X9: SADAIC | Y9: Latin Autor | Z9: ABRAMUS | AA9: Latin Autor | AB9: Latin Autor | AC9: Latin Autor | AD9: Latin Autor | AE9: SACM | AF9: Latin Autor | AG9: Latin Autor | AH9: Latin Autor | AI9: APRA-AMCOS | AJ9: APRA-AMCOS | AK9: QUERY SOURCE/ TERR OWNER | AL9: QUERY SOURCE/ TERR OWNER | AM9: QUERY SOURCE/ TERR OWNER | AN9: QUERY SOURCE/ TERR OWNER | AO9: QUERY SOURCE/ TERR OWNER | AP9: QUERY SOURCE/ TERR OWNER | AQ9: QUERY SOURCE/ TERR OWNER | AR9: QUERY SOURCE/ TERR OWNER | AS9: QUERY SOURCE/ TERR OWNER | AT9: KOMCA | AU9: QUERY SOURCE/ TERR OWNER | AV9: QUERY SOURCE/ TERR OWNER | AW9: CAPASSO | AX9: QUERY SOURCE/ TERR OWNER
A10: STIM-NCB | B10: Licensed By | C10: ICE | D10: ICE | E10: ICE | F10: ICE | G10: ICE | H10: ICE | I10: ICE | J10: ICE | K10: ICE | L10: ICE | M10: ICE | N10: ICE | O10: ICE | P10: ICE | Q10: ICE | R10: RAO | S10: ACUM | T10: ESMAA | U10: MSG | V10: CMRRA | W10: MLC | X10: SADAIC | Y10: Latin Autor | Z10: ABRAMUS | AA10: Latin Autor | AB10: Latin Autor | AC10: Latin Autor | AD10: Latin Autor | AE10: SACM | AF10: Latin Autor | AG10: Latin Autor | AH10: Latin Autor | AI10: APRA-AMCOS | AJ10: APRA-AMCOS | AK10: APRA-AMCOS | AL10: APRA-AMCOS | AM10: APRA-AMCOS | AN10: APRA-AMCOS | AO10: APRA-AMCOS | AP10: APRA-AMCOS | AQ10: APRA-AMCOS | AR10: APRA-AMCOS | AS10: APRA-AMCOS | AT10: APRA-AMCOS | AU10: APRA-AMCOS | AV10: APRA-AMCOS | AW10: CAPASSO | AX10: ICE
A11: SUISA | B11: Licensed By | C11: MINT | D11: MINT | E11: MINT | F11: MINT | G11: MINT | H11: MINT | I11: MINT | J11: MINT | K11: MINT | L11: MINT | M11: SUISA | N11: MINT | O11: MINT | P11: MINT | Q11: MINT | R11: RAO | S11: ACUM | T11: ESMAA | U11: MSG | V11: CMRRA | W11: MLC | X11: SADAIC | Y11: Latin Autor | Z11: ABRAMUS | AA11: Latin Autor | AB11: Latin Autor | AC11: Latin Autor | AD11: Latin Autor | AE11: SACM | AF11: Latin Autor | AG11: Latin Autor | AH11: Latin Autor | AI11: APRA-AMCOS | AJ11: APRA-AMCOS | AK11: QUERY SOURCE/ TERR OWNER | AL11: CASH | AM11: QUERY SOURCE/ TERR OWNER | AN11: QUERY SOURCE/ TERR OWNER | AO11: QUERY SOURCE/ TERR OWNER | AP11: QUERY SOURCE/ TERR OWNER | AQ11: QUERY SOURCE/ TERR OWNER | AR11: QUERY SOURCE/ TERR OWNER | AS11: QUERY SOURCE/ TERR OWNER | AT11: QUERY SOURCE/ TERR OWNER | AU11: QUERY SOURCE/ TERR OWNER | AV11: QUERY SOURCE/ TERR OWNER | AW11: CAPASSO | AX11: QUERY SOURCE/ TERR OWNER
A13: AMRA | B13: Licensed By | C13: AMRA | D13: AMRA | E13: AMRA | F13: AMRA | G13: AMRA | H13: AMRA | I13: AMRA | J13: AMRA | K13: AMRA | L13: AMRA | M13: AMRA | N13: AMRA | O13: AMRA | P13: AMRA | Q13: AMRA | R13: AMRA | S13: AMRA | T13: AMRA | U13: AMRA | V13: AMRA | W13: MLC | X13: SADAIC | Y13: Latin Autor | Z13: AMRA | AA13: Latin Autor | AB13: Latin Autor | AC13: Latin Autor | AD13: Latin Autor | AE13: SACM | AF13: Latin Autor | AG13: Latin Autor | AH13: Latin Autor | AI13: AMRA | AJ13: AMRA | AK13: AMRA | AL13: AMRA | AM13: AMRA | AN13: AMRA | AO13: AMRA | AP13: AMRA | AQ13: AMRA | AR13: AMRA | AS13: AMRA | AT13: KOMCA | AU13: AMRA | AV13: AMRA | AW13: AMRA | AX13: AMRA
A14: APRA-AMCOS | B14: Licensed By | C14: AMRA | D14: AMRA | E14: AMRA | F14: AMRA | G14: AMRA | H14: AMRA | I14: AMRA | J14: AMRA | K14: AMRA | L14: AMRA | M14: AMRA | N14: AMRA | O14: AMRA | P14: AMRA | Q14: AMRA | R14: AMRA | S14: AMRA | T14: AMRA | U14: AMRA | V14: AMRA | W14: MLC | X14: SADAIC | Y14: Latin Autor | Z14: AMRA | AA14: Latin Autor | AB14: Latin Autor | AC14: Latin Autor | AD14: Latin Autor | AE14: SACM | AF14: Latin Autor | AG14: Latin Autor | AH14: Latin Autor | AI14: AMRA | AJ14: AMRA | AK14: AMRA | AL14: AMRA | AM14: AMRA | AN14: AMRA | AO14: AMRA | AP14: AMRA | AQ14: AMRA | AR14: AMRA | AS14: AMRA | AT14: KOMCA | AU14: AMRA | AV14: AMRA | AW14: AMRA | AX14: AMRA
... A35: Non-Society | B35: Licensed By | C35: AMRA | D35: AMRA | E35: AMRA | F35: AMRA | G35: AMRA | H35: AMRA | I35: AMRA | J35: AMRA | K35: AMRA | L35: AMRA | M35: AMRA | N35: AMRA | O35: AMRA | P35: AMRA | Q35: AMRA | R35: AMRA | S35: AMRA | T35: AMRA | U35: AMRA | V35: CMRRA | W35: MLC | X35: SADAIC | Y35: Latin Autor | Z35: AMRA | AA35: Latin Autor | AB35: Latin Autor | AC35: Latin Autor | AD35: Latin Autor | AE35: SACM | AF35: Latin Autor | AG35: Latin Autor | AH35: Latin Autor | AI35: APRA-AMCOS | AJ35: APRA-AMCOS | AK35: AMRA | AL35: AMRA | AM35: AMRA | AN35: AMRA | AO35: AMRA | AP35: AMRA | AQ35: AMRA | AR35: AMRA | AS35: AMRA | AT35: KOMCA | AU35: AMRA | AV35: AMRA | AW35: CAPASSO | AX35: AMRA

Sheet Road Map
A1: CURRENT MATRIX
B2: Area | C2: Considerations
A3: 1 | B3: Repertoire | C3: Define repertoire and review what was addes so far
A4: 2 | B4: What should the matrix show? | C4: Gaps / redirections + how it generally works?
A5: 3 | B5: ASIA | C5: Do certain repertoires have a pan-asian agreement in place (like STIM / BUMA with APRA PAL)? If not, can we assume that this income flows via local Asian sources.
A6: 4 | B6: LAT-AM & ASIAN REPERTOIRE | C6: Does this society's repertoire fall under an agreement with another society? (eg. SACM with PRS for Europe) if not, we should check that the source has reciprocal agreement in place in all of the blank territories. If so, they follow local distribution rules
A8: TECHNICAL MATRIX
B9: Area | C9: Considerations
B10: DSP LEVEL RULES | C10: Some sources have different rules per DSP, how do we build this into the matrix?
A12: DASHBOARD NEEDS
B13: Area | C13: Considerations
A14: 1 | B14: TABLEAU | C14: Can the calculator be migrated onto Tableau?
A19: Source | B19: Technical Issue | C19: Detail
A20: APRA-AMCOS | B20: DSP carve outs | C20: AMRA involvement in APAC differs by DSP. AMRA currently only able to distribute disaggregated ANZ income for Spotify, Apple Music, Youtube, Meta, Tiktok. All other AMRA licensed repertoire is distributed to us via APRA-AMCOS.
A21: APRA-AMCOS | B21: DSP Carve outs | C21: Kobalt has direct mechanical licenses with multiple DSPs (e.g. TikTok, Snapchat, Twitch). Income should not be distributed by AMCOS or AMRA.
A22: LatinAutor territories | B22: DSP carve outs | C22: Kobalt paid directly for Latinautor territories for Spotify only
A23: US (All Sources) MECH | B23: DSP carve outs | C23: Meta & TikTok licensed direct to DSP and data received direct from DSP
A24: US (All Sources) PERF | B24: DSP carve outs | C24: Meta & YT perf included within direct licence
A25: ABRAMUS | B25: DSP carve outs | C25: AMRA involvement in Brazil is only for Spotify, YouTube & Meta
A26: HFA | B26: Online and offline | C26: Both pyhsical and Dig download are included
